Workbook
Name block.CH4: #REF!
Name block.CO2: #REF!
Name block.CO2: #REF!
Name block.CO2: #REF!
Name block.CO2: #REF!
Name block.CO2: #REF!
Name block.CO2: #REF!
Name block.Fgas: #REF!
Name block.Fgas: #REF!
Name block.Fgas: #REF!
Name block.Fgas: #REF!
Name block.Fgas: #REF!
Name block.Fgas: #REF!
Name block.N2O: #REF!
Name block.N2O: #REF!
Name block.N2O: #REF!
Name block.N2O: #REF!
Name block.N2O: #REF!
Name block.N2O: #REF!
Name CAAGR_tolerance: 200
Name CO2percap: #REF!
Name CO2percap: #REF!
Name CO2percap: #REF!
Name CO2percap: #REF!
Name CO2percap: #REF!
Name CO2percap: #REF!
Name CO2perUSD_GDP: #REF!
Name CO2perUSD_GDP: #REF!
Name CO2perUSD_GDP: #REF!
Name CO2perUSD_GDP: #REF!
Name CO2perUSD_GDP: #REF!
Name CO2perUSD_GDP: #REF!
Name cost_data_2015: '[2]Input costs 2015'!$A$1:$XX$40
Name costdata_notrade: '[2]Input costs 2014'!$A$4:$I$35
Name countries_dropdownlist: [2]Lookups!$A$12:$A$37
Name country_id: #REF!
Name country_id: #REF!
Name country_id: #REF!
Name country_id: #REF!
Name country_id: #REF!
Name country_id: #REF!
Name country_id: #REF!
Name Deflator_Data: [4]GDPdeflator!$E$5:$BK$268
Name Deflator_ID: [4]GDPdeflator!$BN$5:$BN$268
Name Deflator_Year: [4]GDPdeflator!$E$4:$BL$4
Name EDGAR_Country: '[5]Database Emissions EDGAR_FAO'!$B$5:$B$230
Name EDGAR_head: '[5]Database Emissions EDGAR_FAO'!$D$4:$AE$4
Name EDGAR_table: '[5]Database Emissions EDGAR_FAO'!$D$5:$AE$230
Name fac_gdp: '[6]Emissions per GDP (MER)'!$B$1
Name GDP: '[2]Input Population GDP'!$F$38:$U$71
Name GHG: #REF!
Name GHG: #REF!
Name GHG: #REF!
Name GHG: #REF!
Name GHG: #REF!
Name GHG: #REF!
Name GHGpercap: #REF!
Name GHGpercap: #REF!
Name GHGpercap: #REF!
Name GHGpercap: #REF!

Sheet Stephan
A1: Country Code | B1: Country name | C1: Access to electricity (% of population) | D1: International migrant stock (% of population) | E1: Population, total | F1: Control of Corruption: Estimate | G1: Government Effectiveness: Estimate | H1: Political Stability and Absence of Violence/Terrorism: Estimate | I1: Regulatory Quality: Estimate | J1: Rule of Law: Estimate | K1: Voice and Accountability: Estimate | L1: Renewable electricity output (GWh) [4.1.2_REN.ELECTRICITY.OUTPUT] | M1: Renewable electricity share of total electricity output (%) [4.1_SHARE.RE.IN.ELECTRICITY] | N1: Renewable energy consumption (TJ) [3.1_RE.CONSUMPTION] | O1: Renewable energy share of TFEC (%) [2.1_SHARE.TOTAL.RE.IN.TFEC] | P1: Total electricity output (GWh) [4.1.1_TOTAL.ELECTRICITY.OUTPUT] | Q1: Total final energy consumption (TFEC) (TJ) [1.1_TOTAL.FINAL.ENERGY.CONSUM] | R1: CO2 emissions (metric tons per capita)_x | S1: Electricity production from coal sources (% of total) | T1: Forest area (% of land area) | U1: Methane emissions (metric tons of CO2 equivalent per capita) | V1: Net migration | W1: Nitrous oxide emissions (metric tons of CO2 equivalent per capita) | X1: Population density (people per sq. km of land area) | Y1: Annual deforestation (% of change) - (for online table only) | Z1: Coal rents (% of GDP) | AA1: GDP (constant 2015 US$) | AB1: GDP per capita (constant 2015 US$) | AC1: Natural gas rents (% of GDP) | AD1: Oil rents (% of GDP) | AE1: Arable land (% of land area) | AF1: CO2 emissions by sector (Mt CO2 eq) - Building | AG1: CO2 emissions by sector (Mt CO2 eq) - Industrial Processes | AH1: CO2 emissions by sector (Mt CO2 eq) - Transportation | AI1: GHG growth (annual %) | AJ1: Non-CO2 GHG emissions by sector (Mt CO2 eq) - Agriculture | AK1: Non-CO2 GHG emissions by sector (Mt CO2 eq) - Industrial Processes | AL1: Per capita GHG emissions (tons/capita) | AM1: Total GHG emissions by sector (Mt CO2 eq) - Agriculture | AN1: Total GHG emissions by sector (Mt CO2 eq) - Building | AO1: Total GHG emissions by sector (Mt CO2 eq) - Industrial Processes | AP1: Total GHG emissions by sector (Mt CO2 eq) - Transportation | AQ1: Expected Years of Schooling | AR1: Gross National Income (GNI) per capita | AS1: Human Development Index (HDI) | AT1: Life Expectancy | AU1: Mean Years of Schooling | AV1: INFORM Risk Index | AW1: Total GHG Emissions | AX1: TREND_GDP (constant 2015 US$) | AY1: TREND_Mean Years of Schooling | AZ1: TREND_Population density (people per sq. km of land area) | BA1: TREND_Population, total | BB1: Avg reduction percentage from 2022 | BC1: Peaked | BD1: Per capita GHG emissions | BE1: Current Policies (2021 - 2030) | BF1: Residual emissions as % 2021 emissions | BG1: Net-zero target status
A2: ARE | B2: =VLOOKUP($A2,'NZ targets'!$G$13:$BG$238,2,FALSE) -> United Arab Emirates | C2: 100 | D2: 88.404048 | E2: 9441129 | F2: 1.1553365 | G2: 1.2999623 | H2: 0.70078534 | I2: 1.0347807 | J2: 0.83664274 | K2: -1.1272526 | L2: 296 | M2: 0.23240111 | N2: 2869.892 | O2: 0.13710805 | P2: 127366 | Q2: 2093160.9 | R2: 20.252272 | S2: 0 | T2: 4.4677556 | U2: 6.1314669 | V2: -2762 | W2: 0.1970047 | X2: 131.86631 | Y2: -0.26595883 | Z2: 0 | AA2: 3.7086607e+11 | AB2: 37497.581 | AC2: 0.43164407 | AD2: 11.512162 | AE2: 0.68994649 | AF2: 0.8 | AG2: 5.59 | AH2: 37.67 | AI2: -2.44 | AJ2: 2.04 | AK2: 2.87 | AL2: 27.33 | AM2: 2.04 | AN2: 0.8 | AO2: 8.45 | AP2: 37.67 | AQ2: 15.71769 | AR2: 62573.592 | AS2: 0.911 | AT2: 78.7104 | AU2: 12.69403 | AV2: 1.7 | AW2: 295.11026 | AX2: 9.9982192e+09 | AY2: 0.3441696 | AZ2: 1.0813899 | BA2: 75660.006 | BB2: -2.3255814 | BC2: 1 | BD2: =VLOOKUP($A2,'NZ targets'!$G$13:$BG$238,33,FALSE) -> -0.026916159 | BE2: =VLOOKUP($A2,'NZ targets'!$G$13:$BG$238,18,FALSE) -> -13 | BF2: =VLOOKUP($A2,'NZ targets'!$G$13:$BG$238,25,FALSE) -> -8.279541 | BG2: =VLOOKUP($A2,'NZ targets'!$G$13:$BG$238,3,FALSE) -> 3
A3: AUS | B3: =VLOOKUP($A3,'NZ targets'!$G$13:$BG$238,2,FALSE) -> Australia | C3: 100 | D3: 28.21841 | E3: 26005540 | F3: 1.7644895 | G3: 1.5288746 | H3: 0.93357205 | I3: 1.8948933 | J3: 1.5100852 | K3: 1.3194804 | L3: 34405 | M3: 13.637841 | N3: 296838.1 | O3: 9.180503 | P3: 252276 | Q3: 3233353.4 | R3: 14.776137 | S3: 62.871617 | T3: 17.421315 | U3: 5.1262619 | V3: 117929 | W3: 1.9233241 | X3: 3.3392284 | Y3: 0.21483114 | Z3: 0.55413179 | AA3: 1.4909678e+12 | AB3: 58029.516 | AC3: 0.91640161 | AD3: 0.25385847 | AE3: 3.983869 | AF3: 15.1 | AG3: 3.02 | AH3: 99.64 | AI3: -0.61 | AJ3: 159.54 | AK3: 14.42 | AL3: 24.79 | AM3: 159.54 | AN3: 15.1 | AO3: 17.44 | AP3: 99.64 | AQ3: 21.05459 | AR3: 49238.433 | AS3: 0.951 | AT3: 84.5265 | AU3: 12.72682 | AV3: 2.4 | AW3: 571.38211 | AX3: 3.2549747e+10 | AY3: 0.07441249 | AZ3: 0.044636503 | BA3: 329293.78 | BB3: -3.5714286 | BC3: 1 | BD3: =VLOOKUP($A3,'NZ targets'!$G$13:$BG$238,33,FALSE) -> -0.043916955 | BE3: =VLOOKUP($A3,'NZ targets'!$G$13:$BG$238,18,FALSE) -> -60 | BF3: =VLOOKUP($A3,'NZ targets'!$G$13:$BG$238,25,FALSE) -> -63.860982 | BG3: =VLOOKUP($A3,'NZ targets'!$G$13:$BG$238,3,FALSE) -> 4
A4: AUT | B4: =VLOOKUP($A4,'NZ targets'!$G$13:$BG$238,2,FALSE) -> Austria | C4: 100 | D4: 17.465726 | E4: 9041851 | F4: 1.2586194 | G4: 1.4654502 | H4: 0.63799536 | I4: 1.2831998 | J4: 1.7058502 | K4: 1.4087608 | L4: 47243 | M4: 76.490779 | N4: 362355.8 | O4: 34.394992 | P4: 61763 | Q4: 1053513.3 | R4: 6.6326457 | S4: 8.2266082 | T4: 47.294474 | U4: 0.76967401 | V4: 20314 | W4: 0.42164385 | X4: 108.52881 | Y4: -0.053645572 | Z4: 0 | AA4: 3.8651424e+11 | AB4: 43346.432 | AC4: 0.0087652478 | AD4: 0.022711461 | AE4: 16.00921 | AF4: 7.45 | AG4: 1.71 | AH4: 24.76 | AI4: -4.04 | AJ4: 7.41 | AK4: 1.73 | AL4: 7.68 | AM4: 7.41 | AN4: 7.45 | AO4: 3.44 | AP4: 24.76 | AQ4: 16.007959 | AR4: 53618.671 | AS4: 0.916 | AT4: 81.5797 | AU4: 12.25669 | AV4: 1.9 | AW4: 76.743304 | AX4: 3.7895452e+09 | AY4: 0.057440874 | AZ4: 0.7427933 | BA4: 59199.242 | BB4: -5.5555556 | BC4: 1 | BD4: =VLOOKUP($A4,'NZ targets'!$G$13:$BG$238,33,FALSE) -> -0.088718244 | BE4: =VLOOKUP($A4,'NZ targets'!$G$13:$BG$238,18,FALSE) -> -5.2338985 | BF4: =VLOOKUP($A4,'NZ targets'!$G$13:$BG$238,25,FALSE) -> -9.058439 | BG4: =VLOOKUP($A4,'NZ targets'!$G$13:$BG$238,3,FALSE) -> 4
A5: BEL | B5: =VLOOKUP($A5,'NZ targets'!$G$13:$BG$238,2,FALSE) -> Belgium | C5: 100 | D5: 12.283533 | E5: 11685814 | F5: 1.4950486 | G5: 1.2276587 | H5: 0.57566881 | I5: 1.2529552 | J5: 1.3489424 | K5: 1.2926087 | L5: 14466 | M5: 20.800023 | N5: 128345.2 | O5: 9.2016405 | P5: 69548 | Q5: 1394807.8 | R5: 7.3981307 | S5: 6.1080117 | T5: 22.764201 | U5: 0.69107897 | V5: 53428 | W5: 0.3955588 | X5: 382.63524 | Y5: -0.15906384 | Z5: 0 | AA5: 4.6667177e+11 | AB5: 40424.639 | AC5: 3.4458349e-05 | AD5: 0 | AE5: 28.562635 | AF5: 22.41 | AG5: 2.29 | AH5: 25.31 | AI5: 0.46 | AJ5: 9.4 | AK5: 3.06 | AL5: 9.53 | AM5: 9.4 | AN5: 22.41 | AO5: 5.35 | AP5: 25.31 | AQ5: 19.604219 | AR5: 52293.4 | AS5: 0.937 | AT5: 81.8787 | AU5: 12.37568 | AV5: 2.1 | AW5: 114.0322 | AX5: 5.1827842e+09 | AY5: 0.11456469 | AZ5: 1.7752834 | BA5: 55904.479 | BB5: -3.5714286 | BC5: 1 | BD5: =VLOOKUP($A5,'NZ targets'!$G$13:$BG$238,33,FALSE) -> -0.04971585 | BE5: =VLOOKUP($A5,'NZ targets'!$G$13:$BG$238,18,FALSE) -> -0.35387688 | BF5: =VLOOKUP($A5,'NZ targets'!$G$13:$BG$238,25,FALSE) -> -0.61246357 | BG5: =VLOOKUP($A5,'NZ targets'!$G$13:$BG$238,3,FALSE) -> 3
A6: BGD | B6: =VLOOKUP($A6,'NZ targets'!$G$13:$BG$238,2,FALSE) -> Bangladesh | C6: 98.991028 | D6: 0.88375374 | E6: 171186372 | F6: -1.0755273 | G6: -0.7625519 | H6: -1.0923711 | I6: -0.92765892 | J6: -0.60133934 | K6: -0.75266188 | L6: 724 | M6: 1.2268899 | N6: 386058.6 | O6: 34.747069 | P6: 59011 | Q6: 1111053.7 | R6: 0.51064756 | S6: 1.6895155 | T6: 14.468772 | U6: 0.53102074 | V6: -61154 | W6: 0.16770211 | X6: 1301.039 | Y6: 0.17934586 | Z6: 0.01043877 | AA6: 2.6675989e+11 | AB6: 1619.7759 | AC6: 0.20682979 | AD6: 0.0097279476 | AE6: 61.458093 | AF6: 9.82 | AG6: 0.8 | AH6: 12.01 | AI6: 3.07 | AJ6: 88.53 | AK6: 3.18 | AL6: 1.37 | AM6: 88.53 | AN6: 9.82 | AO6: 3.97 | AP6: 12.01 | AQ6: 12.44198 | AR6: 5472.1048 | AS6: 0.661 | AT6: 72.3811 | AU6: 7.3790598 | AV6: 5.7 | AW6: 281.08211 | AX6: 1.3062121e+10 | AY6: 0.26075707 | AZ6: 14.73467 | BA6: 1910366.5 | BB6: -3.5714286 | BC6: 1 | BD6: =VLOOKUP($A6,'NZ targets'!$G$13:$BG$238,33,FALSE) | BE6: =VLOOKUP($A6,'NZ targets'!$G$13:$BG$238,18,FALSE) -> 8.2258266 | BF6: =VLOOKUP($A6,'NZ targets'!$G$13:$BG$238,25,FALSE) -> 7.6369218 | BG6: =VLOOKUP($A6,'NZ targets'!$G$13:$BG$238,3,FALSE) -> 1
A7: BGR | B7: =VLOOKUP($A7,'NZ targets'!$G$13:$BG$238,2,FALSE) -> Bulgaria | C7: 99.8 | D7: 1.4281964 | E7: 6465097 | F7: -0.15789711 | G7: -0.27079985 | H7: 0.24625206 | I7: 0.32068691 | J7: -0.10721157 | K7: 0.28520486 | L7: 8768 | M7: 17.988593 | N7: 69034.96 | O7: 17.650078 | P7: 48742 | Q7: 391131.19 | R7: 4.9232804 | S7: 46.206557 | T7: 35.980103 | U7: 1.0067034 | V7: -9902 | W7: 0.62427463 | X7: 63.354302 | Y7: -0.83439604 | Z7: 0.071455114 | AA7: 5.4923718e+10 | AB7: 7920.9113 | AC7: 0.0049703973 | AD7: 0.01300645 | AE7: 32.166544 | AF7: 1.02 | AG7: 1.24 | AH7: 9.44 | AI7: -13.82 | AJ7: 5.26 | AK7: 1.37 | AL7: 2.78 | AM7: 5.26 | AN7: 1.02 | AO7: 2.6 | AP7: 9.44 | AQ7: 13.89729 | AR7: 23078.956 | AS7: 0.795 | AT7: 71.798 | AU7: 11.41318 | AV7: 2.7 | AW7: 68.413545 | AX7: 1.0046248e+09 | AY7: 0.056774055 | AZ7: -0.44229846 | BA7: -68790.909 | BB7: -2.3255814 | BC7: 1 | BD7: =VLOOKUP($A7,'NZ targets'!$G$13:$BG$238,33,FALSE) | BE7: =VLOOKUP($A7,'NZ targets'!$G$13:$BG$238,18,FALSE) -> -9.4482011 | BF7: =VLOOKUP($A7,'NZ targets'!$G$13:$BG$238,25,FALSE) -> -10.72419 | BG7: =VLOOKUP($A7,'NZ targets'!$G$13:$BG$238,3,FALSE) -> 1
A8: BHR | B8: =VLOOKUP($A8,'NZ targets'!$G$13:$BG$238,2,FALSE) -> Bahrain | C8: 100 | D8: 51.126785 | E8: 1472233 | F8: 0.13938564 | G8: 0.64042491 | H8: -0.4070285 | I8: 0.97063351 | J8: 0.43882862 | K8: -1.4175618 | L8: 0 | M8: 0 | N8: 0 | O8: 0 | P8: 28484 | Q8: 191733.46 | R8: 21.976908 | S8: 0 | T8: 0.91139241 | U8: 11.940307 | V8: -48716 | W8: 0.11617056 | X8: 1852.2342 | Y8: -3.2753404 | Z8: 0 | AA8: 3.3258424e+10 | AB8: 19545.579 | AC8: 1.3230688 | AD8: 7.3591311 | AE8: 2.0382166 | AF8: 0.27 | AG8: 0.56 | AH8: 3.85 | AI8: 2.1 | AJ8: 0.05 | AK8: 3.31 | AL8: 31.19 | AM8: 0.05 | AN8: 0.27 | AO8: 3.87 | AP8: 3.85 | AQ8: 16.29756 | AR8: 39497.248 | AS8: 0.875 | AT8: 78.7605 | AU8: 11.04659 | AV8: 1.4 | AW8: 69.976212 | AX8: 9.0491907e+08 | AY8: 0.32702732 | AZ8: 34.387925 | BA8: 23155.63 | BB8: -1.8867925 | BC8: 1 | BD8: =VLOOKUP($A8,'NZ targets'!$G$13:$BG$238,33,FALSE) -> -0.02220396 | BE8: =VLOOKUP($A8,'NZ targets'!$G$13:$BG$238,18,FALSE) -> -0.0248 | BF8: =VLOOKUP($A8,'NZ targets'!$G$13:$BG$238,25,FALSE) -> -0.031253049 | BG8: =VLOOKUP($A8,'NZ targets'!$G$13:$BG$238,3,FALSE) -> 2
A9: CAN | B9: =VLOOKUP($A9,'NZ targets'!$G$13:$BG$238,2,FALSE) -> Canada | C9: 100 | D9: 21.801664 | E9: 38929902 | F9: 1.6585798 | G9: 1.5670705 | H9: 0.77281404 | I9: 1.6770928 | J9: 1.5662202 | K9: 1.4349684 | L9: 422643 | M9: 63.01145 | N9: 1587094 | O9: 22.025359 | P9: 670740 | Q9: 7205757.6 | R9: 13.599375 | S9: 9.8364493 | T9: 39.470128 | U9: 2.6348554 | V9: 195181 | W9: 1.2387219 | X9: 4.3495054 | Y9: 0.014063977 | Z9: 0.053023333 | AA9: 1.6074025e+12 | AB9: 42258.691 | AC9: 0.037249734 | AD9: 1.0879346 | AE9: 4.2646385 | AF9: 75.68 | AG9: 6.75 | AH9: 192.11 | AI9: 2.37 | AJ9: 58.95 | AK9: 14.88 | AL9: 20.6 | AM9: 58.95 | AN9: 75.68 | AO9: 21.64 | AP9: 192.11 | AQ9: 16.396259 | AR9: 46807.986 | AS9: 0.936 | AT9: 82.6565 | AU9: 13.834427 | AV9: 2.4 | AW9: 756.81011 | AX9: 2.49098e+10 | AY9: 0.028846842 | AZ9: 0.050256576 | BA9: 428256.61 | BB9: -3.5714286 | BC9: 1 | BD9: =VLOOKUP($A9,'NZ targets'!$G$13:$BG$238,33,FALSE) -> -0.039599481 | BE9: =VLOOKUP($A9,'NZ targets'!$G$13:$BG$238,18,FALSE) -> -100 | BF9: =VLOOKUP($A9,'NZ targets'!$G$13:$BG$238,25,FALSE) -> -28.496771 | BG9: =VLOOKUP($A9,'NZ targets'!$G$13:$BG$238,3,FALSE) -> 4
A10: CHE | B10: =VLOOKUP($A10,'NZ targets'!$G$13:$BG$238,2,FALSE) -> Switzerland | C10: 100 | D10: 29.386686 | E10: 8775760 | F10: 2.0093138 | G10: 2.0499489 | H10: 1.1611397 | I10: 1.620113 | J10: 1.7518067 | K10: 1.6155596 | L10: 41111 | M10: 62.197982 | N10: 195365.5 | O10: 25.291984 | P10: 66097 | Q10: 772440.4 | R10: 4.0420728 | S10: 0 | T10: 32.208603 | U10: 0.5759601 | V10: 53786 | W10: 0.27745615 | X10: 220.31454 | Y10: -0.32739763 | Z10: 0 | AA10: 7.4002624e+11 | AB10: 85685.29 | AC10: 0 | AD10: 0 | AE10: 10.118463 | AF10: 11.34 | AG10: 1.76 | AH10: 15.82 | AI10: -2.62 | AJ10: 5.54 | AK10: 1.67 | AL10: 5.14 | AM10: 5.54 | AN10: 11.34 | AO10: 3.42 | AP10: 15.82 | AQ10: 16.500299 | AR10: 66933.005 | AS10: 0.962 | AT10: 83.9872 | AU10: 13.85966 | AV10: 1.4 | AW10: 45.56382 | AX10: 1.1788789e+10 | AY10: 0.047105968 | AZ10: 1.9829354 | BA10: 74158.636 | BB10: -3.5714286 | BC10: 1 | BD10: =VLOOKUP($A10,'NZ targets'!$G$13:$BG$238,33,FALSE) -> -0.048161487 | BE10: =VLOOKUP($A10,'NZ targets'!$G$13:$BG$238,18,FALSE) -> -1.4340403 | BF10: =VLOOKUP($A10,'NZ targets'!$G$13:$BG$238,25,FALSE) -> -1.4849326 | BG10: =VLOOKUP($A10,'NZ targets'!$G$13:$BG$238,3,FALSE) -> 4
A11: CHL | B11: =VLOOKUP($A11,'NZ targets'!$G$13:$BG$238,2,FALSE) -> Chile | C11: 100 | D11: 2.6155132 | E11: 19603733 | F11: 0.96828014 | G11: 0.54677397 | H11: 0.11857886 | I11: 0.97841114 | J11: 0.69040066 | K11: 0.97297513 | L11: 32872 | M11: 43.604335 | N11: 259606.8 | O11: 24.882554 | P11: 75387 | Q11: 1043328.6 | R11: 4.3951511 | S11: 37.144335 | T11: 24.657473 | U11: 0.61115767 | V11: 98439 | W11: 0.34193389 | X11: 26.217007 | Y11: -0.75873432 | Z11: 0.0071161044 | AA11: 2.4641299e+11 | AB11: 12890.264 | AC11: 0.011224695 | AD11: 0.017901358 | AE11: 1.6098836 | AF11: 6.58 | AG11: 0.88 | AH11: 28.33 | AI11: -1.89 | AJ11: 10.65 | AK11: 3.15 | AL11: 2.76 | AM11: 10.65 | AN11: 6.58 | AO11: 4.03 | AP11: 28.33 | AQ11: 16.7313 | AR11: 24563.245 | AS11: 0.855 | AT11: 78.9435 | AU11: 10.934966 | AV11: 3.2 | AW11: 137.01125 | AX11: 4.4544707e+09 | AY11: 0.13699494 | AZ11: 0.33774918 | BA11: 253560.3 | BB11: -2.3255814 | BC11: 1 | BD11: =VLOOKUP($A11,'NZ targets'!$G$13:$BG$238,33,FALSE) -> -0.028594465 | BE11: =VLOOKUP($A11,'NZ targets'!$G$13:$BG$238,18,FALSE) -> 65 | BF11: =VLOOKUP($A11,'NZ targets'!$G$13:$BG$238,25,FALSE) -> -62.58523 | BG11: =VLOOKUP($A11,'NZ targets'!$G$13:$BG$238,3,FALSE) -> 4
A12: CHN | B12: =VLOOKUP($A12,'NZ targets'!$G$13:$BG$238,2,FALSE) -> China | C12: 100 | D12: 0.071076396 | E12: 1412175000 | F12: 0.015970249 | G12: 0.49503201 | H12: -0.44107363 | I12: -0.41841763 | J12: -0.041443985 | K12: -1.6095749 | L12: 1398321 | M12: 23.926817 | N12: 9084482 | O12: 12.413353 | P12: 5844158 | Q12: 73183147 | R12: 7.7561379 | S12: 70.309427 | T12: 23.631528 | U12: 0.84068116 | V12: -33649 | W12: 0.38049763 | X12: 150.43975 | Y12: -1.0921141 | Z12: 0.35006509 | AA12: 1.461654e+13 | AB12: 10358.259 | AC12: 0.10814925 | AD12: 0.25510718 | AE12: 12.676591 | AF12: 542.13 | AG12: 782 | AH12: 917.02 | AI12: 2.61 | AJ12: 672.87 | AK12: 384.29 | AL12: 8.4 | AM12: 672.87 | AN12: 542.13 | AO12: 1166.29 | AP12: 917.02 | AQ12: 14.236115 | AR12: 17504.4 | AS12: 0.768 | AT12: 78.2107 | AU12: 7.6001184 | AV12: 3 | AW12: 15684.627 | AX12: 7.3760223e+11 | AY12: 0.083395467 | AZ12: 0.71986065 | BA12: 5736515.2 | BB12: -1.8867925 | BC12: 1 | BD12: =VLOOKUP($A12,'NZ targets'!$G$13:$BG$238,33,FALSE) -> -0.020453535 | BE12: =VLOOKUP($A12,'NZ targets'!$G$13:$BG$238,18,FALSE) -> -1211.5892 | BF12: =VLOOKUP($A12,'NZ targets'!$G$13:$BG$238,25,FALSE) -> -1377.2091 | BG12: =VLOOKUP($A12,'NZ targets'!$G$13:$BG$238,3,FALSE) -> 3
A13: COD | B13: =VLOOKUP($A13,'NZ targets'!$G$13:$BG$238,2,FALSE) -> Congo, Democratic Republic | C13: 20.768187 | D13: 0.70624628 | E13: 99010212 | F13: -1.544474 | G13: -1.7459201 | H13: -1.9777462 | I13: -1.4760695 | J13: -1.6724339 | K13: -1.1836931 | L13: 8926 | M13: 99.821069 | N13: 862513.8 | O13: 95.8177 | P13: 8942 | Q13: 900161.25 | R13: 0.032584781 | S13: 0 | T13: 55.161493 | U13: 0.38430795 | V13: -1643 | W13: 0.16112069 | X13: 42.299075 | Y13: 0.20082871 | Z13: 0 | AA13: 4.5259707e+10 | AB13: 505.34834 | AC13: 0 | AD13: 0.50031777 | AE13: 5.9447299 | AF13: 0 | AG13: 0.08 | AH13: 2.07 | AI13: -0.66 | AJ13: 25.98 | AK13: 2.1 | AL13: 8.11 | AM13: 25.98 | AN13: 0 | AO13: 2.18 | AP13: 2.07 | AQ13: 9.8178645 | AR13: 1076.0988 | AS13: 0.479 | AT13: 59.193 | AU13: 7.0186965 | AV13: 7.7 | AW13: 61.635094 | AX13: 1.9707114e+09 | AY13: 0.14352156 | AZ13: 1.2225697 | BA13: 2837421.5 | BB13: -2.3255814 | BC13: 0 | BD13: =VLOOKUP($A13,'NZ targets'!$G$13:$BG$238,33,FALSE) | BE13: =VLOOKUP($A13,'NZ targets'!$G$13:$BG$238,18,FALSE) -> 214.60858 | BF13: =VLOOKUP($A13,'NZ targets'!$G$13:$BG$238,25,FALSE) -> 180.17104 | BG13: =VLOOKUP($A13,'NZ targets'!$G$13:$BG$238,3,FALSE) -> 1
... A77: ZMB | B77: =VLOOKUP($A77,'NZ targets'!$G$13:$BG$238,2,FALSE) -> Zambia | C77: 46.685116 | D77: 0.78902565 | E77: 20017675 | F77: -0.52919984 | G77: -0.65823275 | H77: 0.10231356 | I77: -0.52905792 | J77: -0.51915401 | K77: -0.089141272 | L77: 13035 | M77: 96.993824 | N77: 301679.8 | O77: 87.985452 | P77: 13439 | Q77: 342874.64 | R77: 0.40190271 | S77: 0 | T77: 60.03015 | U77: 0.81619743 | V77: 9015 | W77: 0.65319531 | X77: 26.195032 | Y77: 0.33348405 | Z77: 0.14289322 | AA77: 2.3418946e+10 | AB77: 1273.8796 | AC77: 0 | AD77: 0 | AE77: 5.1117179 | AF77: 0.13 | AG77: 1.05 | AH77: 2.03 | AI77: -0.68 | AJ77: 24.45 | AK77: 0.59 | AL77: 5.37 | AM77: 24.46 | AN77: 0.13 | AO77: 1.64 | AP77: 2.03 | AQ77: 10.92876 | AR77: 3217.7677 | AS77: 0.565 | AT77: 61.2234 | AU77: 7.1870915 | AV77: 3.9 | AW77: 30.330585 | AX77: 7.1781519e+08 | AY77: 0.092849732 | AZ77: 0.70856464 | BA77: 533121.38 | BB77: -3.5714286 | BC77: 1 | BD77: =VLOOKUP($A77,'NZ targets'!$G$13:$BG$238,33,FALSE) | BE77: =VLOOKUP($A77,'NZ targets'!$G$13:$BG$238,18,FALSE) -> -23.398434 | BF77: =VLOOKUP($A77,'NZ targets'!$G$13:$BG$238,25,FALSE) -> -28.037488 | BG77: =VLOOKUP($A77,'NZ targets'!$G$13:$BG$238,3,FALSE) -> 1

Sheet NZ targets
F1: Target types | G1: Column1 | H1: Type | I1: Number of countries | J1: Emissions share in 2018 | K1: https://eciu.net/netzerotracker | L1: Target types | M1: Number of countries | N1: Emissions share in 2018 | AN1: Source:
F2: Achieved (self-declared) | H2: 5 | I2: =COUNTIF(I$13:I$239,$H2) -> 6 | J2: =SUMIF($I$13:$I$236,5,$J$13:$J$236)/$J$261 -> 0.00057882977 | L2: Achieved, Policy documents, Proposed, Law | M2: =SUM(I2:I5) -> 96 | N2: =SUM(J2:J5) -> 0.84592132 | W2: Residual emissions LULUCF | AN2: IIASA calculations (under development) based on inventory data and national communications. The database is almost ready and will be documented later.
F3: In Law | H3: 4 | I3: =COUNTIF(I$13:I$239,$H3) -> 27 | J3: =(SUMIF($I$13:$I$236,4,$J$13:$J$236))/$J$261 -> 0.23567347 | P3: =N2+N3 -> 0.84592132 | W3: Current policies scenarios | AN3: Nascimento, L., et al., Greenhouse gas mitigation scenarios for major emitting countries. Analysis of current climate policies and mitigation commitments: 2023 Update, 2023: NewClimate Institute (Cologne, Germany), PBL (The Hague, the Netherlands), IIASA (Austria), https://newclimate.org/resources/publications/emissions-scenarios-for-major-economies-2023-update.
F4: In policy document | H4: 3 | I4: =COUNTIF(I$13:I$239,$H4) -> 51 | J4: =SUMIF($I$13:$I$236,3,$J$13:$J$236)/$J$261 -> 0.48575044 | L4: Net zero-target Under Discussion | M4: =I6-M3 -> 55 | N4: =J6-N3 -> 0.0604576 | W4: 2021 emissions | AG4: Commentaar index | AN4: National inventory data, as reported in : Nascimento et al. (2013) for the major emitting countries, and for the other countries
F5: Declaration / pledge | H5: 2 | I5: =COUNTIF(I$13:I$239,$H5) -> 12 | J5: =(SUMIF($I$13:$I$236,2,$J$13:$J$236)+J238)/$J$261 -> 0.12391858 | L5: Climate ambition alliance * | M5: =I7 -> 0 | N5: =J7 -> 0 | AG5: =1000000000*(W20-AC20)/(2050-2022)/BA20 -> -219.55181 | AN5: Gütschow, J. and M. Pflüger, The PRIMAP-hist national historical emissions time series v2.5 (1750-2022). zenodo, 2023.
F6: Proposed / in discussion | H6: 1 | I6: =COUNTIF(I$13:I$239,$H6) -> 55 | J6: =SUMIF($I$13:$I$236,1,$J$13:$J$236)/$J$261 -> 0.0604576 | L6: Countries with no zero target | M6: =I8 -> 74 | N6: =J8 -> 0.090564902 | Q6: * https://unfccc.int/news/climate-ambition-alliance-nations-renew-their-push-to-upscale-action-by-2020-and-achieve-net-zero | W6: NDC targets | AN6: den Elzen, M.G.J., et al., The impact of policy and model uncertainties on emissions projections of the Paris Agreement pledges. Environmental Research Letters, 2023. 18(5): p. 054026.
F7: Climate ambition alliance * | H7: -1 | I7: =COUNTIF(I$13:I$239,$H7) -> 0 | J7: =SUMIF($I$13:$I$236,-1,$J$13:$J$236)/$J$261 -> 0 | L7: Int bunker emissions, remaining LULUCF | N7: =(J243+J244)/J261 -> 0.0030561825 | Q7: https://www.climatechangenews.com/2020/09/17/countries-net-zero-climate-goal/ | AI7: World average Penalty
F8: No target | H8: 0 | I8: =COUNTIF(I$13:I$239,$H8) -> 74 | J8: =SUMIF($I$13:$I$236,0,$J$13:$J$236)/$J$261 -> 0.090564902 | L8: Total | M8: =SUM(M2:M7) -> 225 | N8: =SUM(N2:N7) -> 1 | AI8: 7
F9: EU is only counted for the EU as a whole | H9: INPUT in "input site" | I9: =SUM(I2:I8) -> 225 | J9: =SUM(J2:J8) -> 0.99694382 | L9: Total (EU in MSs) | M9: =M8+27 -> 252 | T9: Nascimento et al | W9: Assumed at least zero residual emissions (not negative) | AF9: Adjust for Incl/Excl LULUCF | AI9: Penalty | AW9: Excl LULUCF | BA9: Equity | BE9: Rogelj et al
G10: =1 -> 1 | H10: =G10+1 -> 2 | I10: =H10+1 -> 3 | J10: =I10+1 -> 4 | K10: =J10+1 -> 5 | L10: =K10+1 -> 6 | M10: =L10+1 -> 7 | N10: =M10+1 -> 8 | O10: =N10+1 -> 9 | ... W10: =V10+1 -> 17 | AF10: Important for Canada, etc. | AI10: -10 | AL10: =W10+1 -> 18 | AN10: =AL10+1 -> 19 | AQ10: =AN10+1 -> 20 | AR10: =AQ10+1 -> 21 | AS10: =AR10+1 -> 22 | AT10: =AS10+1 -> 23 | AU10: =AT10+1 -> 24 | AV10: =AU10+1 -> 25 | BA10: =AV10+1 -> 26 | BB10: =BA10+1 -> 27 | BC10: =BB10+1 -> 28 | BD10: =BC10+1 -> 29 | BE10: =BD10+1 -> 30 | BF10: =BE10+1 -> 31 | BG10: =BF10+1 -> 32 | BH10: Rogelj | BI10: EGR 2023 | BN10: Smith etal
A11: Rogelj analysis | B11: G20 | C11: ISO | D11: VSF nr | E11: Region code | F11: LULUCF | G11: ISO | H11: (Mt CO2 equivalent) | I11: Net-zero target status | J11: 2021 emissions | K11: Current policies | L11: Net-zero targets if available (alternative Current policies) | M11: 2 Degree & net-zero targets | N11: 2 degree scenario | O11: NZ target year | P11: Difference 2Degree - LTS | Q11: 1.5 Degree & net-zero targets | R11: 1.5 degree scenario | S11: Reaching net-zero | T11: Country | U11: Net zero year | V11: NZ GHG year | W11: residual LULUCF emissions in 2050 | X11: LULUCF emis-sions NZ | Y11: LULUCF NDC uncond | Z11: LULUCF NDC cond | AA11: GHG emissions incl LULUCF | AB11: LULUCF emis-sions in 20213 | AC11: GHG emissions excl LULUCF | AD11: Current Policies 2030 incl LULUCF | AE11: LULUCF CurPol 2030 | AF11: Current Policies 2030 excl LULUCF | AG11: Formule Stephan | AH11: (A) Formule Peak | AI11: Penalty (1) | AJ11: Formule no Peak (2) | AK11: (B) Formule no Peak | AL11: Current Policies (2021 - 2030) | AM11: Reduction rate CurPol to NZ target | AN11: Reduction rate 2021 to NZ target2 | AO11: Reduction rate NDC to NZ target | AP11: Maximum inventory data | AQ11: Peak revised | AR11: Residual emissions as % 2021 emissions | AS11: 2030 unconditional NDCs | AT11: 2030 unconditional NDCs2 | AU11: 2030 conditional NDCs | AV11: 2030 conditional NDCs2 | AW11: 2031 conditional NDCs2 | AX11: 2032 conditional NDCs2 | AY11: 2033 conditional NDCs2 | AZ11: 2034 conditional NDCs2 | BA11: Population | BB11: Income | BC11: Incomeper capita | BD11: Emissions per capita | BE11: Legally binding | BF11: Published plan (BOLD: manually coded) | BG11: CurPol 10% below | BH11: Confidence assessment | BI11: Confidence assessment2 | BJ11: Current Policies (2021 - 2030)2 | BK11: Reduction rate CurPol to NZ target3 | BL11: Reduction rate 2021 to NZ target24 | BM11: Reduction rate NDC to NZ target5 | BN11: Low residual LULUCF | BO11: High residual LULUCF | BP11: Low res. CDR | BQ11: High res. CDR | BR11: (Mt CO2 equivalent)2 | BT11: Check
A12: Number | B12: Number | C12: Number | D12: Number | E12: Number | F12: Excl/Incl | G12: Code | H12: Country name | I12: Net zero target | J12: 2021 | K12: 2050 | L12: 2050 | M12: NZT -year | N12: 2050 | O12: 2050 | P12: 2050 | Q12: 2050 | R12: 2050 | S12: Net-zero date | T12: =Table12[[#This Row],[(Mt CO2 equivalent)]] -> Country name | U12: Net zero year | V12: NZ GHG year | W12: residual LULUCF emissions in 2050 | X12: LULUCF emissions NZ | Y12: uncod LULUCF emissions 2030 | Z12: cond LULUCF emissions 2030 | AA12: GHG emissions incl LULUCF 2021 | AB12: LULUCF emissions 2021 | AC12: GHG emissions excl LULUCF 2021 | AD12: Current Policies 2030 incl LULUCF | AE12: 2030 median | AF12: Current Policies 2030 excl LULUCF | AG12: tCO2e/cap | AH12: tCO2e/cap | AI12: tCO2e/cap | AJ12: tCO2e/cap | AK12: tCO2e/cap | AL12: Current Policies (2021 - 2030) | AM12: Reduction rate CurPol to NZ target | AN12: Reduction rate 2021 to NZ target2 | AO12: Reduction rate NDC to NZ target | AP12: MtCO2e | AQ12: =IF(Table12[[#This Row],[Current Policies 2030 incl LULUCF]]>Table12[[#This Row],[Maximum inventory data]],"No","Yes") -> Yes | AR12: %-share in 2021 | AS12: ='input site'!BE12 -> Low | AT12: ='input site'!BF12 -> High | AU12: ='input site'!BG12 -> Low | AV12: 2034 conditional NDCs2 incl | AW12: 2031 conditional NDCs2 | AX12: 2032 conditional NDCs2 | AY12: 2033 conditional NDCs2 | AZ12: 2034 conditional NDCs2 | BA12: 2022 | BB12: 2022 | BC12: 2022 | BD12: 2022 | BJ12: %/yr | BK12: %/yr | BL12: %/yr | BM12: %/yr | BR12: Country name
A13: 0 | B13: 0 | C13: 4 | D13: 1 | E13: 25 | F13: ='input site'!M13 -> excl | G13: AFG | H13: Afghanistan | I13: =VLOOKUP($G13,'NZT data'!$B$3:$C$200,2,FALSE) -> 1 | J13: ='input site'!AS13 -> 48.204461 | K13: ='input site'!BS13 -> 58.63732 | L13: =IF(I13>=1,O13,K13) -> 0 | M13: =IF(I13>=1,O13,N13) -> 0 | N13: ='input site'!EV13 -> 28.988983 | Q13: =IF(I13>=1,O13,R13) -> 0 | R13: ='[5]input site'!CN13 -> 9.2522941 | S13: 2050 | T13: =Table12[[#This Row],[(Mt CO2 equivalent)]] -> Afghanistan | U13: =VLOOKUP($G13,'NZT data'!$B$3:$F$200,4,FALSE) -> 2110 | V13: =VLOOKUP($G13,'NZT data'!$B$3:$F$200,5,FALSE) -> 2125 | W13: =-IF('LUC NGHGI'!EC3="",MIN('LUC NGHGI'!DW3,0.1),MIN('LUC NGHGI'!EC3,0.1)) -> -0.1 | X13: ='LUC NGHGI'!EC3 -> 0 | Y13: ='LUC NGHGI'!DY3 -> 0 | Z13: ='LUC NGHGI'!DZ3 -> 0 | AA13: =Table12[[#This Row],[2021 emissions]] -> 48.204461 | AB13: ='LUC NGHGI'!DW3 -> 9.43107 | AC13: =IF(F13="incl",Table12[[#This Row],[GHG emissions incl LULUCF]]-Table12[[#This Row],[LULUCF emis-sions in 20213]],Table12[[#This Row],[GHG emissions incl LULUCF]]) -> 48.204461 | AD13: ='input site'!BS13 -> 58.63732 | AE13: ='LUC NGHGI'!EH3 -> 0 | AF13: =IF(F13="incl",Table12[[#This Row],[Current Policies 2030 incl LULUCF]]-Table12[[#This Row],[LULUCF CurPol 2030]],Table12[[#This Row],[Current Policies 2030 incl LULUCF]]) -> 58.63732 | AG13: =IF(Table12[[#This Row],[Net-zero target status]]<=1,"",IF(Table12[[#This Row],[NZ GHG year]]="","",1000000000*(Table12[[#This Row],[residual LULUCF emissions in 2050]]-Table12[[#This Row],[GHG emissions excl LULUCF]])/(Table12[[#This Row],[NZ GHG year]]-2021)/Table12[[#This Row],[Population]])) | AH13: =IF(Table12[[#This Row],[Peak revised]]="Yes",IF(Table12[[#This Row],[Net-zero target status]]<=1,"",IF(Table12[[#This Row],[NZ GHG year]]="","",1000000000*(Table12[[#This Row],[residual LULUCF emissions in 2050]]-Table12[[#This Row],[GHG emissions excl LULUCF]])/(Table12[[#This Row],[NZ GHG year]]-2021)/Table12[[#This Row],[Population]])),"") | AI13: =MAX(0,(1000000*(Table12[[#This Row],[Current Policies 2030 excl LULUCF]]/2+Table12[[#This Row],[GHG emissions excl LULUCF]]/2)/Table12[[#This Row],[Population]]-$AI$8)*10)*$AI$10 -> 0 | AJ13: =IF(Table12[[#This Row],[Peak revised]]="No",IF(Table12[[#This Row],[Net-zero target status]]<=1,"",IF(Table12[[#This Row],[NZ GHG year]]="","",1000000000*(Table12[[#This Row],[residual LULUCF emissions in 2050]]-Table12[[#This Row],[Current Policies 2030 excl LULUCF]])/(Table12[[#This Row],[NZ GHG year]]-2021)/Table12[[#This Row],[Population]])),"") | AK13: =IF(Table12[[#This Row],[Formule no Peak (2)]]="","",Table12[[#This Row],[Penalty (1)]]+Table12[[#This Row],[Formule no Peak (2)]]) | AL13: =(Table12[[#This Row],[Current Policies 2030 excl LULUCF]]-Table12[[#This Row],[GHG emissions excl LULUCF]])/(2030-2021)/Table12[[#This Row],[GHG emissions excl LULUCF]] -> 0.024047702 | AM13: =IF(Table12[[#This Row],[Net-zero target status]]<=1,"",IF(Table12[[#This Row],[NZ GHG year]]="","",(Table12[[#This Row],[residual LULUCF emissions in 2050]]-Table12[[#This Row],[Current Policies 2030 excl LULUCF]])/(Table12[[#This Row],[NZ GHG year]]-2030)/Table12[[#This Row],[Current Policies 2030 excl LULUCF]])) | AN13: =IF(Table12[[#This Row],[Net-zero target status]]<=1,"",IF(Table12[[#This Row],[NZ GHG year]]="","",(Table12[[#This Row],[residual LULUCF emissions in 2050]]-Table12[[#This Row],[GHG emissions excl LULUCF]])/(Table12[[#This Row],[NZ GHG year]]-2021)/Table12[[#This Row],[GHG emissions excl LULUCF]])) | AO13: =IF(Table12[[#This Row],[Net-zero target status]]<=1,"",IF(Table12[[#This Row],[NZ GHG year]]="","",(Table12[[#This Row],[residual LULUCF emissions in 2050]]-Table12[[#This Row],[2030 conditional NDCs]])/(Table12[[#This Row],[NZ GHG year]]-2030)/Table12[[#This Row],[2030 conditional NDCs]])) | AP13: =MAX('input site'!AH13:AS13) -> 48.204461 | AQ13: =IF(Table12[[#This Row],[Current Policies 2030 incl LULUCF]]>Table12[[#This Row],[Maximum inventory data]],"No","Yes") -> No | AR13: =IF(Table12[[#This Row],[Net-zero target status]]>=1.5,Table12[[#This Row],[residual LULUCF emissions in 2050]]/Table12[[#This Row],[GHG emissions excl LULUCF]],"") | AU13: ='input site'!BG13 -> 42.283763 | AV13: ='input site'!BH13 -> 42.283763 | AW13: =IF(Table12[[#This Row],[2030 unconditional NDCs]]="","",IF(F13="incl",Table12[[#This Row],[2030 unconditional NDCs]]-Table12[[#This Row],[LULUCF NDC uncond]],Table12[[#This Row],[2030 unconditional NDCs]])) | AX13: =IF(Table12[[#This Row],[2030 unconditional NDCs2]]="","",IF(F13="incl",Table12[[#This Row],[2030 unconditional NDCs2]]-Table12[[#This Row],[LULUCF NDC uncond]],Table12[[#This Row],[2030 unconditional NDCs2]])) | AY13: =IF(Table12[[#This Row],[2030 conditional NDCs]]="","",IF(F13="incl",Table12[[#This Row],[2030 conditional NDCs]]-Table12[[#This Row],[LULUCF NDC cond]],Table12[[#This Row],[2030 conditional NDCs]])) -> 42.283763 | AZ13: =IF(Table12[[#This Row],[2030 conditional NDCs2]]="","",IF(F13="incl",Table12[[#This Row],[2030 conditional NDCs2]]-Table12[[#This Row],[LULUCF NDC cond]],Table12[[#This Row],[2030 conditional NDCs2]])) -> 42.283763 | BA13: =VLOOKUP($G13,'Population90 20'!$C$6:$AU$231,37,FALSE) -> 40754388 | BB13: =VLOOKUP($G13,'Overview GDP (PPP)'!$C$6:$AI$231,33,FALSE) -> 64483801 | BC13: =Table12[[#This Row],[Income]]/Table12[[#This Row],[Population]] -> 1.5822542 | BD13: =Table12[[#This Row],[GHG emissions excl LULUCF]]*1000000/Table12[[#This Row],[Population]] -> 1.1828042 | BE13: =VLOOKUP($G13,EGR2023_MASTER!$B$4:$S$38,14,FALSE) -> #N/A | BF13: =VLOOKUP($G13,EGR2023_MASTER!$B$4:$S$38,15,FALSE) -> #N/A | BG13: =VLOOKUP($G13,EGR2023_MASTER!$B$4:$S$38,16,FALSE) -> #N/A | BH13: =IF(AND(BE13="Y",AND(BF13="credible",BG13="Y")),"higher",IF(BG13="Y","lower",IF(AND(BG13="N",OR(BE13="Y",BF13="credible")),"lower","much lower"))) -> #N/A | BI13: =IF(AND($BF13="credible",BG13="Y"),"stronger","weak") -> #N/A | BJ13: =(Table12[[#This Row],[Current Policies 2030 excl LULUCF]]/Table12[[#This Row],[GHG emissions excl LULUCF]])^(1/(2030-2021))-1 -> 0.022007535 | BK13: =IF(Table12[[#This Row],[Net-zero target status]]<=1,"",IF(Table12[[#This Row],[NZ GHG year]]="","",((MAX(Table12[[#This Row],[residual LULUCF emissions in 2050]],0.1)/Table12[[#This Row],[Current Policies 2030 excl LULUCF]])^(1/(Table12[[#This Row],[NZ GHG year]]-2021))-1))) | BL13: =IF(Table12[[#This Row],[Net-zero target status]]<=1,"",IF(Table12[[#This Row],[NZ GHG year]]="","",((MAX(Table12[[#This Row],[residual LULUCF emissions in 2050]],0.1)/Table12[[#This Row],[GHG emissions excl LULUCF]])^(1/(Table12[[#This Row],[NZ GHG year]]-2021))-1))) | BM13: =IF(Table12[[#This Row],[Net-zero target status]]<=1,"",IF(Table12[[#This Row],[NZ GHG year]]="","",((MAX(Table12[[#This Row],[residual LULUCF emissions in 2050]],0.1)/AVERAGE(Table12[[#This Row],[2030 conditional NDCs]:[2030 conditional NDCs2]]))^(1/(Table12[[#This Row],[NZ GHG year]]-2021))-1))) | BR13: Afghanistan | BT13: =IF(Table12[[#This Row],[Reduction rate 2021 to NZ target2]]="","",J13*(1+AN13)^(Table12[[#This Row],[NZ GHG year]]-2021))
A14: 0 | B14: 0 | C14: 8 | D14: 2 | E14: 12 | F14: ='input site'!M14 -> excl | G14: ALB | H14: Albania | I14: 0 | J14: ='input site'!AS14 -> 10.422791 | K14: ='input site'!BS14 -> 5.3405672 | L14: =IF(I14>=1,O14,K14) -> 5.3405672 | M14: =IF(I14>=1,O14,N14) -> 2.405956 | N14: ='input site'!EV14 -> 2.405956 | Q14: =IF(I14>=1,O14,R14) -> 0.98976222 | R14: ='[5]input site'!CN14 -> 0.98976222 | T14: =Table12[[#This Row],[(Mt CO2 equivalent)]] -> Albania | U14: =VLOOKUP($G14,'NZT data'!$B$3:$F$200,4,FALSE) -> 2110 | V14: =VLOOKUP($G14,'NZT data'!$B$3:$F$200,5,FALSE) | W14: =-IF('LUC NGHGI'!EC4="",MIN('LUC NGHGI'!DW4,0.1),MIN('LUC NGHGI'!EC4,0.1)) -> -0.1 | X14: ='LUC NGHGI'!EC4 -> 1.953267 | Y14: ='LUC NGHGI'!DY4 -> 1.953267 | Z14: ='LUC NGHGI'!DZ4 -> 1.953267 | AA14: =Table12[[#This Row],[2021 emissions]] -> 10.422791 | AB14: ='LUC NGHGI'!DW4 -> 1.9695025 | AC14: =IF(F14="incl",Table12[[#This Row],[GHG emissions incl LULUCF]]-Table12[[#This Row],[LULUCF emis-sions in 20213]],Table12[[#This Row],[GHG emissions incl LULUCF]]) -> 10.422791 | AD14: ='input site'!BS14 -> 5.3405672 | AE14: ='LUC NGHGI'!EH4 -> 2.1375888 | AF14: =IF(F14="incl",Table12[[#This Row],[Current Policies 2030 incl LULUCF]]-Table12[[#This Row],[LULUCF CurPol 2030]],Table12[[#This Row],[Current Policies 2030 incl LULUCF]]) -> 5.3405672 | AG14: =IF(Table12[[#This Row],[Net-zero target status]]<=1,"",IF(Table12[[#This Row],[NZ GHG year]]="","",1000000000*(Table12[[#This Row],[residual LULUCF emissions in 2050]]-Table12[[#This Row],[GHG emissions excl LULUCF]])/(Table12[[#This Row],[NZ GHG year]]-2021)/Table12[[#This Row],[Population]])) | AH14: =IF(Table12[[#This Row],[Peak revised]]="Yes",IF(Table12[[#This Row],[Net-zero target status]]<=1,"",IF(Table12[[#This Row],[NZ GHG year]]="","",1000000000*(Table12[[#This Row],[residual LULUCF emissions in 2050]]-Table12[[#This Row],[GHG emissions excl LULUCF]])/(Table12[[#This Row],[NZ GHG year]]-2021)/Table12[[#This Row],[Population]])),"") | AI14: =MAX(0,(1000000*(Table12[[#This Row],[Current Policies 2030 excl LULUCF]]/2+Table12[[#This Row],[GHG emissions excl LULUCF]]/2)/Table12[[#This Row],[Population]]-$AI$8)*10)*$AI$10 -> 0 | AJ14: =IF(Table12[[#This Row],[Peak revised]]="No",IF(Table12[[#This Row],[Net-zero target status]]<=1,"",IF(Table12[[#This Row],[NZ GHG year]]="","",1000000000*(Table12[[#This Row],[residual LULUCF emissions in 2050]]-Table12[[#This Row],[Current Policies 2030 excl LULUCF]])/(Table12[[#This Row],[NZ GHG year]]-2021)/Table12[[#This Row],[Population]])),"") | AK14: =IF(Table12[[#This Row],[Formule no Peak (2)]]="","",Table12[[#This Row],[Penalty (1)]]+Table12[[#This Row],[Formule no Peak (2)]]) | AL14: =(Table12[[#This Row],[Current Policies 2030 excl LULUCF]]-Table12[[#This Row],[GHG emissions excl LULUCF]])/(2030-2021)/Table12[[#This Row],[GHG emissions excl LULUCF]] -> -0.054178534 | AM14: =IF(Table12[[#This Row],[Net-zero target status]]<=1,"",IF(Table12[[#This Row],[NZ GHG year]]="","",(Table12[[#This Row],[residual LULUCF emissions in 2050]]-Table12[[#This Row],[Current Policies 2030 excl LULUCF]])/(Table12[[#This Row],[NZ GHG year]]-2030)/Table12[[#This Row],[Current Policies 2030 excl LULUCF]])) | AN14: =IF(Table12[[#This Row],[Net-zero target status]]<=1,"",IF(Table12[[#This Row],[NZ GHG year]]="","",(Table12[[#This Row],[residual LULUCF emissions in 2050]]-Table12[[#This Row],[GHG emissions excl LULUCF]])/(Table12[[#This Row],[NZ GHG year]]-2021)/Table12[[#This Row],[GHG emissions excl LULUCF]])) | AO14: =IF(Table12[[#This Row],[Net-zero target status]]<=1,"",IF(Table12[[#This Row],[NZ GHG year]]="","",(Table12[[#This Row],[residual LULUCF emissions in 2050]]-Table12[[#This Row],[2030 conditional NDCs]])/(Table12[[#This Row],[NZ GHG year]]-2030)/Table12[[#This Row],[2030 conditional NDCs]])) | AP14: =MAX('input site'!AH14:AS14) -> 10.670696 | AQ14: =IF(Table12[[#This Row],[Current Policies 2030 incl LULUCF]]>Table12[[#This Row],[Maximum inventory data]],"No","Yes") -> Yes | AR14: =IF(Table12[[#This Row],[Net-zero target status]]>=1.5,Table12[[#This Row],[residual LULUCF emissions in 2050]]/Table12[[#This Row],[GHG emissions excl LULUCF]],"") | AU14: ='input site'!BG14 -> 11.978 | AV14: ='input site'!BH14 -> 11.978 | AW14: =IF(Table12[[#This Row],[2030 unconditional NDCs]]="","",IF(F14="incl",Table12[[#This Row],[2030 unconditional NDCs]]-Table12[[#This Row],[LULUCF NDC uncond]],Table12[[#This Row],[2030 unconditional NDCs]])) | AX14: =IF(Table12[[#This Row],[2030 unconditional NDCs2]]="","",IF(F14="incl",Table12[[#This Row],[2030 unconditional NDCs2]]-Table12[[#This Row],[LULUCF NDC uncond]],Table12[[#This Row],[2030 unconditional NDCs2]])) | AY14: =IF(Table12[[#This Row],[2030 conditional NDCs]]="","",IF(F14="incl",Table12[[#This Row],[2030 conditional NDCs]]-Table12[[#This Row],[LULUCF NDC cond]],Table12[[#This Row],[2030 conditional NDCs]])) -> 11.978 | AZ14: =IF(Table12[[#This Row],[2030 conditional NDCs2]]="","",IF(F14="incl",Table12[[#This Row],[2030 conditional NDCs2]]-Table12[[#This Row],[LULUCF NDC cond]],Table12[[#This Row],[2030 conditional NDCs2]])) -> 11.978 | BA14: =VLOOKUP($G14,'Population90 20'!$C$6:$AU$231,37,FALSE) -> 2866374 | BB14: =VLOOKUP($G14,'Overview GDP (PPP)'!$C$6:$AI$231,33,FALSE) -> 35274375 | BC14: =Table12[[#This Row],[Income]]/Table12[[#This Row],[Population]] -> 12.306271 | BD14: =Table12[[#This Row],[GHG emissions excl LULUCF]]*1000000/Table12[[#This Row],[Population]] -> 3.6362286 | BE14: =VLOOKUP($G14,EGR2023_MASTER!$B$4:$S$38,14,FALSE) -> #N/A | BF14: =VLOOKUP($G14,EGR2023_MASTER!$B$4:$S$38,15,FALSE) -> #N/A | BG14: =VLOOKUP($G14,EGR2023_MASTER!$B$4:$S$38,16,FALSE) -> #N/A | BH14: =IF(AND(BE14="Y",AND(BF14="credible",BG14="Y")),"higher",IF(BG14="Y","lower",IF(AND(BG14="N",OR(BE14="Y",BF14="credible")),"lower","much lower"))) -> #N/A | BI14: =IF(AND($BF14="credible",BG14="Y"),"stronger","weak") -> #N/A | BJ14: =(Table12[[#This Row],[Current Policies 2030 excl LULUCF]]/Table12[[#This Row],[GHG emissions excl LULUCF]])^(1/(2030-2021))-1 -> -0.071603048 | BK14: =IF(Table12[[#This Row],[Net-zero target status]]<=1,"",IF(Table12[[#This Row],[NZ GHG year]]="","",((MAX(Table12[[#This Row],[residual LULUCF emissions in 2050]],0.1)/Table12[[#This Row],[Current Policies 2030 excl LULUCF]])^(1/(Table12[[#This Row],[NZ GHG year]]-2021))-1))) | BL14: =IF(Table12[[#This Row],[Net-zero target status]]<=1,"",IF(Table12[[#This Row],[NZ GHG year]]="","",((MAX(Table12[[#This Row],[residual LULUCF emissions in 2050]],0.1)/Table12[[#This Row],[GHG emissions excl LULUCF]])^(1/(Table12[[#This Row],[NZ GHG year]]-2021))-1))) | BM14: =IF(Table12[[#This Row],[Net-zero target status]]<=1,"",IF(Table12[[#This Row],[NZ GHG year]]="","",((MAX(Table12[[#This Row],[residual LULUCF emissions in 2050]],0.1)/AVERAGE(Table12[[#This Row],[2030 conditional NDCs]:[2030 conditional NDCs2]]))^(1/(Table12[[#This Row],[NZ GHG year]]-2021))-1))) | BR14: Albania | BT14: =IF(Table12[[#This Row],[Reduction rate 2021 to NZ target2]]="","",J14*(1+AN14)^(Table12[[#This Row],[NZ GHG year]]-2021))
A15: 0 | B15: 0 | C15: 12 | D15: 3 | E15: 7 | F15: ='input site'!M15 -> incl | G15: DZA | H15: Algeria | I15: =VLOOKUP($G15,'NZT data'!$B$3:$C$200,2,FALSE) -> 0 | J15: ='input site'!AS15 -> 259.62369 | K15: ='input site'!BS15 -> 258.88165 | L15: =IF(I15>=1,O15,K15) -> 258.88165 | M15: =IF(I15>=1,O15,N15) -> 122.83157 | N15: ='input site'!EV15 -> 122.83157 | Q15: =IF(I15>=1,O15,R15) -> 35.930255 | R15: ='[5]input site'!CN15 -> 35.930255 | T15: =Table12[[#This Row],[(Mt CO2 equivalent)]] -> Algeria | U15: =VLOOKUP($G15,'NZT data'!$B$3:$F$200,4,FALSE) -> 2110 | V15: =VLOOKUP($G15,'NZT data'!$B$3:$F$200,5,FALSE) | W15: =-IF('LUC NGHGI'!EC5="",MIN('LUC NGHGI'!DW5,0.1),MIN('LUC NGHGI'!EC5,0.1)) -> 8.93341 | X15: ='LUC NGHGI'!EC5 -> -8.93341 | Y15: ='LUC NGHGI'!DY5 -> -16 | Z15: ='LUC NGHGI'!DZ5 -> -8 | AA15: =Table12[[#This Row],[2021 emissions]] -> 259.62369 | AB15: ='LUC NGHGI'!DW5 -> -10.657188 | AC15: =IF(F15="incl",Table12[[#This Row],[GHG emissions incl LULUCF]]-Table12[[#This Row],[LULUCF emis-sions in 20213]],Table12[[#This Row],[GHG emissions incl LULUCF]]) -> 270.28088 | AD15: ='input site'!BS15 -> 258.88165 | AE15: ='LUC NGHGI'!EH5 -> -11.303418 | AF15: =IF(F15="incl",Table12[[#This Row],[Current Policies 2030 incl LULUCF]]-Table12[[#This Row],[LULUCF CurPol 2030]],Table12[[#This Row],[Current Policies 2030 incl LULUCF]]) -> 270.18507 | AG15: =IF(Table12[[#This Row],[Net-zero target status]]<=1,"",IF(Table12[[#This Row],[NZ GHG year]]="","",1000000000*(Table12[[#This Row],[residual LULUCF emissions in 2050]]-Table12[[#This Row],[GHG emissions excl LULUCF]])/(Table12[[#This Row],[NZ GHG year]]-2021)/Table12[[#This Row],[Population]])) | AH15: =IF(Table12[[#This Row],[Peak revised]]="Yes",IF(Table12[[#This Row],[Net-zero target status]]<=1,"",IF(Table12[[#This Row],[NZ GHG year]]="","",1000000000*(Table12[[#This Row],[residual LULUCF emissions in 2050]]-Table12[[#This Row],[GHG emissions excl LULUCF]])/(Table12[[#This Row],[NZ GHG year]]-2021)/Table12[[#This Row],[Population]])),"") | AI15: =MAX(0,(1000000*(Table12[[#This Row],[Current Policies 2030 excl LULUCF]]/2+Table12[[#This Row],[GHG emissions excl LULUCF]]/2)/Table12[[#This Row],[Population]]-$AI$8)*10)*$AI$10 -> 0 | AJ15: =IF(Table12[[#This Row],[Peak revised]]="No",IF(Table12[[#This Row],[Net-zero target status]]<=1,"",IF(Table12[[#This Row],[NZ GHG year]]="","",1000000000*(Table12[[#This Row],[residual LULUCF emissions in 2050]]-Table12[[#This Row],[Current Policies 2030 excl LULUCF]])/(Table12[[#This Row],[NZ GHG year]]-2021)/Table12[[#This Row],[Population]])),"") | AK15: =IF(Table12[[#This Row],[Formule no Peak (2)]]="","",Table12[[#This Row],[Penalty (1)]]+Table12[[#This Row],[Formule no Peak (2)]]) | AL15: =(Table12[[#This Row],[Current Policies 2030 excl LULUCF]]-Table12[[#This Row],[GHG emissions excl LULUCF]])/(2030-2021)/Table12[[#This Row],[GHG emissions excl LULUCF]] -> -3.9388357e-05 | AM15: =IF(Table12[[#This Row],[Net-zero target status]]<=1,"",IF(Table12[[#This Row],[NZ GHG year]]="","",(Table12[[#This Row],[residual LULUCF emissions in 2050]]-Table12[[#This Row],[Current Policies 2030 excl LULUCF]])/(Table12[[#This Row],[NZ GHG year]]-2030)/Table12[[#This Row],[Current Policies 2030 excl LULUCF]])) | AN15: =IF(Table12[[#This Row],[Net-zero target status]]<=1,"",IF(Table12[[#This Row],[NZ GHG year]]="","",(Table12[[#This Row],[residual LULUCF emissions in 2050]]-Table12[[#This Row],[GHG emissions excl LULUCF]])/(Table12[[#This Row],[NZ GHG year]]-2021)/Table12[[#This Row],[GHG emissions excl LULUCF]])) | AO15: =IF(Table12[[#This Row],[Net-zero target status]]<=1,"",IF(Table12[[#This Row],[NZ GHG year]]="","",(Table12[[#This Row],[residual LULUCF emissions in 2050]]-Table12[[#This Row],[2030 conditional NDCs]])/(Table12[[#This Row],[NZ GHG year]]-2030)/Table12[[#This Row],[2030 conditional NDCs]])) | AP15: =MAX('input site'!AH15:AS15) -> 267.17547 | AQ15: =IF(Table12[[#This Row],[Current Policies 2030 incl LULUCF]]>Table12[[#This Row],[Maximum inventory data]],"No","Yes") -> Yes | AR15: =IF(Table12[[#This Row],[Net-zero target status]]>=1.5,Table12[[#This Row],[residual LULUCF emissions in 2050]]/Table12[[#This Row],[GHG emissions excl LULUCF]],"") | AS15: ='input site'!BE15 -> 233.7343 | AT15: ='input site'!BF15 -> 233.7343 | AU15: ='input site'!BG15 -> 196.03522 | AV15: ='input site'!BH15 -> 196.03522 | AW15: =IF(Table12[[#This Row],[2030 unconditional NDCs]]="","",IF(F15="incl",Table12[[#This Row],[2030 unconditional NDCs]]-Table12[[#This Row],[LULUCF NDC uncond]],Table12[[#This Row],[2030 unconditional NDCs]])) -> 249.7343 | AX15: =IF(Table12[[#This Row],[2030 unconditional NDCs2]]="","",IF(F15="incl",Table12[[#This Row],[2030 unconditional NDCs2]]-Table12[[#This Row],[LULUCF NDC uncond]],Table12[[#This Row],[2030 unconditional NDCs2]])) -> 249.7343 | AY15: =IF(Table12[[#This Row],[2030 conditional NDCs]]="","",IF(F15="incl",Table12[[#This Row],[2030 conditional NDCs]]-Table12[[#This Row],[LULUCF NDC cond]],Table12[[#This Row],[2030 conditional NDCs]])) -> 204.03522 | AZ15: =IF(Table12[[#This Row],[2030 conditional NDCs2]]="","",IF(F15="incl",Table12[[#This Row],[2030 conditional NDCs2]]-Table12[[#This Row],[LULUCF NDC cond]],Table12[[#This Row],[2030 conditional NDCs2]])) -> 204.03522 | BA15: =VLOOKUP($G15,'Population90 20'!$C$6:$AU$231,37,FALSE) -> 45350148 | BB15: =VLOOKUP($G15,'Overview GDP (PPP)'!$C$6:$AI$231,33,FALSE) -> 5.8638961e+08 | BC15: =Table12[[#This Row],[Income]]/Table12[[#This Row],[Population]] -> 12.930269 | BD15: =Table12[[#This Row],[GHG emissions excl LULUCF]]*1000000/Table12[[#This Row],[Population]] -> 5.9598677 | BE15: =VLOOKUP($G15,EGR2023_MASTER!$B$4:$S$38,14,FALSE) -> #N/A | BF15: =VLOOKUP($G15,EGR2023_MASTER!$B$4:$S$38,15,FALSE) -> #N/A | BG15: =VLOOKUP($G15,EGR2023_MASTER!$B$4:$S$38,16,FALSE) -> #N/A | BH15: =IF(AND(BE15="Y",AND(BF15="credible",BG15="Y")),"higher",IF(BG15="Y","lower",IF(AND(BG15="N",OR(BE15="Y",BF15="credible")),"lower","much lower"))) -> #N/A | BI15: =IF(AND($BF15="credible",BG15="Y"),"stronger","weak") -> #N/A | BJ15: =(Table12[[#This Row],[Current Policies 2030 excl LULUCF]]/Table12[[#This Row],[GHG emissions excl LULUCF]])^(1/(2030-2021))-1 -> -3.9394565e-05 | BK15: =IF(Table12[[#This Row],[Net-zero target status]]<=1,"",IF(Table12[[#This Row],[NZ GHG year]]="","",((MAX(Table12[[#This Row],[residual LULUCF emissions in 2050]],0.1)/Table12[[#This Row],[Current Policies 2030 excl LULUCF]])^(1/(Table12[[#This Row],[NZ GHG year]]-2021))-1))) | BL15: =IF(Table12[[#This Row],[Net-zero target status]]<=1,"",IF(Table12[[#This Row],[NZ GHG year]]="","",((MAX(Table12[[#This Row],[residual LULUCF emissions in 2050]],0.1)/Table12[[#This Row],[GHG emissions excl LULUCF]])^(1/(Table12[[#This Row],[NZ GHG year]]-2021))-1))) | BM15: =IF(Table12[[#This Row],[Net-zero target status]]<=1,"",IF(Table12[[#This Row],[NZ GHG year]]="","",((MAX(Table12[[#This Row],[residual LULUCF emissions in 2050]],0.1)/AVERAGE(Table12[[#This Row],[2030 conditional NDCs]:[2030 conditional NDCs2]]))^(1/(Table12[[#This Row],[NZ GHG year]]-2021))-1))) | BR15: Algeria | BT15: =IF(Table12[[#This Row],[Reduction rate 2021 to NZ target2]]="","",J15*(1+AN15)^(Table12[[#This Row],[NZ GHG year]]-2021))
A16: 0 | B16: 0 | C16: 16 | D16: 4 | E16: 24 | F16: ='input site'!M16 -> excl | G16: ASM | H16: American Samoa | I16: 0 | J16: ='input site'!AS16 -> 0 | K16: ='input site'!BS16 -> 0 | L16: =IF(I16>=1,O16,K16) -> 0 | M16: =IF(I16>=1,O16,N16) -> 0 | N16: ='input site'!EV16 -> 0 | Q16: =IF(I16>=1,O16,R16) -> 0.0062334932 | R16: ='[5]input site'!CN16 -> 0.0062334932 | T16: =Table12[[#This Row],[(Mt CO2 equivalent)]] -> American Samoa | U16: 2100 | V16: 2100 | W16: =-IF('LUC NGHGI'!EC6="",MIN('LUC NGHGI'!DW6,0.1),MIN('LUC NGHGI'!EC6,0.1)) -> 0.757 | X16: ='LUC NGHGI'!EC6 -> -0.757 | Y16: ='LUC NGHGI'!DY6 -> -0.757 | Z16: ='LUC NGHGI'!DZ6 -> -0.757 | AA16: =Table12[[#This Row],[2021 emissions]] -> 0 | AB16: ='LUC NGHGI'!DW6 -> -0.63783226 | AC16: =IF(F16="incl",Table12[[#This Row],[GHG emissions incl LULUCF]]-Table12[[#This Row],[LULUCF emis-sions in 20213]],Table12[[#This Row],[GHG emissions incl LULUCF]]) -> 0 | AD16: ='input site'!BS16 -> 0 | AE16: ='LUC NGHGI'!EH6 -> -0.70635243 | AF16: =IF(F16="incl",Table12[[#This Row],[Current Policies 2030 incl LULUCF]]-Table12[[#This Row],[LULUCF CurPol 2030]],Table12[[#This Row],[Current Policies 2030 incl LULUCF]]) -> 0 | AG16: =IF(Table12[[#This Row],[Net-zero target status]]<=1,"",IF(Table12[[#This Row],[NZ GHG year]]="","",1000000000*(Table12[[#This Row],[residual LULUCF emissions in 2050]]-Table12[[#This Row],[GHG emissions excl LULUCF]])/(Table12[[#This Row],[NZ GHG year]]-2021)/Table12[[#This Row],[Population]])) | AH16: =IF(Table12[[#This Row],[Peak revised]]="Yes",IF(Table12[[#This Row],[Net-zero target status]]<=1,"",IF(Table12[[#This Row],[NZ GHG year]]="","",1000000000*(Table12[[#This Row],[residual LULUCF emissions in 2050]]-Table12[[#This Row],[GHG emissions excl LULUCF]])/(Table12[[#This Row],[NZ GHG year]]-2021)/Table12[[#This Row],[Population]])),"") | AI16: =MAX(0,(1000000*(Table12[[#This Row],[Current Policies 2030 excl LULUCF]]/2+Table12[[#This Row],[GHG emissions excl LULUCF]]/2)/Table12[[#This Row],[Population]]-$AI$8)*10)*$AI$10 -> 0 | AJ16: =IF(Table12[[#This Row],[Peak revised]]="No",IF(Table12[[#This Row],[Net-zero target status]]<=1,"",IF(Table12[[#This Row],[NZ GHG year]]="","",1000000000*(Table12[[#This Row],[residual LULUCF emissions in 2050]]-Table12[[#This Row],[Current Policies 2030 excl LULUCF]])/(Table12[[#This Row],[NZ GHG year]]-2021)/Table12[[#This Row],[Population]])),"") | AK16: =IF(Table12[[#This Row],[Formule no Peak (2)]]="","",Table12[[#This Row],[Penalty (1)]]+Table12[[#This Row],[Formule no Peak (2)]]) | AL16: =(Table12[[#This Row],[Current Policies 2030 excl LULUCF]]-Table12[[#This Row],[GHG emissions excl LULUCF]])/(2030-2021)/Table12[[#This Row],[GHG emissions excl LULUCF]] -> #DIV/0! | AM16: =IF(Table12[[#This Row],[Net-zero target status]]<=1,"",IF(Table12[[#This Row],[NZ GHG year]]="","",(Table12[[#This Row],[residual LULUCF emissions in 2050]]-Table12[[#This Row],[Current Policies 2030 excl LULUCF]])/(Table12[[#This Row],[NZ GHG year]]-2030)/Table12[[#This Row],[Current Policies 2030 excl LULUCF]])) | AN16: =IF(Table12[[#This Row],[Net-zero target status]]<=1,"",IF(Table12[[#This Row],[NZ GHG year]]="","",(Table12[[#This Row],[residual LULUCF emissions in 2050]]-Table12[[#This Row],[GHG emissions excl LULUCF]])/(Table12[[#This Row],[NZ GHG year]]-2021)/Table12[[#This Row],[GHG emissions excl LULUCF]])) | AO16: =IF(Table12[[#This Row],[Net-zero target status]]<=1,"",IF(Table12[[#This Row],[NZ GHG year]]="","",(Table12[[#This Row],[residual LULUCF emissions in 2050]]-Table12[[#This Row],[2030 conditional NDCs]])/(Table12[[#This Row],[NZ GHG year]]-2030)/Table12[[#This Row],[2030 conditional NDCs]])) | AP16: =MAX('input site'!AH16:AS16) -> 0 | AQ16: =IF(Table12[[#This Row],[Current Policies 2030 incl LULUCF]]>Table12[[#This Row],[Maximum inventory data]],"No","Yes") -> Yes | AR16: =IF(Table12[[#This Row],[Net-zero target status]]>=1.5,Table12[[#This Row],[residual LULUCF emissions in 2050]]/Table12[[#This Row],[GHG emissions excl LULUCF]],"") | AW16: =IF(Table12[[#This Row],[2030 unconditional NDCs]]="","",IF(F16="incl",Table12[[#This Row],[2030 unconditional NDCs]]-Table12[[#This Row],[LULUCF NDC uncond]],Table12[[#This Row],[2030 unconditional NDCs]])) | AX16: =IF(Table12[[#This Row],[2030 unconditional NDCs2]]="","",IF(F16="incl",Table12[[#This Row],[2030 unconditional NDCs2]]-Table12[[#This Row],[LULUCF NDC uncond]],Table12[[#This Row],[2030 unconditional NDCs2]])) | AY16: =IF(Table12[[#This Row],[2030 conditional NDCs]]="","",IF(F16="incl",Table12[[#This Row],[2030 conditional NDCs]]-Table12[[#This Row],[LULUCF NDC cond]],Table12[[#This Row],[2030 conditional NDCs]])) | AZ16: =IF(Table12[[#This Row],[2030 conditional NDCs2]]="","",IF(F16="incl",Table12[[#This Row],[2030 conditional NDCs2]]-Table12[[#This Row],[LULUCF NDC cond]],Table12[[#This Row],[2030 conditional NDCs2]])) | BA16: =VLOOKUP($G16,'Population90 20'!$C$6:$AU$231,37,FALSE) -> 55030 | BB16: =VLOOKUP($G16,'Overview GDP (PPP)'!$C$6:$AI$231,33,FALSE) -> 486064.72 | BC16: =Table12[[#This Row],[Income]]/Table12[[#This Row],[Population]] -> 8.8327225 | BD16: =Table12[[#This Row],[GHG emissions excl LULUCF]]*1000000/Table12[[#This Row],[Population]] -> 0 | BE16: =VLOOKUP($G16,EGR2023_MASTER!$B$4:$S$38,14,FALSE) -> #N/A | BF16: =VLOOKUP($G16,EGR2023_MASTER!$B$4:$S$38,15,FALSE) -> #N/A | BG16: =VLOOKUP($G16,EGR2023_MASTER!$B$4:$S$38,16,FALSE) -> #N/A | BH16: =IF(AND(BE16="Y",AND(BF16="credible",BG16="Y")),"higher",IF(BG16="Y","lower",IF(AND(BG16="N",OR(BE16="Y",BF16="credible")),"lower","much lower"))) -> #N/A | BI16: =IF(AND($BF16="credible",BG16="Y"),"stronger","weak") -> #N/A | BJ16: =(Table12[[#This Row],[Current Policies 2030 excl LULUCF]]/Table12[[#This Row],[GHG emissions excl LULUCF]])^(1/(2030-2021))-1 -> #DIV/0! | BK16: =IF(Table12[[#This Row],[Net-zero target status]]<=1,"",IF(Table12[[#This Row],[NZ GHG year]]="","",((MAX(Table12[[#This Row],[residual LULUCF emissions in 2050]],0.1)/Table12[[#This Row],[Current Policies 2030 excl LULUCF]])^(1/(Table12[[#This Row],[NZ GHG year]]-2021))-1))) | BL16: =IF(Table12[[#This Row],[Net-zero target status]]<=1,"",IF(Table12[[#This Row],[NZ GHG year]]="","",((MAX(Table12[[#This Row],[residual LULUCF emissions in 2050]],0.1)/Table12[[#This Row],[GHG emissions excl LULUCF]])^(1/(Table12[[#This Row],[NZ GHG year]]-2021))-1))) | BM16: =IF(Table12[[#This Row],[Net-zero target status]]<=1,"",IF(Table12[[#This Row],[NZ GHG year]]="","",((MAX(Table12[[#This Row],[residual LULUCF emissions in 2050]],0.1)/AVERAGE(Table12[[#This Row],[2030 conditional NDCs]:[2030 conditional NDCs2]]))^(1/(Table12[[#This Row],[NZ GHG year]]-2021))-1))) | BR16: American Samoa | BT16: =IF(Table12[[#This Row],[Reduction rate 2021 to NZ target2]]="","",J16*(1+AN16)^(Table12[[#This Row],[NZ GHG year]]-2021))
A17: 0 | B17: 0 | C17: 20 | D17: 5 | E17: 11 | F17: ='input site'!M17 -> excl | G17: AND | H17: Andorra | I17: =VLOOKUP($G17,'NZT data'!$B$3:$C$200,2,FALSE) -> 3 | J17: ='input site'!AS17 -> 0.49976677 | K17: ='input site'!BS17 -> 0.27884462 | L17: =IF(I17>=1,O17,K17) -> 0 | M17: =IF(I17>=1,O17,N17) -> 0 | N17: ='input site'!EV17 -> 0.10690788 | Q17: =IF(I17>=1,O17,R17) -> 0 | R17: ='[5]input site'!CN17 -> 0 | T17: =Table12[[#This Row],[(Mt CO2 equivalent)]] -> Andorra | U17: =VLOOKUP($G17,'NZT data'!$B$3:$F$200,4,FALSE) -> 2050 | V17: =VLOOKUP($G17,'NZT data'!$B$3:$F$200,5,FALSE) -> 2050 | W17: =-IF('LUC NGHGI'!EC7="",MIN('LUC NGHGI'!DW7,0.1),MIN('LUC NGHGI'!EC7,0.1)) -> -0.1 | X17: ='LUC NGHGI'!EC7 -> 0.14 | Y17: ='LUC NGHGI'!DY7 -> -0.14005074 | Z17: ='LUC NGHGI'!DZ7 -> -0.14005074 | AA17: =Table12[[#This Row],[2021 emissions]] -> 0.49976677 | AB17: ='LUC NGHGI'!DW7 -> -0.14024416 | AC17: =IF(F17="incl",Table12[[#This Row],[GHG emissions incl LULUCF]]-Table12[[#This Row],[LULUCF emis-sions in 20213]],Table12[[#This Row],[GHG emissions incl LULUCF]]) -> 0.49976677 | AD17: ='input site'!BS17 -> 0.27884462 | AE17: ='LUC NGHGI'!EH7 -> -0.14502097 | AF17: =IF(F17="incl",Table12[[#This Row],[Current Policies 2030 incl LULUCF]]-Table12[[#This Row],[LULUCF CurPol 2030]],Table12[[#This Row],[Current Policies 2030 incl LULUCF]]) -> 0.27884462 | AH17: =IF(Table12[[#This Row],[Peak revised]]="Yes",IF(Table12[[#This Row],[Net-zero target status]]<=1,"",IF(Table12[[#This Row],[NZ GHG year]]="","",1000000000*(Table12[[#This Row],[residual LULUCF emissions in 2050]]-Table12[[#This Row],[GHG emissions excl LULUCF]])/(Table12[[#This Row],[NZ GHG year]]-2021)/Table12[[#This Row],[Population]])),"") -> #DIV/0! | AI17: =MAX(0,(1000000*(Table12[[#This Row],[Current Policies 2030 excl LULUCF]]/2+Table12[[#This Row],[GHG emissions excl LULUCF]]/2)/Table12[[#This Row],[Population]]-$AI$8)*10)*$AI$10 -> #DIV/0! | AJ17: =IF(Table12[[#This Row],[Peak revised]]="No",IF(Table12[[#This Row],[Net-zero target status]]<=1,"",IF(Table12[[#This Row],[NZ GHG year]]="","",1000000000*(Table12[[#This Row],[residual LULUCF emissions in 2050]]-Table12[[#This Row],[Current Policies 2030 excl LULUCF]])/(Table12[[#This Row],[NZ GHG year]]-2021)/Table12[[#This Row],[Population]])),"") | AK17: =IF(Table12[[#This Row],[Formule no Peak (2)]]="","",Table12[[#This Row],[Penalty (1)]]+Table12[[#This Row],[Formule no Peak (2)]]) | AL17: =(Table12[[#This Row],[Current Policies 2030 excl LULUCF]]-Table12[[#This Row],[GHG emissions excl LULUCF]])/(2030-2021)/Table12[[#This Row],[GHG emissions excl LULUCF]] -> -0.049116721 | AM17: =IF(Table12[[#This Row],[Net-zero target status]]<=1,"",IF(Table12[[#This Row],[NZ GHG year]]="","",(Table12[[#This Row],[residual LULUCF emissions in 2050]]-Table12[[#This Row],[Current Policies 2030 excl LULUCF]])/(Table12[[#This Row],[NZ GHG year]]-2030)/Table12[[#This Row],[Current Policies 2030 excl LULUCF]])) -> -0.067931133 | AN17: =IF(Table12[[#This Row],[Net-zero target status]]<=1,"",IF(Table12[[#This Row],[NZ GHG year]]="","",(Table12[[#This Row],[residual LULUCF emissions in 2050]]-Table12[[#This Row],[GHG emissions excl LULUCF]])/(Table12[[#This Row],[NZ GHG year]]-2021)/Table12[[#This Row],[GHG emissions excl LULUCF]])) -> -0.041382529 | AO17: =IF(Table12[[#This Row],[Net-zero target status]]<=1,"",IF(Table12[[#This Row],[NZ GHG year]]="","",(Table12[[#This Row],[residual LULUCF emissions in 2050]]-Table12[[#This Row],[2030 conditional NDCs]])/(Table12[[#This Row],[NZ GHG year]]-2030)/Table12[[#This Row],[2030 conditional NDCs]])) -> -0.064844724 | AP17: =MAX('input site'!AH17:AS17) -> 0.53152265 | AQ17: =IF(Table12[[#This Row],[Current Policies 2030 incl LULUCF]]>Table12[[#This Row],[Maximum inventory data]],"No","Yes") -> Yes | AR17: =IF(Table12[[#This Row],[Net-zero target status]]>=1.5,Table12[[#This Row],[residual LULUCF emissions in 2050]]/Table12[[#This Row],[GHG emissions excl LULUCF]],"") -> -0.20009334 | AS17: ='input site'!BE17 -> 0.33682 | AT17: ='input site'!BF17 -> 0.33682 | AU17: ='input site'!BG17 -> 0.33682 | AV17: ='input site'!BH17 -> 0.33682 | AW17: =IF(Table12[[#This Row],[2030 unconditional NDCs]]="","",IF(F17="incl",Table12[[#This Row],[2030 unconditional NDCs]]-Table12[[#This Row],[LULUCF NDC uncond]],Table12[[#This Row],[2030 unconditional NDCs]])) -> 0.33682 | AX17: =IF(Table12[[#This Row],[2030 unconditional NDCs2]]="","",IF(F17="incl",Table12[[#This Row],[2030 unconditional NDCs2]]-Table12[[#This Row],[LULUCF NDC uncond]],Table12[[#This Row],[2030 unconditional NDCs2]])) -> 0.33682 | AY17: =IF(Table12[[#This Row],[2030 conditional NDCs]]="","",IF(F17="incl",Table12[[#This Row],[2030 conditional NDCs]]-Table12[[#This Row],[LULUCF NDC cond]],Table12[[#This Row],[2030 conditional NDCs]])) -> 0.33682 | AZ17: =IF(Table12[[#This Row],[2030 conditional NDCs2]]="","",IF(F17="incl",Table12[[#This Row],[2030 conditional NDCs2]]-Table12[[#This Row],[LULUCF NDC cond]],Table12[[#This Row],[2030 conditional NDCs2]])) -> 0.33682 | BB17: =VLOOKUP($G17,'Overview GDP (PPP)'!$C$6:$AI$231,33,FALSE) -> 0 | BD17: =Table12[[#This Row],[GHG emissions excl LULUCF]]*1000000/Table12[[#This Row],[Population]] -> #DIV/0! | BE17: =VLOOKUP($G17,EGR2023_MASTER!$B$4:$S$38,14,FALSE) -> #N/A | BF17: =VLOOKUP($G17,EGR2023_MASTER!$B$4:$S$38,15,FALSE) -> #N/A | BG17: =VLOOKUP($G17,EGR2023_MASTER!$B$4:$S$38,16,FALSE) -> #N/A | BH17: =IF(AND(BE17="Y",AND(BF17="credible",BG17="Y")),"higher",IF(BG17="Y","lower",IF(AND(BG17="N",OR(BE17="Y",BF17="credible")),"lower","much lower"))) -> #N/A | BI17: =IF(AND($BF17="credible",BG17="Y"),"stronger","weak") -> #N/A | BJ17: =(Table12[[#This Row],[Current Policies 2030 excl LULUCF]]/Table12[[#This Row],[GHG emissions excl LULUCF]])^(1/(2030-2021))-1 -> -0.062774972 | BK17: =IF(Table12[[#This Row],[Net-zero target status]]<=1,"",IF(Table12[[#This Row],[NZ GHG year]]="","",((MAX(Table12[[#This Row],[residual LULUCF emissions in 2050]],0.1)/Table12[[#This Row],[Current Policies 2030 excl LULUCF]])^(1/(Table12[[#This Row],[NZ GHG year]]-2021))-1))) -> -0.034743621 | BL17: =IF(Table12[[#This Row],[Net-zero target status]]<=1,"",IF(Table12[[#This Row],[NZ GHG year]]="","",((MAX(Table12[[#This Row],[residual LULUCF emissions in 2050]],0.1)/Table12[[#This Row],[GHG emissions excl LULUCF]])^(1/(Table12[[#This Row],[NZ GHG year]]-2021))-1))) -> -0.053970731 | BM17: =IF(Table12[[#This Row],[Net-zero target status]]<=1,"",IF(Table12[[#This Row],[NZ GHG year]]="","",((MAX(Table12[[#This Row],[residual LULUCF emissions in 2050]],0.1)/AVERAGE(Table12[[#This Row],[2030 conditional NDCs]:[2030 conditional NDCs2]]))^(1/(Table12[[#This Row],[NZ GHG year]]-2021))-1))) -> -0.041010468 | BR17: Andorra | BT17: =IF(Table12[[#This Row],[Reduction rate 2021 to NZ target2]]="","",J17*(1+AN17)^(Table12[[#This Row],[NZ GHG year]]-2021)) -> 0.14671761
A18: 0 | B18: 0 | C18: 24 | D18: 6 | E18: 26 | F18: ='input site'!M18 -> incl | G18: AGO | H18: Angola | I18: =VLOOKUP($G18,'NZT data'!$B$3:$C$200,2,FALSE) -> 1 | J18: ='input site'!AS18 -> 157.57325 | K18: ='input site'!BS18 -> 187.01658 | L18: =IF(I18>=1,O18,K18) -> 0 | M18: =IF(I18>=1,O18,N18) -> 0 | N18: ='input site'!EV18 -> 117.79556 | Q18: =IF(I18>=1,O18,R18) -> 0 | R18: ='[5]input site'!CN18 -> 159.46108 | S18: 2050 | T18: =Table12[[#This Row],[(Mt CO2 equivalent)]] -> Angola | U18: =VLOOKUP($G18,'NZT data'!$B$3:$F$200,4,FALSE) -> 2110 | V18: =VLOOKUP($G18,'NZT data'!$B$3:$F$200,5,FALSE) -> 2125 | W18: =-IF('LUC NGHGI'!EC8="",MIN('LUC NGHGI'!DW8,0.1),MIN('LUC NGHGI'!EC8,0.1)) -> -0.1 | X18: ='LUC NGHGI'!EC8 -> 68.557628 | Y18: ='LUC NGHGI'!DY8 -> 68.557628 | Z18: ='LUC NGHGI'!DZ8 -> 68.557628 | AA18: =Table12[[#This Row],[2021 emissions]] -> 157.57325 | AB18: ='LUC NGHGI'!DW8 -> 69.814562 | AC18: =IF(F18="incl",Table12[[#This Row],[GHG emissions incl LULUCF]]-Table12[[#This Row],[LULUCF emis-sions in 20213]],Table12[[#This Row],[GHG emissions incl LULUCF]]) -> 87.758688 | AD18: ='input site'!BS18 -> 187.01658 | AE18: ='LUC NGHGI'!EH8 -> 54.965158 | AF18: =IF(F18="incl",Table12[[#This Row],[Current Policies 2030 incl LULUCF]]-Table12[[#This Row],[LULUCF CurPol 2030]],Table12[[#This Row],[Current Policies 2030 incl LULUCF]]) -> 132.05143 | AG18: =IF(Table12[[#This Row],[Net-zero target status]]<=1,"",IF(Table12[[#This Row],[NZ GHG year]]="","",1000000000*(Table12[[#This Row],[residual LULUCF emissions in 2050]]-Table12[[#This Row],[GHG emissions excl LULUCF]])/(Table12[[#This Row],[NZ GHG year]]-2021)/Table12[[#This Row],[Population]])) | AH18: =IF(Table12[[#This Row],[Peak revised]]="Yes",IF(Table12[[#This Row],[Net-zero target status]]<=1,"",IF(Table12[[#This Row],[NZ GHG year]]="","",1000000000*(Table12[[#This Row],[residual LULUCF emissions in 2050]]-Table12[[#This Row],[GHG emissions excl LULUCF]])/(Table12[[#This Row],[NZ GHG year]]-2021)/Table12[[#This Row],[Population]])),"") | AI18: =MAX(0,(1000000*(Table12[[#This Row],[Current Policies 2030 excl LULUCF]]/2+Table12[[#This Row],[GHG emissions excl LULUCF]]/2)/Table12[[#This Row],[Population]]-$AI$8)*10)*$AI$10 -> 0 | AJ18: =IF(Table12[[#This Row],[Peak revised]]="No",IF(Table12[[#This Row],[Net-zero target status]]<=1,"",IF(Table12[[#This Row],[NZ GHG year]]="","",1000000000*(Table12[[#This Row],[residual LULUCF emissions in 2050]]-Table12[[#This Row],[Current Policies 2030 excl LULUCF]])/(Table12[[#This Row],[NZ GHG year]]-2021)/Table12[[#This Row],[Population]])),"") | AK18: =IF(Table12[[#This Row],[Formule no Peak (2)]]="","",Table12[[#This Row],[Penalty (1)]]+Table12[[#This Row],[Formule no Peak (2)]]) | AL18: =(Table12[[#This Row],[Current Policies 2030 excl LULUCF]]-Table12[[#This Row],[GHG emissions excl LULUCF]])/(2030-2021)/Table12[[#This Row],[GHG emissions excl LULUCF]] -> 0.056078953 | AM18: =IF(Table12[[#This Row],[Net-zero target status]]<=1,"",IF(Table12[[#This Row],[NZ GHG year]]="","",(Table12[[#This Row],[residual LULUCF emissions in 2050]]-Table12[[#This Row],[Current Policies 2030 excl LULUCF]])/(Table12[[#This Row],[NZ GHG year]]-2030)/Table12[[#This Row],[Current Policies 2030 excl LULUCF]])) | AN18: =IF(Table12[[#This Row],[Net-zero target status]]<=1,"",IF(Table12[[#This Row],[NZ GHG year]]="","",(Table12[[#This Row],[residual LULUCF emissions in 2050]]-Table12[[#This Row],[GHG emissions excl LULUCF]])/(Table12[[#This Row],[NZ GHG year]]-2021)/Table12[[#This Row],[GHG emissions excl LULUCF]])) | AO18: =IF(Table12[[#This Row],[Net-zero target status]]<=1,"",IF(Table12[[#This Row],[NZ GHG year]]="","",(Table12[[#This Row],[residual LULUCF emissions in 2050]]-Table12[[#This Row],[2030 conditional NDCs]])/(Table12[[#This Row],[NZ GHG year]]-2030)/Table12[[#This Row],[2030 conditional NDCs]])) | AP18: =MAX('input site'!AH18:AS18) -> 179.95235 | AQ18: =IF(Table12[[#This Row],[Current Policies 2030 incl LULUCF]]>Table12[[#This Row],[Maximum inventory data]],"No","Yes") -> No | AR18: =IF(Table12[[#This Row],[Net-zero target status]]>=1.5,Table12[[#This Row],[residual LULUCF emissions in 2050]]/Table12[[#This Row],[GHG emissions excl LULUCF]],"") | AS18: ='input site'!BE18 -> 93.2842 | AT18: ='input site'!BF18 -> 93.2842 | AU18: ='input site'!BG18 -> 82.4372 | AV18: ='input site'!BH18 -> 82.4372 | AW18: =IF(Table12[[#This Row],[2030 unconditional NDCs]]="","",IF(F18="incl",Table12[[#This Row],[2030 unconditional NDCs]]-Table12[[#This Row],[LULUCF NDC uncond]],Table12[[#This Row],[2030 unconditional NDCs]])) -> 24.726572 | AX18: =IF(Table12[[#This Row],[2030 unconditional NDCs2]]="","",IF(F18="incl",Table12[[#This Row],[2030 unconditional NDCs2]]-Table12[[#This Row],[LULUCF NDC uncond]],Table12[[#This Row],[2030 unconditional NDCs2]])) -> 24.726572 | AY18: =IF(Table12[[#This Row],[2030 conditional NDCs]]="","",IF(F18="incl",Table12[[#This Row],[2030 conditional NDCs]]-Table12[[#This Row],[LULUCF NDC cond]],Table12[[#This Row],[2030 conditional NDCs]])) -> 13.879572 | AZ18: =IF(Table12[[#This Row],[2030 conditional NDCs2]]="","",IF(F18="incl",Table12[[#This Row],[2030 conditional NDCs2]]-Table12[[#This Row],[LULUCF NDC cond]],Table12[[#This Row],[2030 conditional NDCs2]])) -> 13.879572 | BA18: =VLOOKUP($G18,'Population90 20'!$C$6:$AU$231,37,FALSE) -> 35027343 | BB18: =VLOOKUP($G18,'Overview GDP (PPP)'!$C$6:$AI$231,33,FALSE) -> 1.7639597e+08 | BC18: =Table12[[#This Row],[Income]]/Table12[[#This Row],[Population]] -> 5.0359506 | BD18: =Table12[[#This Row],[GHG emissions excl LULUCF]]*1000000/Table12[[#This Row],[Population]] -> 2.5054338 | BE18: =VLOOKUP($G18,EGR2023_MASTER!$B$4:$S$38,14,FALSE) -> #N/A | BF18: =VLOOKUP($G18,EGR2023_MASTER!$B$4:$S$38,15,FALSE) -> #N/A | BG18: =VLOOKUP($G18,EGR2023_MASTER!$B$4:$S$38,16,FALSE) -> #N/A | BH18: =IF(AND(BE18="Y",AND(BF18="credible",BG18="Y")),"higher",IF(BG18="Y","lower",IF(AND(BG18="N",OR(BE18="Y",BF18="credible")),"lower","much lower"))) -> #N/A | BI18: =IF(AND($BF18="credible",BG18="Y"),"stronger","weak") -> #N/A | BJ18: =(Table12[[#This Row],[Current Policies 2030 excl LULUCF]]/Table12[[#This Row],[GHG emissions excl LULUCF]])^(1/(2030-2021))-1 -> 0.046446421 | BK18: =IF(Table12[[#This Row],[Net-zero target status]]<=1,"",IF(Table12[[#This Row],[NZ GHG year]]="","",((MAX(Table12[[#This Row],[residual LULUCF emissions in 2050]],0.1)/Table12[[#This Row],[Current Policies 2030 excl LULUCF]])^(1/(Table12[[#This Row],[NZ GHG year]]-2021))-1))) | BL18: =IF(Table12[[#This Row],[Net-zero target status]]<=1,"",IF(Table12[[#This Row],[NZ GHG year]]="","",((MAX(Table12[[#This Row],[residual LULUCF emissions in 2050]],0.1)/Table12[[#This Row],[GHG emissions excl LULUCF]])^(1/(Table12[[#This Row],[NZ GHG year]]-2021))-1))) | BM18: =IF(Table12[[#This Row],[Net-zero target status]]<=1,"",IF(Table12[[#This Row],[NZ GHG year]]="","",((MAX(Table12[[#This Row],[residual LULUCF emissions in 2050]],0.1)/AVERAGE(Table12[[#This Row],[2030 conditional NDCs]:[2030 conditional NDCs2]]))^(1/(Table12[[#This Row],[NZ GHG year]]-2021))-1))) | BR18: Angola | BT18: =IF(Table12[[#This Row],[Reduction rate 2021 to NZ target2]]="","",J18*(1+AN18)^(Table12[[#This Row],[NZ GHG year]]-2021))
A19: 0 | B19: 0 | C19: 660 | D19: 171 | E19: 4 | F19: ='input site'!M19 -> excl | G19: AIA | H19: Anguilla | I19: 0 | J19: ='input site'!AS19 -> 0.14020385 | K19: ='input site'!BS19 -> 0.17288105 | L19: =IF(I19>=1,O19,K19) -> 0.17288105 | M19: =IF(I19>=1,O19,N19) -> 0.079466083 | N19: ='input site'!EV19 -> 0.079466083 | Q19: =IF(I19>=1,O19,R19) -> 0.0036527076 | R19: ='[5]input site'!CN19 -> 0.0036527076 | T19: =Table12[[#This Row],[(Mt CO2 equivalent)]] -> Anguilla | U19: 2100 | V19: 2100 | W19: =-IF('LUC NGHGI'!EC9="",MIN('LUC NGHGI'!DW9,0.1),MIN('LUC NGHGI'!EC9,0.1)) -> 0 | X19: ='LUC NGHGI'!EC9 | Y19: ='LUC NGHGI'!DY9 | Z19: ='LUC NGHGI'!DZ9 | AA19: =Table12[[#This Row],[2021 emissions]] -> 0.14020385 | AB19: ='LUC NGHGI'!DW9 -> 0 | AC19: =IF(F19="incl",Table12[[#This Row],[GHG emissions incl LULUCF]]-Table12[[#This Row],[LULUCF emis-sions in 20213]],Table12[[#This Row],[GHG emissions incl LULUCF]]) -> 0.14020385 | AD19: ='input site'!BS19 -> 0.17288105 | AE19: ='LUC NGHGI'!EH9 | AF19: =IF(F19="incl",Table12[[#This Row],[Current Policies 2030 incl LULUCF]]-Table12[[#This Row],[LULUCF CurPol 2030]],Table12[[#This Row],[Current Policies 2030 incl LULUCF]]) -> 0.17288105 | AG19: =IF(Table12[[#This Row],[Net-zero target status]]<=1,"",IF(Table12[[#This Row],[NZ GHG year]]="","",1000000000*(Table12[[#This Row],[residual LULUCF emissions in 2050]]-Table12[[#This Row],[GHG emissions excl LULUCF]])/(Table12[[#This Row],[NZ GHG year]]-2021)/Table12[[#This Row],[Population]])) | AH19: =IF(Table12[[#This Row],[Peak revised]]="Yes",IF(Table12[[#This Row],[Net-zero target status]]<=1,"",IF(Table12[[#This Row],[NZ GHG year]]="","",1000000000*(Table12[[#This Row],[residual LULUCF emissions in 2050]]-Table12[[#This Row],[GHG emissions excl LULUCF]])/(Table12[[#This Row],[NZ GHG year]]-2021)/Table12[[#This Row],[Population]])),"") | AI19: =MAX(0,(1000000*(Table12[[#This Row],[Current Policies 2030 excl LULUCF]]/2+Table12[[#This Row],[GHG emissions excl LULUCF]]/2)/Table12[[#This Row],[Population]]-$AI$8)*10)*$AI$10 -> -327.85587 | AJ19: =IF(Table12[[#This Row],[Peak revised]]="No",IF(Table12[[#This Row],[Net-zero target status]]<=1,"",IF(Table12[[#This Row],[NZ GHG year]]="","",1000000000*(Table12[[#This Row],[residual LULUCF emissions in 2050]]-Table12[[#This Row],[Current Policies 2030 excl LULUCF]])/(Table12[[#This Row],[NZ GHG year]]-2021)/Table12[[#This Row],[Population]])),"") | AK19: =IF(Table12[[#This Row],[Formule no Peak (2)]]="","",Table12[[#This Row],[Penalty (1)]]+Table12[[#This Row],[Formule no Peak (2)]]) | AL19: =(Table12[[#This Row],[Current Policies 2030 excl LULUCF]]-Table12[[#This Row],[GHG emissions excl LULUCF]])/(2030-2021)/Table12[[#This Row],[GHG emissions excl LULUCF]] -> 0.025896577 | AM19: =IF(Table12[[#This Row],[Net-zero target status]]<=1,"",IF(Table12[[#This Row],[NZ GHG year]]="","",(Table12[[#This Row],[residual LULUCF emissions in 2050]]-Table12[[#This Row],[Current Policies 2030 excl LULUCF]])/(Table12[[#This Row],[NZ GHG year]]-2030)/Table12[[#This Row],[Current Policies 2030 excl LULUCF]])) | AN19: =IF(Table12[[#This Row],[Net-zero target status]]<=1,"",IF(Table12[[#This Row],[NZ GHG year]]="","",(Table12[[#This Row],[residual LULUCF emissions in 2050]]-Table12[[#This Row],[GHG emissions excl LULUCF]])/(Table12[[#This Row],[NZ GHG year]]-2021)/Table12[[#This Row],[GHG emissions excl LULUCF]])) | AO19: =IF(Table12[[#This Row],[Net-zero target status]]<=1,"",IF(Table12[[#This Row],[NZ GHG year]]="","",(Table12[[#This Row],[residual LULUCF emissions in 2050]]-Table12[[#This Row],[2030 conditional NDCs]])/(Table12[[#This Row],[NZ GHG year]]-2030)/Table12[[#This Row],[2030 conditional NDCs]])) | AP19: =MAX('input site'!AH19:AS19) -> 0.15875563 | AQ19: =IF(Table12[[#This Row],[Current Policies 2030 incl LULUCF]]>Table12[[#This Row],[Maximum inventory data]],"No","Yes") -> No | AR19: =IF(Table12[[#This Row],[Net-zero target status]]>=1.5,Table12[[#This Row],[residual LULUCF emissions in 2050]]/Table12[[#This Row],[GHG emissions excl LULUCF]],"") | AW19: =IF(Table12[[#This Row],[2030 unconditional NDCs]]="","",IF(F19="incl",Table12[[#This Row],[2030 unconditional NDCs]]-Table12[[#This Row],[LULUCF NDC uncond]],Table12[[#This Row],[2030 unconditional NDCs]])) | AX19: =IF(Table12[[#This Row],[2030 unconditional NDCs2]]="","",IF(F19="incl",Table12[[#This Row],[2030 unconditional NDCs2]]-Table12[[#This Row],[LULUCF NDC uncond]],Table12[[#This Row],[2030 unconditional NDCs2]])) | AY19: =IF(Table12[[#This Row],[2030 conditional NDCs]]="","",IF(F19="incl",Table12[[#This Row],[2030 conditional NDCs]]-Table12[[#This Row],[LULUCF NDC cond]],Table12[[#This Row],[2030 conditional NDCs]])) | AZ19: =IF(Table12[[#This Row],[2030 conditional NDCs2]]="","",IF(F19="incl",Table12[[#This Row],[2030 conditional NDCs2]]-Table12[[#This Row],[LULUCF NDC cond]],Table12[[#This Row],[2030 conditional NDCs2]])) | BA19: =VLOOKUP($G19,'Population90 20'!$C$6:$AU$231,37,FALSE) -> 15230 | BB19: =VLOOKUP($G19,'Overview GDP (PPP)'!$C$6:$AI$231,33,FALSE) -> 338269.13 | BC19: =Table12[[#This Row],[Income]]/Table12[[#This Row],[Population]] -> 22.210711 | BD19: =Table12[[#This Row],[GHG emissions excl LULUCF]]*1000000/Table12[[#This Row],[Population]] -> 9.2057682 | BE19: =VLOOKUP($G19,EGR2023_MASTER!$B$4:$S$38,14,FALSE) -> #N/A | BF19: =VLOOKUP($G19,EGR2023_MASTER!$B$4:$S$38,15,FALSE) -> #N/A | BG19: =VLOOKUP($G19,EGR2023_MASTER!$B$4:$S$38,16,FALSE) -> #N/A | BH19: =IF(AND(BE19="Y",AND(BF19="credible",BG19="Y")),"higher",IF(BG19="Y","lower",IF(AND(BG19="N",OR(BE19="Y",BF19="credible")),"lower","much lower"))) -> #N/A | BI19: =IF(AND($BF19="credible",BG19="Y"),"stronger","weak") -> #N/A | BJ19: =(Table12[[#This Row],[Current Policies 2030 excl LULUCF]]/Table12[[#This Row],[GHG emissions excl LULUCF]])^(1/(2030-2021))-1 -> 0.02355154 | BK19: =IF(Table12[[#This Row],[Net-zero target status]]<=1,"",IF(Table12[[#This Row],[NZ GHG year]]="","",((MAX(Table12[[#This Row],[residual LULUCF emissions in 2050]],0.1)/Table12[[#This Row],[Current Policies 2030 excl LULUCF]])^(1/(Table12[[#This Row],[NZ GHG year]]-2021))-1))) | BL19: =IF(Table12[[#This Row],[Net-zero target status]]<=1,"",IF(Table12[[#This Row],[NZ GHG year]]="","",((MAX(Table12[[#This Row],[residual LULUCF emissions in 2050]],0.1)/Table12[[#This Row],[GHG emissions excl LULUCF]])^(1/(Table12[[#This Row],[NZ GHG year]]-2021))-1))) | BM19: =IF(Table12[[#This Row],[Net-zero target status]]<=1,"",IF(Table12[[#This Row],[NZ GHG year]]="","",((MAX(Table12[[#This Row],[residual LULUCF emissions in 2050]],0.1)/AVERAGE(Table12[[#This Row],[2030 conditional NDCs]:[2030 conditional NDCs2]]))^(1/(Table12[[#This Row],[NZ GHG year]]-2021))-1))) | BR19: Anguilla | BT19: =IF(Table12[[#This Row],[Reduction rate 2021 to NZ target2]]="","",J19*(1+AN19)^(Table12[[#This Row],[NZ GHG year]]-2021))
A20: 1 | B20: 1 | C20: 32 | D20: 8 | E20: 6 | F20: ='input site'!M20 -> incl | G20: ARG | H20: Argentina | I20: =VLOOKUP($G20,'NZT data'!$B$3:$C$200,2,FALSE) -> 3 | J20: ='input site'!AS20 -> 365.87596 | K20: ='input site'!BS20 -> 376.10161 | L20: =IF(I20>=1,O20,K20) -> 0 | M20: =IF(I20>=1,O20,N20) -> 0 | N20: ='input site'!EV20 -> 239.92365 | O20: 0 | P20: =O20-N20 -> -239.92365 | Q20: =IF(I20>=1,O20,R20) -> 0 | R20: ='input site'!EZ20 -> 141.94514 | S20: ='input site'!FA20 -> 2050, same value as Climate Resource | T20: =Table12[[#This Row],[(Mt CO2 equivalent)]] -> Argentina | U20: =VLOOKUP($G20,'NZT data'!$B$3:$F$200,4,FALSE) -> 2050 | V20: =VLOOKUP($G20,'NZT data'!$B$3:$F$200,5,FALSE) -> 2050 | W20: =-IF('LUC NGHGI'!EC10="",MIN('LUC NGHGI'!DW10,0.1),MIN('LUC NGHGI'!EC10,0.1)) -> 26.65009 | X20: ='LUC NGHGI'!EC10 -> -26.65009 | Y20: ='LUC NGHGI'!DY10 -> -26.65009 | Z20: ='LUC NGHGI'!DZ10 -> -42.56 | AA20: =Table12[[#This Row],[2021 emissions]] -> 365.87596 | AB20: ='LUC NGHGI'!DW10 -> 56.380224 | AC20: =IF(F20="incl",Table12[[#This Row],[GHG emissions incl LULUCF]]-Table12[[#This Row],[LULUCF emis-sions in 20213]],Table12[[#This Row],[GHG emissions incl LULUCF]]) -> 309.49573 | AD20: ='input site'!BS20 -> 376.10161 | AE20: ='LUC NGHGI'!EH10 -> -17.89451 | AF20: =IF(F20="incl",Table12[[#This Row],[Current Policies 2030 incl LULUCF]]-Table12[[#This Row],[LULUCF CurPol 2030]],Table12[[#This Row],[Current Policies 2030 incl LULUCF]]) -> 393.99612 | AG20: =IF(Table12[[#This Row],[Net-zero target status]]<=1,"",IF(Table12[[#This Row],[NZ GHG year]]="","",1000000000*(Table12[[#This Row],[residual LULUCF emissions in 2050]]-Table12[[#This Row],[GHG emissions excl LULUCF]])/(Table12[[#This Row],[NZ GHG year]]-2021)/Table12[[#This Row],[Population]])) -> -211.98106 | AH20: =IF(Table12[[#This Row],[Peak revised]]="Yes",IF(Table12[[#This Row],[Net-zero target status]]<=1,"",IF(Table12[[#This Row],[NZ GHG year]]="","",1000000000*(Table12[[#This Row],[residual LULUCF emissions in 2050]]-Table12[[#This Row],[GHG emissions excl LULUCF]])/(Table12[[#This Row],[NZ GHG year]]-2021)/Table12[[#This Row],[Population]])),"") -> -211.98106 | AI20: =MAX(0,(1000000*(Table12[[#This Row],[Current Policies 2030 excl LULUCF]]/2+Table12[[#This Row],[GHG emissions excl LULUCF]]/2)/Table12[[#This Row],[Population]]-$AI$8)*10)*$AI$10 -> -64.494972 | AJ20: =IF(Table12[[#This Row],[Peak revised]]="No",IF(Table12[[#This Row],[Net-zero target status]]<=1,"",IF(Table12[[#This Row],[NZ GHG year]]="","",1000000000*(Table12[[#This Row],[residual LULUCF emissions in 2050]]-Table12[[#This Row],[Current Policies 2030 excl LULUCF]])/(Table12[[#This Row],[NZ GHG year]]-2021)/Table12[[#This Row],[Population]])),"") | AK20: =IF(Table12[[#This Row],[Formule no Peak (2)]]="","",Table12[[#This Row],[Penalty (1)]]+Table12[[#This Row],[Formule no Peak (2)]]) | AL20: =(Table12[[#This Row],[Current Policies 2030 excl LULUCF]]-Table12[[#This Row],[GHG emissions excl LULUCF]])/(2030-2021)/Table12[[#This Row],[GHG emissions excl LULUCF]] -> 0.030336224 | AM20: =IF(Table12[[#This Row],[Net-zero target status]]<=1,"",IF(Table12[[#This Row],[NZ GHG year]]="","",(Table12[[#This Row],[residual LULUCF emissions in 2050]]-Table12[[#This Row],[Current Policies 2030 excl LULUCF]])/(Table12[[#This Row],[NZ GHG year]]-2030)/Table12[[#This Row],[Current Policies 2030 excl LULUCF]])) -> -0.046617976 | AN20: =IF(Table12[[#This Row],[Net-zero target status]]<=1,"",IF(Table12[[#This Row],[NZ GHG year]]="","",(Table12[[#This Row],[residual LULUCF emissions in 2050]]-Table12[[#This Row],[GHG emissions excl LULUCF]])/(Table12[[#This Row],[NZ GHG year]]-2021)/Table12[[#This Row],[GHG emissions excl LULUCF]])) -> -0.031513514 | AO20: =IF(Table12[[#This Row],[Net-zero target status]]<=1,"",IF(Table12[[#This Row],[NZ GHG year]]="","",(Table12[[#This Row],[residual LULUCF emissions in 2050]]-Table12[[#This Row],[2030 conditional NDCs]])/(Table12[[#This Row],[NZ GHG year]]-2030)/Table12[[#This Row],[2030 conditional NDCs]])) -> -0.046181936 | AP20: =MAX('input site'!AH20:AS20) -> 418.05176 | AQ20: =IF(Table12[[#This Row],[Current Policies 2030 incl LULUCF]]>Table12[[#This Row],[Maximum inventory data]],"No","Yes") -> Yes | AR20: =IF(Table12[[#This Row],[Net-zero target status]]>=1.5,Table12[[#This Row],[residual LULUCF emissions in 2050]]/Table12[[#This Row],[GHG emissions excl LULUCF]],"") -> 0.086108102 | AS20: ='input site'!BE20 -> 349 | AT20: ='input site'!BF20 -> 349 | AU20: ='input site'!BG20 -> 349 | AV20: ='input site'!BH20 -> 349 | AW20: =IF(Table12[[#This Row],[2030 unconditional NDCs]]="","",IF(F20="incl",Table12[[#This Row],[2030 unconditional NDCs]]-Table12[[#This Row],[LULUCF NDC uncond]],Table12[[#This Row],[2030 unconditional NDCs]])) -> 375.65009 | AX20: =IF(Table12[[#This Row],[2030 unconditional NDCs2]]="","",IF(F20="incl",Table12[[#This Row],[2030 unconditional NDCs2]]-Table12[[#This Row],[LULUCF NDC uncond]],Table12[[#This Row],[2030 unconditional NDCs2]])) -> 375.65009 | AY20: =IF(Table12[[#This Row],[2030 conditional NDCs]]="","",IF(F20="incl",Table12[[#This Row],[2030 conditional NDCs]]-Table12[[#This Row],[LULUCF NDC cond]],Table12[[#This Row],[2030 conditional NDCs]])) -> 391.56 | AZ20: =IF(Table12[[#This Row],[2030 conditional NDCs2]]="","",IF(F20="incl",Table12[[#This Row],[2030 conditional NDCs2]]-Table12[[#This Row],[LULUCF NDC cond]],Table12[[#This Row],[2030 conditional NDCs2]])) -> 391.56 | BA20: =VLOOKUP($G20,'Population90 20'!$C$6:$AU$231,37,FALSE) -> 46010234 | BB20: =VLOOKUP($G20,'Overview GDP (PPP)'!$C$6:$AI$231,33,FALSE) -> 8.1345266e+08 | BC20: =Table12[[#This Row],[Income]]/Table12[[#This Row],[Population]] -> 17.67982 | BD20: =Table12[[#This Row],[GHG emissions excl LULUCF]]*1000000/Table12[[#This Row],[Population]] -> 6.7266716 | BE20: =VLOOKUP($G20,EGR2023_MASTER!$B$4:$S$38,14,FALSE) -> N | BF20: =VLOOKUP($G20,EGR2023_MASTER!$B$4:$S$38,15,FALSE) -> Weaker | BG20: =VLOOKUP($G20,EGR2023_MASTER!$B$4:$S$38,16,FALSE) -> n | BH20: =IF(AND(BE20="Y",AND(BF20="credible",BG20="Y")),"higher",IF(BG20="Y","lower",IF(AND(BG20="N",OR(BE20="Y",BF20="credible")),"lower","much lower"))) -> much lower | BI20: =IF(AND($BF20="credible",BG20="Y"),"stronger","weak") -> weak | BJ20: =(Table12[[#This Row],[Current Policies 2030 excl LULUCF]]/Table12[[#This Row],[GHG emissions excl LULUCF]])^(1/(2030-2021))-1 -> 0.027184805 | BK20: =IF(Table12[[#This Row],[Net-zero target status]]<=1,"",IF(Table12[[#This Row],[NZ GHG year]]="","",((MAX(Table12[[#This Row],[residual LULUCF emissions in 2050]],0.1)/Table12[[#This Row],[Current Policies 2030 excl LULUCF]])^(1/(Table12[[#This Row],[NZ GHG year]]-2021))-1))) -> -0.088698046 | BL20: =IF(Table12[[#This Row],[Net-zero target status]]<=1,"",IF(Table12[[#This Row],[NZ GHG year]]="","",((MAX(Table12[[#This Row],[residual LULUCF emissions in 2050]],0.1)/Table12[[#This Row],[GHG emissions excl LULUCF]])^(1/(Table12[[#This Row],[NZ GHG year]]-2021))-1))) -> -0.081080686 | BM20: =IF(Table12[[#This Row],[Net-zero target status]]<=1,"",IF(Table12[[#This Row],[NZ GHG year]]="","",((MAX(Table12[[#This Row],[residual LULUCF emissions in 2050]],0.1)/AVERAGE(Table12[[#This Row],[2030 conditional NDCs]:[2030 conditional NDCs2]]))^(1/(Table12[[#This Row],[NZ GHG year]]-2021))-1))) -> -0.084879281 | BR20: Argentina | BT20: =IF(Table12[[#This Row],[Reduction rate 2021 to NZ target2]]="","",J20*(1+AN20)^(Table12[[#This Row],[NZ GHG year]]-2021)) -> 144.55971
A21: 0 | B21: 0 | C21: 51 | D21: 14 | E21: 16 | F21: ='input site'!M21 -> excl | G21: ARM | H21: Armenia | I21: =VLOOKUP($G21,'NZT data'!$B$3:$C$200,2,FALSE) -> 1 | J21: ='input site'!AS21 -> 12.227112 | K21: ='input site'!BS21 -> 11.537793 | L21: =IF(I21>=1,O21,K21) -> 0 | M21: =IF(I21>=1,O21,N21) -> 0 | N21: ='input site'!EV21 -> 1.9630306 | O21: 0 | P21: =O21-N21 -> -1.9630306 | Q21: =IF(I21>=1,O21,R21) -> 0 | R21: ='input site'!EZ21 -> 1.8656998 | S21: ='input site'!FA21 -> 2050 | T21: =Table12[[#This Row],[(Mt CO2 equivalent)]] -> Armenia | U21: =VLOOKUP($G21,'NZT data'!$B$3:$F$200,4,FALSE) -> 2110 | V21: =VLOOKUP($G21,'NZT data'!$B$3:$F$200,5,FALSE) -> 2110 | W21: =-IF('LUC NGHGI'!EC11="",MIN('LUC NGHGI'!DW11,0.1),MIN('LUC NGHGI'!EC11,0.1)) -> 0.50971338 | X21: ='LUC NGHGI'!EC11 -> -0.50971338 | Y21: ='LUC NGHGI'!DY11 -> -1.5097134 | Z21: ='LUC NGHGI'!DZ11 -> -1.5097134 | AA21: =Table12[[#This Row],[2021 emissions]] -> 12.227112 | AB21: ='LUC NGHGI'!DW11 -> -0.50839666 | AC21: =IF(F21="incl",Table12[[#This Row],[GHG emissions incl LULUCF]]-Table12[[#This Row],[LULUCF emis-sions in 20213]],Table12[[#This Row],[GHG emissions incl LULUCF]]) -> 12.227112 | AD21: ='input site'!BS21 -> 11.537793 | AE21: ='LUC NGHGI'!EH11 -> -0.67899388 | AF21: =IF(F21="incl",Table12[[#This Row],[Current Policies 2030 incl LULUCF]]-Table12[[#This Row],[LULUCF CurPol 2030]],Table12[[#This Row],[Current Policies 2030 incl LULUCF]]) -> 11.537793 | AG21: =IF(Table12[[#This Row],[Net-zero target status]]<=1,"",IF(Table12[[#This Row],[NZ GHG year]]="","",1000000000*(Table12[[#This Row],[residual LULUCF emissions in 2050]]-Table12[[#This Row],[GHG emissions excl LULUCF]])/(Table12[[#This Row],[NZ GHG year]]-2021)/Table12[[#This Row],[Population]])) | AH21: =IF(Table12[[#This Row],[Peak revised]]="Yes",IF(Table12[[#This Row],[Net-zero target status]]<=1,"",IF(Table12[[#This Row],[NZ GHG year]]="","",1000000000*(Table12[[#This Row],[residual LULUCF emissions in 2050]]-Table12[[#This Row],[GHG emissions excl LULUCF]])/(Table12[[#This Row],[NZ GHG year]]-2021)/Table12[[#This Row],[Population]])),"") | AI21: =MAX(0,(1000000*(Table12[[#This Row],[Current Policies 2030 excl LULUCF]]/2+Table12[[#This Row],[GHG emissions excl LULUCF]]/2)/Table12[[#This Row],[Population]]-$AI$8)*10)*$AI$10 -> 0 | AJ21: =IF(Table12[[#This Row],[Peak revised]]="No",IF(Table12[[#This Row],[Net-zero target status]]<=1,"",IF(Table12[[#This Row],[NZ GHG year]]="","",1000000000*(Table12[[#This Row],[residual LULUCF emissions in 2050]]-Table12[[#This Row],[Current Policies 2030 excl LULUCF]])/(Table12[[#This Row],[NZ GHG year]]-2021)/Table12[[#This Row],[Population]])),"") | AK21: =IF(Table12[[#This Row],[Formule no Peak (2)]]="","",Table12[[#This Row],[Penalty (1)]]+Table12[[#This Row],[Formule no Peak (2)]]) | AL21: =(Table12[[#This Row],[Current Policies 2030 excl LULUCF]]-Table12[[#This Row],[GHG emissions excl LULUCF]])/(2030-2021)/Table12[[#This Row],[GHG emissions excl LULUCF]] -> -0.0062640273 | AM21: =IF(Table12[[#This Row],[Net-zero target status]]<=1,"",IF(Table12[[#This Row],[NZ GHG year]]="","",(Table12[[#This Row],[residual LULUCF emissions in 2050]]-Table12[[#This Row],[Current Policies 2030 excl LULUCF]])/(Table12[[#This Row],[NZ GHG year]]-2030)/Table12[[#This Row],[Current Policies 2030 excl LULUCF]])) | AN21: =IF(Table12[[#This Row],[Net-zero target status]]<=1,"",IF(Table12[[#This Row],[NZ GHG year]]="","",(Table12[[#This Row],[residual LULUCF emissions in 2050]]-Table12[[#This Row],[GHG emissions excl LULUCF]])/(Table12[[#This Row],[NZ GHG year]]-2021)/Table12[[#This Row],[GHG emissions excl LULUCF]])) | AO21: =IF(Table12[[#This Row],[Net-zero target status]]<=1,"",IF(Table12[[#This Row],[NZ GHG year]]="","",(Table12[[#This Row],[residual LULUCF emissions in 2050]]-Table12[[#This Row],[2030 conditional NDCs]])/(Table12[[#This Row],[NZ GHG year]]-2030)/Table12[[#This Row],[2030 conditional NDCs]])) | AP21: =MAX('input site'!AH21:AS21) -> 12.227112 | AQ21: =IF(Table12[[#This Row],[Current Policies 2030 incl LULUCF]]>Table12[[#This Row],[Maximum inventory data]],"No","Yes") -> Yes | AR21: =IF(Table12[[#This Row],[Net-zero target status]]>=1.5,Table12[[#This Row],[residual LULUCF emissions in 2050]]/Table12[[#This Row],[GHG emissions excl LULUCF]],"") | AW21: =IF(Table12[[#This Row],[2030 unconditional NDCs]]="","",IF(F21="incl",Table12[[#This Row],[2030 unconditional NDCs]]-Table12[[#This Row],[LULUCF NDC uncond]],Table12[[#This Row],[2030 unconditional NDCs]])) | AX21: =IF(Table12[[#This Row],[2030 unconditional NDCs2]]="","",IF(F21="incl",Table12[[#This Row],[2030 unconditional NDCs2]]-Table12[[#This Row],[LULUCF NDC uncond]],Table12[[#This Row],[2030 unconditional NDCs2]])) | AY21: =IF(Table12[[#This Row],[2030 conditional NDCs]]="","",IF(F21="incl",Table12[[#This Row],[2030 conditional NDCs]]-Table12[[#This Row],[LULUCF NDC cond]],Table12[[#This Row],[2030 conditional NDCs]])) | AZ21: =IF(Table12[[#This Row],[2030 conditional NDCs2]]="","",IF(F21="incl",Table12[[#This Row],[2030 conditional NDCs2]]-Table12[[#This Row],[LULUCF NDC cond]],Table12[[#This Row],[2030 conditional NDCs2]])) | BA21: =VLOOKUP($G21,'Population90 20'!$C$6:$AU$231,37,FALSE) -> 2971966 | BB21: =VLOOKUP($G21,'Overview GDP (PPP)'!$C$6:$AI$231,33,FALSE) -> 27090645 | BC21: =Table12[[#This Row],[Income]]/Table12[[#This Row],[Population]] -> 9.1153953 | BD21: =Table12[[#This Row],[GHG emissions excl LULUCF]]*1000000/Table12[[#This Row],[Population]] -> 4.1141494 | BE21: =VLOOKUP($G21,EGR2023_MASTER!$B$4:$S$38,14,FALSE) -> #N/A | BF21: =VLOOKUP($G21,EGR2023_MASTER!$B$4:$S$38,15,FALSE) -> #N/A | BG21: =VLOOKUP($G21,EGR2023_MASTER!$B$4:$S$38,16,FALSE) -> #N/A | BH21: =IF(AND(BE21="Y",AND(BF21="credible",BG21="Y")),"higher",IF(BG21="Y","lower",IF(AND(BG21="N",OR(BE21="Y",BF21="credible")),"lower","much lower"))) -> #N/A | BI21: =IF(AND($BF21="credible",BG21="Y"),"stronger","weak") -> #N/A | BJ21: =(Table12[[#This Row],[Current Policies 2030 excl LULUCF]]/Table12[[#This Row],[GHG emissions excl LULUCF]])^(1/(2030-2021))-1 -> -0.0064267879 | BK21: =IF(Table12[[#This Row],[Net-zero target status]]<=1,"",IF(Table12[[#This Row],[NZ GHG year]]="","",((MAX(Table12[[#This Row],[residual LULUCF emissions in 2050]],0.1)/Table12[[#This Row],[Current Policies 2030 excl LULUCF]])^(1/(Table12[[#This Row],[NZ GHG year]]-2021))-1))) | BL21: =IF(Table12[[#This Row],[Net-zero target status]]<=1,"",IF(Table12[[#This Row],[NZ GHG year]]="","",((MAX(Table12[[#This Row],[residual LULUCF emissions in 2050]],0.1)/Table12[[#This Row],[GHG emissions excl LULUCF]])^(1/(Table12[[#This Row],[NZ GHG year]]-2021))-1))) | BM21: =IF(Table12[[#This Row],[Net-zero target status]]<=1,"",IF(Table12[[#This Row],[NZ GHG year]]="","",((MAX(Table12[[#This Row],[residual LULUCF emissions in 2050]],0.1)/AVERAGE(Table12[[#This Row],[2030 conditional NDCs]:[2030 conditional NDCs2]]))^(1/(Table12[[#This Row],[NZ GHG year]]-2021))-1))) | BR21: Armenia | BT21: =IF(Table12[[#This Row],[Reduction rate 2021 to NZ target2]]="","",J21*(1+AN21)^(Table12[[#This Row],[NZ GHG year]]-2021))
A22: 0 | B22: 0 | C22: 533 | D22: 139 | E22: 4 | F22: ='input site'!M22 -> excl | G22: ABW | H22: Aruba | I22: 0 | J22: ='input site'!AS22 -> 0.94354415 | K22: ='input site'!BS22 -> 1.1634552 | L22: =IF(I22>=1,O22,K22) -> 1.1634552 | M22: =IF(I22>=1,O22,N22) -> 0.53389806 | N22: ='input site'!EV22 -> 0.53389806 | Q22: =IF(I22>=1,O22,R22) -> 0.1085844 | R22: ='input site'!EZ22 -> 0.1085844 | S22: ='input site'!FA22 -> 0 | T22: =Table12[[#This Row],[(Mt CO2 equivalent)]] -> Aruba | U22: 2100 | V22: 2100 | W22: =-IF('LUC NGHGI'!EC12="",MIN('LUC NGHGI'!DW12,0.1),MIN('LUC NGHGI'!EC12,0.1)) -> 0 | X22: ='LUC NGHGI'!EC12 | Y22: ='LUC NGHGI'!DY12 | Z22: ='LUC NGHGI'!DZ12 | AA22: =Table12[[#This Row],[2021 emissions]] -> 0.94354415 | AB22: ='LUC NGHGI'!DW12 -> 0 | AC22: =IF(F22="incl",Table12[[#This Row],[GHG emissions incl LULUCF]]-Table12[[#This Row],[LULUCF emis-sions in 20213]],Table12[[#This Row],[GHG emissions incl LULUCF]]) -> 0.94354415 | AD22: ='input site'!BS22 -> 1.1634552 | AE22: ='LUC NGHGI'!EH12 -> 0 | AF22: =IF(F22="incl",Table12[[#This Row],[Current Policies 2030 incl LULUCF]]-Table12[[#This Row],[LULUCF CurPol 2030]],Table12[[#This Row],[Current Policies 2030 incl LULUCF]]) -> 1.1634552 | AG22: =IF(Table12[[#This Row],[Net-zero target status]]<=1,"",IF(Table12[[#This Row],[NZ GHG year]]="","",1000000000*(Table12[[#This Row],[residual LULUCF emissions in 2050]]-Table12[[#This Row],[GHG emissions excl LULUCF]])/(Table12[[#This Row],[NZ GHG year]]-2021)/Table12[[#This Row],[Population]])) | AH22: =IF(Table12[[#This Row],[Peak revised]]="Yes",IF(Table12[[#This Row],[Net-zero target status]]<=1,"",IF(Table12[[#This Row],[NZ GHG year]]="","",1000000000*(Table12[[#This Row],[residual LULUCF emissions in 2050]]-Table12[[#This Row],[GHG emissions excl LULUCF]])/(Table12[[#This Row],[NZ GHG year]]-2021)/Table12[[#This Row],[Population]])),"") | AI22: =MAX(0,(1000000*(Table12[[#This Row],[Current Policies 2030 excl LULUCF]]/2+Table12[[#This Row],[GHG emissions excl LULUCF]]/2)/Table12[[#This Row],[Population]]-$AI$8)*10)*$AI$10 -> -279.00704 | AJ22: =IF(Table12[[#This Row],[Peak revised]]="No",IF(Table12[[#This Row],[Net-zero target status]]<=1,"",IF(Table12[[#This Row],[NZ GHG year]]="","",1000000000*(Table12[[#This Row],[residual LULUCF emissions in 2050]]-Table12[[#This Row],[Current Policies 2030 excl LULUCF]])/(Table12[[#This Row],[NZ GHG year]]-2021)/Table12[[#This Row],[Population]])),"") | AK22: =IF(Table12[[#This Row],[Formule no Peak (2)]]="","",Table12[[#This Row],[Penalty (1)]]+Table12[[#This Row],[Formule no Peak (2)]]) | AL22: =(Table12[[#This Row],[Current Policies 2030 excl LULUCF]]-Table12[[#This Row],[GHG emissions excl LULUCF]])/(2030-2021)/Table12[[#This Row],[GHG emissions excl LULUCF]] -> 0.025896577 | AM22: =IF(Table12[[#This Row],[Net-zero target status]]<=1,"",IF(Table12[[#This Row],[NZ GHG year]]="","",(Table12[[#This Row],[residual LULUCF emissions in 2050]]-Table12[[#This Row],[Current Policies 2030 excl LULUCF]])/(Table12[[#This Row],[NZ GHG year]]-2030)/Table12[[#This Row],[Current Policies 2030 excl LULUCF]])) | AN22: =IF(Table12[[#This Row],[Net-zero target status]]<=1,"",IF(Table12[[#This Row],[NZ GHG year]]="","",(Table12[[#This Row],[residual LULUCF emissions in 2050]]-Table12[[#This Row],[GHG emissions excl LULUCF]])/(Table12[[#This Row],[NZ GHG year]]-2021)/Table12[[#This Row],[GHG emissions excl LULUCF]])) | AO22: =IF(Table12[[#This Row],[Net-zero target status]]<=1,"",IF(Table12[[#This Row],[NZ GHG year]]="","",(Table12[[#This Row],[residual LULUCF emissions in 2050]]-Table12[[#This Row],[2030 conditional NDCs]])/(Table12[[#This Row],[NZ GHG year]]-2030)/Table12[[#This Row],[2030 conditional NDCs]])) | AP22: =MAX('input site'!AH22:AS22) -> 2.5753925 | AQ22: =IF(Table12[[#This Row],[Current Policies 2030 incl LULUCF]]>Table12[[#This Row],[Maximum inventory data]],"No","Yes") -> Yes | AR22: =IF(Table12[[#This Row],[Net-zero target status]]>=1.5,Table12[[#This Row],[residual LULUCF emissions in 2050]]/Table12[[#This Row],[GHG emissions excl LULUCF]],"") | AW22: =IF(Table12[[#This Row],[2030 unconditional NDCs]]="","",IF(F22="incl",Table12[[#This Row],[2030 unconditional NDCs]]-Table12[[#This Row],[LULUCF NDC uncond]],Table12[[#This Row],[2030 unconditional NDCs]])) | AX22: =IF(Table12[[#This Row],[2030 unconditional NDCs2]]="","",IF(F22="incl",Table12[[#This Row],[2030 unconditional NDCs2]]-Table12[[#This Row],[LULUCF NDC uncond]],Table12[[#This Row],[2030 unconditional NDCs2]])) | AY22: =IF(Table12[[#This Row],[2030 conditional NDCs]]="","",IF(F22="incl",Table12[[#This Row],[2030 conditional NDCs]]-Table12[[#This Row],[LULUCF NDC cond]],Table12[[#This Row],[2030 conditional NDCs]])) | AZ22: =IF(Table12[[#This Row],[2030 conditional NDCs2]]="","",IF(F22="incl",Table12[[#This Row],[2030 conditional NDCs2]]-Table12[[#This Row],[LULUCF NDC cond]],Table12[[#This Row],[2030 conditional NDCs2]])) | BA22: =VLOOKUP($G22,'Population90 20'!$C$6:$AU$231,37,FALSE) -> 107609 | BB22: =VLOOKUP($G22,'Overview GDP (PPP)'!$C$6:$AI$231,33,FALSE) -> 3823960.8 | BC22: =Table12[[#This Row],[Income]]/Table12[[#This Row],[Population]] -> 35.535697 | BD22: =Table12[[#This Row],[GHG emissions excl LULUCF]]*1000000/Table12[[#This Row],[Population]] -> 8.7682643 | BE22: =VLOOKUP($G22,EGR2023_MASTER!$B$4:$S$38,14,FALSE) -> #N/A | BF22: =VLOOKUP($G22,EGR2023_MASTER!$B$4:$S$38,15,FALSE) -> #N/A | BG22: =VLOOKUP($G22,EGR2023_MASTER!$B$4:$S$38,16,FALSE) -> #N/A | BH22: =IF(AND(BE22="Y",AND(BF22="credible",BG22="Y")),"higher",IF(BG22="Y","lower",IF(AND(BG22="N",OR(BE22="Y",BF22="credible")),"lower","much lower"))) -> #N/A | BI22: =IF(AND($BF22="credible",BG22="Y"),"stronger","weak") -> #N/A | BJ22: =(Table12[[#This Row],[Current Policies 2030 excl LULUCF]]/Table12[[#This Row],[GHG emissions excl LULUCF]])^(1/(2030-2021))-1 -> 0.02355154 | BK22: =IF(Table12[[#This Row],[Net-zero target status]]<=1,"",IF(Table12[[#This Row],[NZ GHG year]]="","",((MAX(Table12[[#This Row],[residual LULUCF emissions in 2050]],0.1)/Table12[[#This Row],[Current Policies 2030 excl LULUCF]])^(1/(Table12[[#This Row],[NZ GHG year]]-2021))-1))) | BL22: =IF(Table12[[#This Row],[Net-zero target status]]<=1,"",IF(Table12[[#This Row],[NZ GHG year]]="","",((MAX(Table12[[#This Row],[residual LULUCF emissions in 2050]],0.1)/Table12[[#This Row],[GHG emissions excl LULUCF]])^(1/(Table12[[#This Row],[NZ GHG year]]-2021))-1))) | BM22: =IF(Table12[[#This Row],[Net-zero target status]]<=1,"",IF(Table12[[#This Row],[NZ GHG year]]="","",((MAX(Table12[[#This Row],[residual LULUCF emissions in 2050]],0.1)/AVERAGE(Table12[[#This Row],[2030 conditional NDCs]:[2030 conditional NDCs2]]))^(1/(Table12[[#This Row],[NZ GHG year]]-2021))-1))) | BR22: Aruba | BT22: =IF(Table12[[#This Row],[Reduction rate 2021 to NZ target2]]="","",J22*(1+AN22)^(Table12[[#This Row],[NZ GHG year]]-2021))
A23: 1 | B23: 1 | C23: 36 | D23: 9 | E23: 24 | F23: ='input site'!M23 -> incl | G23: AUS | H23: Australia | I23: =VLOOKUP($G23,'NZT data'!$B$3:$C$200,2,FALSE) -> 4 | J23: ='input site'!AS23 -> 458.66 | K23: ='input site'!BS23 -> 429.31307 | L23: =IF(I23>=1,O23,K23) -> 0 | M23: =IF(I23>=1,O23,N23) -> 0 | N23: ='input site'!EV23 -> 201.08308 | O23: 0 | Q23: =IF(I23>=1,O23,R23) -> 0 | R23: ='input site'!EZ23 -> 86.981235 | S23: ='input site'!FA23 -> States have net zero targets | T23: =Table12[[#This Row],[(Mt CO2 equivalent)]] -> Australia | U23: =VLOOKUP($G23,'NZT data'!$B$3:$F$200,4,FALSE) -> 2050 | V23: =VLOOKUP($G23,'NZT data'!$B$3:$F$200,5,FALSE) -> 2050 | W23: =-IF('LUC NGHGI'!EC13="",MIN('LUC NGHGI'!DW13,0.1),MIN('LUC NGHGI'!EC13,0.1)) -> 60 | X23: ='LUC NGHGI'!EC13 -> -60 | Y23: ='LUC NGHGI'!DY13 -> -42 | Z23: ='LUC NGHGI'!DZ13 -> -42 | AA23: =Table12[[#This Row],[2021 emissions]] -> 458.66 | AB23: ='LUC NGHGI'!DW13 -> -63.860982 | AC23: =IF(F23="incl",Table12[[#This Row],[GHG emissions incl LULUCF]]-Table12[[#This Row],[LULUCF emis-sions in 20213]],Table12[[#This Row],[GHG emissions incl LULUCF]]) -> 522.52098 | AD23: ='input site'!BS23 -> 429.31307 | AE23: =Table12[[#This Row],[LULUCF emis-sions in 20213]] -> -63.860982 | AF23: =IF(F23="incl",Table12[[#This Row],[Current Policies 2030 incl LULUCF]]-Table12[[#This Row],[LULUCF CurPol 2030]],Table12[[#This Row],[Current Policies 2030 incl LULUCF]]) -> 493.17405 | AG23: =IF(Table12[[#This Row],[Net-zero target status]]<=1,"",IF(Table12[[#This Row],[NZ GHG year]]="","",1000000000*(Table12[[#This Row],[residual LULUCF emissions in 2050]]-Table12[[#This Row],[GHG emissions excl LULUCF]])/(Table12[[#This Row],[NZ GHG year]]-2021)/Table12[[#This Row],[Population]])) -> -611.80431 | AH23: =IF(Table12[[#This Row],[Peak revised]]="Yes",IF(Table12[[#This Row],[Net-zero target status]]<=1,"",IF(Table12[[#This Row],[NZ GHG year]]="","",1000000000*(Table12[[#This Row],[residual LULUCF emissions in 2050]]-Table12[[#This Row],[GHG emissions excl LULUCF]])/(Table12[[#This Row],[NZ GHG year]]-2021)/Table12[[#This Row],[Population]])),"") -> -611.80431 | AI23: =MAX(0,(1000000*(Table12[[#This Row],[Current Policies 2030 excl LULUCF]]/2+Table12[[#This Row],[GHG emissions excl LULUCF]]/2)/Table12[[#This Row],[Population]]-$AI$8)*10)*$AI$10 -> -1248.1053 | AJ23: =IF(Table12[[#This Row],[Peak revised]]="No",IF(Table12[[#This Row],[Net-zero target status]]<=1,"",IF(Table12[[#This Row],[NZ GHG year]]="","",1000000000*(Table12[[#This Row],[residual LULUCF emissions in 2050]]-Table12[[#This Row],[Current Policies 2030 excl LULUCF]])/(Table12[[#This Row],[NZ GHG year]]-2021)/Table12[[#This Row],[Population]])),"") | AK23: =IF(Table12[[#This Row],[Formule no Peak (2)]]="","",Table12[[#This Row],[Penalty (1)]]+Table12[[#This Row],[Formule no Peak (2)]]) | AL23: =(Table12[[#This Row],[Current Policies 2030 excl LULUCF]]-Table12[[#This Row],[GHG emissions excl LULUCF]])/(2030-2021)/Table12[[#This Row],[GHG emissions excl LULUCF]] -> -0.0062404578 | AM23: =IF(Table12[[#This Row],[Net-zero target status]]<=1,"",IF(Table12[[#This Row],[NZ GHG year]]="","",(Table12[[#This Row],[residual LULUCF emissions in 2050]]-Table12[[#This Row],[Current Policies 2030 excl LULUCF]])/(Table12[[#This Row],[NZ GHG year]]-2030)/Table12[[#This Row],[Current Policies 2030 excl LULUCF]])) -> -0.043916955 | AN23: =IF(Table12[[#This Row],[Net-zero target status]]<=1,"",IF(Table12[[#This Row],[NZ GHG year]]="","",(Table12[[#This Row],[residual LULUCF emissions in 2050]]-Table12[[#This Row],[GHG emissions excl LULUCF]])/(Table12[[#This Row],[NZ GHG year]]-2021)/Table12[[#This Row],[GHG emissions excl LULUCF]])) -> -0.030523175 | AO23: =IF(Table12[[#This Row],[Net-zero target status]]<=1,"",IF(Table12[[#This Row],[NZ GHG year]]="","",(Table12[[#This Row],[residual LULUCF emissions in 2050]]-Table12[[#This Row],[2030 conditional NDCs]])/(Table12[[#This Row],[NZ GHG year]]-2030)/Table12[[#This Row],[2030 conditional NDCs]])) -> -0.041346195 | AP23: =MAX('input site'!AH23:AS23) -> 605.27 | AQ23: =IF(Table12[[#This Row],[Current Policies 2030 incl LULUCF]]>Table12[[#This Row],[Maximum inventory data]],"No","Yes") -> Yes | AR23: =IF(Table12[[#This Row],[Net-zero target status]]>=1.5,Table12[[#This Row],[residual LULUCF emissions in 2050]]/Table12[[#This Row],[GHG emissions excl LULUCF]],"") -> 0.11482792 | AS23: ='input site'!BE23 -> 346.6683 | AT23: ='input site'!BF23 -> 346.6683 | AU23: ='input site'!BG23 -> 346.6683 | AV23: ='input site'!BH23 -> 346.6683 | AW23: =IF(Table12[[#This Row],[2030 unconditional NDCs]]="","",IF(F23="incl",Table12[[#This Row],[2030 unconditional NDCs]]-Table12[[#This Row],[LULUCF NDC uncond]],Table12[[#This Row],[2030 unconditional NDCs]])) -> 388.6683 | AX23: =IF(Table12[[#This Row],[2030 unconditional NDCs2]]="","",IF(F23="incl",Table12[[#This Row],[2030 unconditional NDCs2]]-Table12[[#This Row],[LULUCF NDC uncond]],Table12[[#This Row],[2030 unconditional NDCs2]])) -> 388.6683 | AY23: =IF(Table12[[#This Row],[2030 conditional NDCs]]="","",IF(F23="incl",Table12[[#This Row],[2030 conditional NDCs]]-Table12[[#This Row],[LULUCF NDC cond]],Table12[[#This Row],[2030 conditional NDCs]])) -> 388.6683 | AZ23: =IF(Table12[[#This Row],[2030 conditional NDCs2]]="","",IF(F23="incl",Table12[[#This Row],[2030 conditional NDCs2]]-Table12[[#This Row],[LULUCF NDC cond]],Table12[[#This Row],[2030 conditional NDCs2]])) -> 388.6683 | BA23: =VLOOKUP($G23,'Population90 20'!$C$6:$AU$231,37,FALSE) -> 26068792 | BB23: =VLOOKUP($G23,'Overview GDP (PPP)'!$C$6:$AI$231,33,FALSE) -> 1.1356359e+09 | BC23: =Table12[[#This Row],[Income]]/Table12[[#This Row],[Population]] -> 43.563044 | BD23: =Table12[[#This Row],[GHG emissions excl LULUCF]]*1000000/Table12[[#This Row],[Population]] -> 20.043928 | BE23: =VLOOKUP($G23,EGR2023_MASTER!$B$4:$S$38,14,FALSE) -> Y | BF23: =VLOOKUP($G23,EGR2023_MASTER!$B$4:$S$38,15,FALSE) -> Weaker | BG23: =VLOOKUP($G23,EGR2023_MASTER!$B$4:$S$38,16,FALSE) -> n | BH23: =IF(AND(BE23="Y",AND(BF23="credible",BG23="Y")),"higher",IF(BG23="Y","lower",IF(AND(BG23="N",OR(BE23="Y",BF23="credible")),"lower","much lower"))) -> lower | BI23: =IF(AND($BF23="credible",BG23="Y"),"stronger","weak") -> weak | BJ23: =(Table12[[#This Row],[Current Policies 2030 excl LULUCF]]/Table12[[#This Row],[GHG emissions excl LULUCF]])^(1/(2030-2021))-1 -> -0.0064019733 | BK23: =IF(Table12[[#This Row],[Net-zero target status]]<=1,"",IF(Table12[[#This Row],[NZ GHG year]]="","",((MAX(Table12[[#This Row],[residual LULUCF emissions in 2050]],0.1)/Table12[[#This Row],[Current Policies 2030 excl LULUCF]])^(1/(Table12[[#This Row],[NZ GHG year]]-2021))-1))) -> -0.070063094 | BL23: =IF(Table12[[#This Row],[Net-zero target status]]<=1,"",IF(Table12[[#This Row],[NZ GHG year]]="","",((MAX(Table12[[#This Row],[residual LULUCF emissions in 2050]],0.1)/Table12[[#This Row],[GHG emissions excl LULUCF]])^(1/(Table12[[#This Row],[NZ GHG year]]-2021))-1))) -> -0.071914804 | BM23: =IF(Table12[[#This Row],[Net-zero target status]]<=1,"",IF(Table12[[#This Row],[NZ GHG year]]="","",((MAX(Table12[[#This Row],[residual LULUCF emissions in 2050]],0.1)/AVERAGE(Table12[[#This Row],[2030 conditional NDCs]:[2030 conditional NDCs2]]))^(1/(Table12[[#This Row],[NZ GHG year]]-2021))-1))) -> -0.058690776 | BN23: ='Supplementary Data 2'!AC25 -> 63 | BO23: ='Supplementary Data 2'!AC27 -> 204 | BP23: ='Supplementary Data 2'!AB25 -> 43 | BQ23: ='Supplementary Data 2'!AB28+'Supplementary Data 2'!AA28 -> 216 | BR23: Australia | BT23: =IF(Table12[[#This Row],[Reduction rate 2021 to NZ target2]]="","",J23*(1+AN23)^(Table12[[#This Row],[NZ GHG year]]-2021)) -> 186.6708
A24: 0 | B24: 0 | C24: 40 | D24: 10 | E24: 11 | F24: ='input site'!M24 -> incl | G24: AUT | H24: Austria | I24: =VLOOKUP($G24,'NZT data'!$B$3:$C$200,2,FALSE) -> 4 | J24: ='input site'!AS24 -> 66.913132 | K24: ='input site'!BS24 -> 37.334149 | L24: =IF(I24>=1,O24,K24) -> 0 | M24: =IF(I24>=1,O24,N24) -> 0 | N24: ='input site'!EV24 -> 17.052423 | Q24: =IF(I24>=1,O24,R24) -> 0 | R24: ='input site'!EZ24 -> 9.432103 | S24: ='input site'!FA24 -> 2040 (part of the EU) | T24: =Table12[[#This Row],[(Mt CO2 equivalent)]] -> Austria | U24: =VLOOKUP($G24,'NZT data'!$B$3:$F$200,4,FALSE) -> 2040 | V24: =VLOOKUP($G24,'NZT data'!$B$3:$F$200,5,FALSE) -> 2040 | W24: =-IF('LUC NGHGI'!EC14="",MIN('LUC NGHGI'!DW14,0.1),MIN('LUC NGHGI'!EC14,0.1)) -> 5.2338985 | X24: ='LUC NGHGI'!EC14 -> -5.2338985 | Y24: ='LUC NGHGI'!DY14 -> -5.2338985 | Z24: ='LUC NGHGI'!DZ14 -> -5.2338985 | AA24: =Table12[[#This Row],[2021 emissions]] -> 66.913132 | AB24: ='LUC NGHGI'!DW14 -> -10.41311 | AC24: =IF(F24="incl",Table12[[#This Row],[GHG emissions incl LULUCF]]-Table12[[#This Row],[LULUCF emis-sions in 20213]],Table12[[#This Row],[GHG emissions incl LULUCF]]) -> 77.326242 | AD24: ='input site'!BS24 -> 37.334149 | AE24: ='LUC NGHGI'!EH14 -> -9.058439 | AF24: =IF(F24="incl",Table12[[#This Row],[Current Policies 2030 incl LULUCF]]-Table12[[#This Row],[LULUCF CurPol 2030]],Table12[[#This Row],[Current Policies 2030 incl LULUCF]]) -> 46.392588 | AG24: =IF(Table12[[#This Row],[Net-zero target status]]<=1,"",IF(Table12[[#This Row],[NZ GHG year]]="","",1000000000*(Table12[[#This Row],[residual LULUCF emissions in 2050]]-Table12[[#This Row],[GHG emissions excl LULUCF]])/(Table12[[#This Row],[NZ GHG year]]-2021)/Table12[[#This Row],[Population]])) -> -418.49071 | AH24: =IF(Table12[[#This Row],[Peak revised]]="Yes",IF(Table12[[#This Row],[Net-zero target status]]<=1,"",IF(Table12[[#This Row],[NZ GHG year]]="","",1000000000*(Table12[[#This Row],[residual LULUCF emissions in 2050]]-Table12[[#This Row],[GHG emissions excl LULUCF]])/(Table12[[#This Row],[NZ GHG year]]-2021)/Table12[[#This Row],[Population]])),"") -> -418.49071 | AI24: =MAX(0,(1000000*(Table12[[#This Row],[Current Policies 2030 excl LULUCF]]/2+Table12[[#This Row],[GHG emissions excl LULUCF]]/2)/Table12[[#This Row],[Population]]-$AI$8)*10)*$AI$10 -> 0 | AJ24: =IF(Table12[[#This Row],[Peak revised]]="No",IF(Table12[[#This Row],[Net-zero target status]]<=1,"",IF(Table12[[#This Row],[NZ GHG year]]="","",1000000000*(Table12[[#This Row],[residual LULUCF emissions in 2050]]-Table12[[#This Row],[Current Policies 2030 excl LULUCF]])/(Table12[[#This Row],[NZ GHG year]]-2021)/Table12[[#This Row],[Population]])),"") | AK24: =IF(Table12[[#This Row],[Formule no Peak (2)]]="","",Table12[[#This Row],[Penalty (1)]]+Table12[[#This Row],[Formule no Peak (2)]]) | AL24: =(Table12[[#This Row],[Current Policies 2030 excl LULUCF]]-Table12[[#This Row],[GHG emissions excl LULUCF]])/(2030-2021)/Table12[[#This Row],[GHG emissions excl LULUCF]] -> -0.044448981 | AM24: =IF(Table12[[#This Row],[Net-zero target status]]<=1,"",IF(Table12[[#This Row],[NZ GHG year]]="","",(Table12[[#This Row],[residual LULUCF emissions in 2050]]-Table12[[#This Row],[Current Policies 2030 excl LULUCF]])/(Table12[[#This Row],[NZ GHG year]]-2030)/Table12[[#This Row],[Current Policies 2030 excl LULUCF]])) -> -0.088718244 | AN24: =IF(Table12[[#This Row],[Net-zero target status]]<=1,"",IF(Table12[[#This Row],[NZ GHG year]]="","",(Table12[[#This Row],[residual LULUCF emissions in 2050]]-Table12[[#This Row],[GHG emissions excl LULUCF]])/(Table12[[#This Row],[NZ GHG year]]-2021)/Table12[[#This Row],[GHG emissions excl LULUCF]])) -> -0.049069162 | AO24: =IF(Table12[[#This Row],[Net-zero target status]]<=1,"",IF(Table12[[#This Row],[NZ GHG year]]="","",(Table12[[#This Row],[residual LULUCF emissions in 2050]]-Table12[[#This Row],[2030 conditional NDCs]])/(Table12[[#This Row],[NZ GHG year]]-2030)/Table12[[#This Row],[2030 conditional NDCs]])) -> #DIV/0! | AP24: =MAX('input site'!AH24:AS24) -> 83.523725 | AQ24: =IF(Table12[[#This Row],[Current Policies 2030 incl LULUCF]]>Table12[[#This Row],[Maximum inventory data]],"No","Yes") -> Yes | AR24: =IF(Table12[[#This Row],[Net-zero target status]]>=1.5,Table12[[#This Row],[residual LULUCF emissions in 2050]]/Table12[[#This Row],[GHG emissions excl LULUCF]],"") -> 0.067685929 | AS24: ='input site'!BE24 | AW24: =IF(Table12[[#This Row],[2030 unconditional NDCs]]="","",IF(F24="incl",Table12[[#This Row],[2030 unconditional NDCs]]-Table12[[#This Row],[LULUCF NDC uncond]],Table12[[#This Row],[2030 unconditional NDCs]])) | AX24: =IF(Table12[[#This Row],[2030 unconditional NDCs2]]="","",IF(F24="incl",Table12[[#This Row],[2030 unconditional NDCs2]]-Table12[[#This Row],[LULUCF NDC uncond]],Table12[[#This Row],[2030 unconditional NDCs2]])) | AY24: =IF(Table12[[#This Row],[2030 conditional NDCs]]="","",IF(F24="incl",Table12[[#This Row],[2030 conditional NDCs]]-Table12[[#This Row],[LULUCF NDC cond]],Table12[[#This Row],[2030 conditional NDCs]])) | AZ24: =IF(Table12[[#This Row],[2030 conditional NDCs2]]="","",IF(F24="incl",Table12[[#This Row],[2030 conditional NDCs2]]-Table12[[#This Row],[LULUCF NDC cond]],Table12[[#This Row],[2030 conditional NDCs2]])) | BA24: =VLOOKUP($G24,'Population90 20'!$C$6:$AU$231,37,FALSE) -> 9066710 | BB24: =VLOOKUP($G24,'Overview GDP (PPP)'!$C$6:$AI$231,33,FALSE) -> 4.1115063e+08 | BC24: =Table12[[#This Row],[Income]]/Table12[[#This Row],[Population]] -> 45.347279 | BD24: =Table12[[#This Row],[GHG emissions excl LULUCF]]*1000000/Table12[[#This Row],[Population]] -> 8.5285889 | BE24: =VLOOKUP($G24,EGR2023_MASTER!$B$4:$S$38,14,FALSE) -> #N/A | BF24: =VLOOKUP($G24,EGR2023_MASTER!$B$4:$S$38,15,FALSE) -> #N/A | BG24: =VLOOKUP($G24,EGR2023_MASTER!$B$4:$S$38,16,FALSE) -> #N/A | BH24: =IF(AND(BE24="Y",AND(BF24="credible",BG24="Y")),"higher",IF(BG24="Y","lower",IF(AND(BG24="N",OR(BE24="Y",BF24="credible")),"lower","much lower"))) -> #N/A | BI24: =IF(AND($BF24="credible",BG24="Y"),"stronger","weak") -> #N/A | BJ24: =(Table12[[#This Row],[Current Policies 2030 excl LULUCF]]/Table12[[#This Row],[GHG emissions excl LULUCF]])^(1/(2030-2021))-1 -> -0.055184836 | BK24: =IF(Table12[[#This Row],[Net-zero target status]]<=1,"",IF(Table12[[#This Row],[NZ GHG year]]="","",((MAX(Table12[[#This Row],[residual LULUCF emissions in 2050]],0.1)/Table12[[#This Row],[Current Policies 2030 excl LULUCF]])^(1/(Table12[[#This Row],[NZ GHG year]]-2021))-1))) -> -0.10849232 | BL24: =IF(Table12[[#This Row],[Net-zero target status]]<=1,"",IF(Table12[[#This Row],[NZ GHG year]]="","",((MAX(Table12[[#This Row],[residual LULUCF emissions in 2050]],0.1)/Table12[[#This Row],[GHG emissions excl LULUCF]])^(1/(Table12[[#This Row],[NZ GHG year]]-2021))-1))) -> -0.13214477 | BM24: =IF(Table12[[#This Row],[Net-zero target status]]<=1,"",IF(Table12[[#This Row],[NZ GHG year]]="","",((MAX(Table12[[#This Row],[residual LULUCF emissions in 2050]],0.1)/AVERAGE(Table12[[#This Row],[2030 conditional NDCs]:[2030 conditional NDCs2]]))^(1/(Table12[[#This Row],[NZ GHG year]]-2021))-1))) -> #DIV/0! | BR24: Austria | BT24: =IF(Table12[[#This Row],[Reduction rate 2021 to NZ target2]]="","",J24*(1+AN24)^(Table12[[#This Row],[NZ GHG year]]-2021)) -> 25.724151
A25: 0 | B25: 0 | C25: 31 | D25: 7 | E25: 16 | F25: ='input site'!M25 -> excl | G25: AZE | H25: Azerbaijan | I25: =VLOOKUP($G25,'NZT data'!$B$3:$C$200,2,FALSE) -> 0 | J25: ='input site'!AS25 -> 66.491822 | K25: ='input site'!BS25 -> 62.743263 | L25: =IF(I25>=1,O25,K25) -> 62.743263 | M25: =IF(I25>=1,O25,N25) -> 11.010685 | N25: ='input site'!EV25 -> 11.010685 | Q25: =IF(I25>=1,O25,R25) -> 10.464754 | R25: ='input site'!EZ25 -> 10.464754 | S25: ='input site'!FA25 -> 0 | T25: =Table12[[#This Row],[(Mt CO2 equivalent)]] -> Azerbaijan | U25: =VLOOKUP($G25,'NZT data'!$B$3:$F$200,4,FALSE) -> 2110 | V25: =VLOOKUP($G25,'NZT data'!$B$3:$F$200,5,FALSE) | W25: =-IF('LUC NGHGI'!EC15="",MIN('LUC NGHGI'!DW15,0.1),MIN('LUC NGHGI'!EC15,0.1)) -> 7.5860358 | X25: ='LUC NGHGI'!EC15 -> -7.5860358 | Y25: ='LUC NGHGI'!DY15 -> -7.5860358 | Z25: ='LUC NGHGI'!DZ15 -> -7.5860358 | AA25: =Table12[[#This Row],[2021 emissions]] -> 66.491822 | AB25: ='LUC NGHGI'!DW15 -> -7.7484998 | AC25: =IF(F25="incl",Table12[[#This Row],[GHG emissions incl LULUCF]]-Table12[[#This Row],[LULUCF emis-sions in 20213]],Table12[[#This Row],[GHG emissions incl LULUCF]]) -> 66.491822 | AD25: ='input site'!BS25 -> 62.743263 | AE25: ='LUC NGHGI'!EH15 -> -10.105428 | AF25: =IF(F25="incl",Table12[[#This Row],[Current Policies 2030 incl LULUCF]]-Table12[[#This Row],[LULUCF CurPol 2030]],Table12[[#This Row],[Current Policies 2030 incl LULUCF]]) -> 62.743263 | AG25: =IF(Table12[[#This Row],[Net-zero target status]]<=1,"",IF(Table12[[#This Row],[NZ GHG year]]="","",1000000000*(Table12[[#This Row],[residual LULUCF emissions in 2050]]-Table12[[#This Row],[GHG emissions excl LULUCF]])/(Table12[[#This Row],[NZ GHG year]]-2021)/Table12[[#This Row],[Population]])) | AH25: =IF(Table12[[#This Row],[Peak revised]]="Yes",IF(Table12[[#This Row],[Net-zero target status]]<=1,"",IF(Table12[[#This Row],[NZ GHG year]]="","",1000000000*(Table12[[#This Row],[residual LULUCF emissions in 2050]]-Table12[[#This Row],[GHG emissions excl LULUCF]])/(Table12[[#This Row],[NZ GHG year]]-2021)/Table12[[#This Row],[Population]])),"") | AI25: =MAX(0,(1000000*(Table12[[#This Row],[Current Policies 2030 excl LULUCF]]/2+Table12[[#This Row],[GHG emissions excl LULUCF]]/2)/Table12[[#This Row],[Population]]-$AI$8)*10)*$AI$10 -> 0 | AJ25: =IF(Table12[[#This Row],[Peak revised]]="No",IF(Table12[[#This Row],[Net-zero target status]]<=1,"",IF(Table12[[#This Row],[NZ GHG year]]="","",1000000000*(Table12[[#This Row],[residual LULUCF emissions in 2050]]-Table12[[#This Row],[Current Policies 2030 excl LULUCF]])/(Table12[[#This Row],[NZ GHG year]]-2021)/Table12[[#This Row],[Population]])),"") | AK25: =IF(Table12[[#This Row],[Formule no Peak (2)]]="","",Table12[[#This Row],[Penalty (1)]]+Table12[[#This Row],[Formule no Peak (2)]]) | AL25: =(Table12[[#This Row],[Current Policies 2030 excl LULUCF]]-Table12[[#This Row],[GHG emissions excl LULUCF]])/(2030-2021)/Table12[[#This Row],[GHG emissions excl LULUCF]] -> -0.0062640273 | AM25: =IF(Table12[[#This Row],[Net-zero target status]]<=1,"",IF(Table12[[#This Row],[NZ GHG year]]="","",(Table12[[#This Row],[residual LULUCF emissions in 2050]]-Table12[[#This Row],[Current Policies 2030 excl LULUCF]])/(Table12[[#This Row],[NZ GHG year]]-2030)/Table12[[#This Row],[Current Policies 2030 excl LULUCF]])) | AN25: =IF(Table12[[#This Row],[Net-zero target status]]<=1,"",IF(Table12[[#This Row],[NZ GHG year]]="","",(Table12[[#This Row],[residual LULUCF emissions in 2050]]-Table12[[#This Row],[GHG emissions excl LULUCF]])/(Table12[[#This Row],[NZ GHG year]]-2021)/Table12[[#This Row],[GHG emissions excl LULUCF]])) | AO25: =IF(Table12[[#This Row],[Net-zero target status]]<=1,"",IF(Table12[[#This Row],[NZ GHG year]]="","",(Table12[[#This Row],[residual LULUCF emissions in 2050]]-Table12[[#This Row],[2030 conditional NDCs]])/(Table12[[#This Row],[NZ GHG year]]-2030)/Table12[[#This Row],[2030 conditional NDCs]])) | AP25: =MAX('input site'!AH25:AS25) -> 70.862791 | AQ25: =IF(Table12[[#This Row],[Current Policies 2030 incl LULUCF]]>Table12[[#This Row],[Maximum inventory data]],"No","Yes") -> Yes | AR25: =IF(Table12[[#This Row],[Net-zero target status]]>=1.5,Table12[[#This Row],[residual LULUCF emissions in 2050]]/Table12[[#This Row],[GHG emissions excl LULUCF]],"") | AS25: ='input site'!BE25 -> 47.66515 | AT25: ='input site'!BF25 -> 47.66515 | AU25: ='input site'!BG25 -> 47.66515 | AV25: ='input site'!BH25 -> 47.66515 | AW25: =IF(Table12[[#This Row],[2030 unconditional NDCs]]="","",IF(F25="incl",Table12[[#This Row],[2030 unconditional NDCs]]-Table12[[#This Row],[LULUCF NDC uncond]],Table12[[#This Row],[2030 unconditional NDCs]])) -> 47.66515 | AX25: =IF(Table12[[#This Row],[2030 unconditional NDCs2]]="","",IF(F25="incl",Table12[[#This Row],[2030 unconditional NDCs2]]-Table12[[#This Row],[LULUCF NDC uncond]],Table12[[#This Row],[2030 unconditional NDCs2]])) -> 47.66515 | AY25: =IF(Table12[[#This Row],[2030 conditional NDCs]]="","",IF(F25="incl",Table12[[#This Row],[2030 conditional NDCs]]-Table12[[#This Row],[LULUCF NDC cond]],Table12[[#This Row],[2030 conditional NDCs]])) -> 47.66515 | AZ25: =IF(Table12[[#This Row],[2030 conditional NDCs2]]="","",IF(F25="incl",Table12[[#This Row],[2030 conditional NDCs2]]-Table12[[#This Row],[LULUCF NDC cond]],Table12[[#This Row],[2030 conditional NDCs2]])) -> 47.66515 | BA25: =VLOOKUP($G25,'Population90 20'!$C$6:$AU$231,37,FALSE) -> 10300205 | BB25: =VLOOKUP($G25,'Overview GDP (PPP)'!$C$6:$AI$231,33,FALSE) -> 1.591866e+08 | BC25: =Table12[[#This Row],[Income]]/Table12[[#This Row],[Population]] -> 15.454702 | BD25: =Table12[[#This Row],[GHG emissions excl LULUCF]]*1000000/Table12[[#This Row],[Population]] -> 6.4553882 | BE25: =VLOOKUP($G25,EGR2023_MASTER!$B$4:$S$38,14,FALSE) -> #N/A | BF25: =VLOOKUP($G25,EGR2023_MASTER!$B$4:$S$38,15,FALSE) -> #N/A | BG25: =VLOOKUP($G25,EGR2023_MASTER!$B$4:$S$38,16,FALSE) -> #N/A | BH25: =IF(AND(BE25="Y",AND(BF25="credible",BG25="Y")),"higher",IF(BG25="Y","lower",IF(AND(BG25="N",OR(BE25="Y",BF25="credible")),"lower","much lower"))) -> #N/A | BI25: =IF(AND($BF25="credible",BG25="Y"),"stronger","weak") -> #N/A | BJ25: =(Table12[[#This Row],[Current Policies 2030 excl LULUCF]]/Table12[[#This Row],[GHG emissions excl LULUCF]])^(1/(2030-2021))-1 -> -0.0064267879 | BK25: =IF(Table12[[#This Row],[Net-zero target status]]<=1,"",IF(Table12[[#This Row],[NZ GHG year]]="","",((MAX(Table12[[#This Row],[residual LULUCF emissions in 2050]],0.1)/Table12[[#This Row],[Current Policies 2030 excl LULUCF]])^(1/(Table12[[#This Row],[NZ GHG year]]-2021))-1))) | BL25: =IF(Table12[[#This Row],[Net-zero target status]]<=1,"",IF(Table12[[#This Row],[NZ GHG year]]="","",((MAX(Table12[[#This Row],[residual LULUCF emissions in 2050]],0.1)/Table12[[#This Row],[GHG emissions excl LULUCF]])^(1/(Table12[[#This Row],[NZ GHG year]]-2021))-1))) | BM25: =IF(Table12[[#This Row],[Net-zero target status]]<=1,"",IF(Table12[[#This Row],[NZ GHG year]]="","",((MAX(Table12[[#This Row],[residual LULUCF emissions in 2050]],0.1)/AVERAGE(Table12[[#This Row],[2030 conditional NDCs]:[2030 conditional NDCs2]]))^(1/(Table12[[#This Row],[NZ GHG year]]-2021))-1))) | BR25: Azerbaijan | BT25: =IF(Table12[[#This Row],[Reduction rate 2021 to NZ target2]]="","",J25*(1+AN25)^(Table12[[#This Row],[NZ GHG year]]-2021))
A26: 0 | B26: 0 | C26: 44 | D26: 11 | E26: 4 | F26: ='input site'!M26 -> excl | G26: BHS | H26: Bahamas | I26: =VLOOKUP($G26,'NZT data'!$B$3:$C$200,2,FALSE) -> 1 | J26: ='input site'!AS26 -> 3.107964 | K26: ='input site'!BS26 -> 3.8323346 | L26: =IF(I26>=1,O26,K26) -> 0 | M26: =IF(I26>=1,O26,N26) -> 0 | N26: ='input site'!EV26 -> 1.7381268 | O26: 0 | P26: =O26-N26 -> -1.7381268 | Q26: =IF(I26>=1,O26,R26) -> 0 | R26: ='input site'!EZ26 -> 0.35350093 | S26: ='input site'!FA26 -> 2050 | T26: =Table12[[#This Row],[(Mt CO2 equivalent)]] -> Bahamas | U26: =VLOOKUP($G26,'NZT data'!$B$3:$F$200,4,FALSE) -> 2110 | V26: =VLOOKUP($G26,'NZT data'!$B$3:$F$200,5,FALSE) -> 2110 | W26: =-IF('LUC NGHGI'!EC16="",MIN('LUC NGHGI'!DW16,0.1),MIN('LUC NGHGI'!EC16,0.1)) -> -0.1 | X26: ='LUC NGHGI'!EC16 -> 2.6087596 | Y26: ='LUC NGHGI'!DY16 -> 2.6087596 | Z26: ='LUC NGHGI'!DZ16 -> 2.6087596 | AA26: =Table12[[#This Row],[2021 emissions]] -> 3.107964 | AB26: ='LUC NGHGI'!DW16 -> 2.626176 | AC26: =IF(F26="incl",Table12[[#This Row],[GHG emissions incl LULUCF]]-Table12[[#This Row],[LULUCF emis-sions in 20213]],Table12[[#This Row],[GHG emissions incl LULUCF]]) -> 3.107964 | AD26: ='input site'!BS26 -> 3.8323346 | AE26: ='LUC NGHGI'!EH16 -> 1.5510422 | AF26: =IF(F26="incl",Table12[[#This Row],[Current Policies 2030 incl LULUCF]]-Table12[[#This Row],[LULUCF CurPol 2030]],Table12[[#This Row],[Current Policies 2030 incl LULUCF]]) -> 3.8323346 | AG26: =IF(Table12[[#This Row],[Net-zero target status]]<=1,"",IF(Table12[[#This Row],[NZ GHG year]]="","",1000000000*(Table12[[#This Row],[residual LULUCF emissions in 2050]]-Table12[[#This Row],[GHG emissions excl LULUCF]])/(Table12[[#This Row],[NZ GHG year]]-2021)/Table12[[#This Row],[Population]])) | AH26: =IF(Table12[[#This Row],[Peak revised]]="Yes",IF(Table12[[#This Row],[Net-zero target status]]<=1,"",IF(Table12[[#This Row],[NZ GHG year]]="","",1000000000*(Table12[[#This Row],[residual LULUCF emissions in 2050]]-Table12[[#This Row],[GHG emissions excl LULUCF]])/(Table12[[#This Row],[NZ GHG year]]-2021)/Table12[[#This Row],[Population]])),"") | AI26: =MAX(0,(1000000*(Table12[[#This Row],[Current Policies 2030 excl LULUCF]]/2+Table12[[#This Row],[GHG emissions excl LULUCF]]/2)/Table12[[#This Row],[Population]]-$AI$8)*10)*$AI$10 -> -166.41965 | AJ26: =IF(Table12[[#This Row],[Peak revised]]="No",IF(Table12[[#This Row],[Net-zero target status]]<=1,"",IF(Table12[[#This Row],[NZ GHG year]]="","",1000000000*(Table12[[#This Row],[residual LULUCF emissions in 2050]]-Table12[[#This Row],[Current Policies 2030 excl LULUCF]])/(Table12[[#This Row],[NZ GHG year]]-2021)/Table12[[#This Row],[Population]])),"") | AK26: =IF(Table12[[#This Row],[Formule no Peak (2)]]="","",Table12[[#This Row],[Penalty (1)]]+Table12[[#This Row],[Formule no Peak (2)]]) | AL26: =(Table12[[#This Row],[Current Policies 2030 excl LULUCF]]-Table12[[#This Row],[GHG emissions excl LULUCF]])/(2030-2021)/Table12[[#This Row],[GHG emissions excl LULUCF]] -> 0.025896577 | AM26: =IF(Table12[[#This Row],[Net-zero target status]]<=1,"",IF(Table12[[#This Row],[NZ GHG year]]="","",(Table12[[#This Row],[residual LULUCF emissions in 2050]]-Table12[[#This Row],[Current Policies 2030 excl LULUCF]])/(Table12[[#This Row],[NZ GHG year]]-2030)/Table12[[#This Row],[Current Policies 2030 excl LULUCF]])) | AN26: =IF(Table12[[#This Row],[Net-zero target status]]<=1,"",IF(Table12[[#This Row],[NZ GHG year]]="","",(Table12[[#This Row],[residual LULUCF emissions in 2050]]-Table12[[#This Row],[GHG emissions excl LULUCF]])/(Table12[[#This Row],[NZ GHG year]]-2021)/Table12[[#This Row],[GHG emissions excl LULUCF]])) | AO26: =IF(Table12[[#This Row],[Net-zero target status]]<=1,"",IF(Table12[[#This Row],[NZ GHG year]]="","",(Table12[[#This Row],[residual LULUCF emissions in 2050]]-Table12[[#This Row],[2030 conditional NDCs]])/(Table12[[#This Row],[NZ GHG year]]-2030)/Table12[[#This Row],[2030 conditional NDCs]])) | AP26: =MAX('input site'!AH26:AS26) -> 3.386214 | AQ26: =IF(Table12[[#This Row],[Current Policies 2030 incl LULUCF]]>Table12[[#This Row],[Maximum inventory data]],"No","Yes") -> No | AR26: =IF(Table12[[#This Row],[Net-zero target status]]>=1.5,Table12[[#This Row],[residual LULUCF emissions in 2050]]/Table12[[#This Row],[GHG emissions excl LULUCF]],"") | AS26: ='input site'!BE26 | AU26: ='input site'!BG26 -> 3.7531781 | AV26: ='input site'!BH26 -> 3.7531781 | AW26: =IF(Table12[[#This Row],[2030 unconditional NDCs]]="","",IF(F26="incl",Table12[[#This Row],[2030 unconditional NDCs]]-Table12[[#This Row],[LULUCF NDC uncond]],Table12[[#This Row],[2030 unconditional NDCs]])) | AX26: =IF(Table12[[#This Row],[2030 unconditional NDCs2]]="","",IF(F26="incl",Table12[[#This Row],[2030 unconditional NDCs2]]-Table12[[#This Row],[LULUCF NDC uncond]],Table12[[#This Row],[2030 unconditional NDCs2]])) | AY26: =IF(Table12[[#This Row],[2030 conditional NDCs]]="","",IF(F26="incl",Table12[[#This Row],[2030 conditional NDCs]]-Table12[[#This Row],[LULUCF NDC cond]],Table12[[#This Row],[2030 conditional NDCs]])) -> 3.7531781 | AZ26: =IF(Table12[[#This Row],[2030 conditional NDCs2]]="","",IF(F26="incl",Table12[[#This Row],[2030 conditional NDCs2]]-Table12[[#This Row],[LULUCF NDC cond]],Table12[[#This Row],[2030 conditional NDCs2]])) -> 3.7531781 | BA26: =VLOOKUP($G26,'Population90 20'!$C$6:$AU$231,37,FALSE) -> 400516 | BB26: =VLOOKUP($G26,'Overview GDP (PPP)'!$C$6:$AI$231,33,FALSE) -> 11210603 | BC26: =Table12[[#This Row],[Income]]/Table12[[#This Row],[Population]] -> 27.990399 | BD26: =Table12[[#This Row],[GHG emissions excl LULUCF]]*1000000/Table12[[#This Row],[Population]] -> 7.7598997 | BE26: =VLOOKUP($G26,EGR2023_MASTER!$B$4:$S$38,14,FALSE) -> #N/A | BF26: =VLOOKUP($G26,EGR2023_MASTER!$B$4:$S$38,15,FALSE) -> #N/A | BG26: =VLOOKUP($G26,EGR2023_MASTER!$B$4:$S$38,16,FALSE) -> #N/A | BH26: =IF(AND(BE26="Y",AND(BF26="credible",BG26="Y")),"higher",IF(BG26="Y","lower",IF(AND(BG26="N",OR(BE26="Y",BF26="credible")),"lower","much lower"))) -> #N/A | BI26: =IF(AND($BF26="credible",BG26="Y"),"stronger","weak") -> #N/A | BJ26: =(Table12[[#This Row],[Current Policies 2030 excl LULUCF]]/Table12[[#This Row],[GHG emissions excl LULUCF]])^(1/(2030-2021))-1 -> 0.02355154 | BK26: =IF(Table12[[#This Row],[Net-zero target status]]<=1,"",IF(Table12[[#This Row],[NZ GHG year]]="","",((MAX(Table12[[#This Row],[residual LULUCF emissions in 2050]],0.1)/Table12[[#This Row],[Current Policies 2030 excl LULUCF]])^(1/(Table12[[#This Row],[NZ GHG year]]-2021))-1))) | BL26: =IF(Table12[[#This Row],[Net-zero target status]]<=1,"",IF(Table12[[#This Row],[NZ GHG year]]="","",((MAX(Table12[[#This Row],[residual LULUCF emissions in 2050]],0.1)/Table12[[#This Row],[GHG emissions excl LULUCF]])^(1/(Table12[[#This Row],[NZ GHG year]]-2021))-1))) | BM26: =IF(Table12[[#This Row],[Net-zero target status]]<=1,"",IF(Table12[[#This Row],[NZ GHG year]]="","",((MAX(Table12[[#This Row],[residual LULUCF emissions in 2050]],0.1)/AVERAGE(Table12[[#This Row],[2030 conditional NDCs]:[2030 conditional NDCs2]]))^(1/(Table12[[#This Row],[NZ GHG year]]-2021))-1))) | BR26: Bahamas | BT26: =IF(Table12[[#This Row],[Reduction rate 2021 to NZ target2]]="","",J26*(1+AN26)^(Table12[[#This Row],[NZ GHG year]]-2021))
A27: 0 | B27: 0 | C27: 48 | D27: 12 | E27: 17 | F27: ='input site'!M27 -> excl | G27: BHR | H27: Bahrain | I27: =VLOOKUP($G27,'NZT data'!$B$3:$C$200,2,FALSE) -> 2 | J27: ='input site'!AS27 -> 30.391856 | K27: ='input site'!BS27 -> 30.178257 | L27: =IF(I27>=1,O27,K27) -> 0 | M27: =IF(I27>=1,O27,N27) -> 0 | N27: ='input site'!EV27 -> 15.716037 | Q27: =IF(I27>=1,O27,R27) -> 0 | R27: ='input site'!EZ27 -> 2.7375605 | S27: ='input site'!FA27 -> 0 | T27: =Table12[[#This Row],[(Mt CO2 equivalent)]] -> Bahrain | U27: =VLOOKUP($G27,'NZT data'!$B$3:$F$200,4,FALSE) -> 2060 | V27: =VLOOKUP($G27,'NZT data'!$B$3:$F$200,5,FALSE) -> 2075 | W27: =-IF('LUC NGHGI'!EC17="",MIN('LUC NGHGI'!DW17,0.1),MIN('LUC NGHGI'!EC17,0.1)) -> 0.0248 | X27: ='LUC NGHGI'!EC17 -> -0.0248 | Y27: ='LUC NGHGI'!DY17 -> -0.0248 | Z27: ='LUC NGHGI'!DZ17 -> -0.0248 | AA27: =Table12[[#This Row],[2021 emissions]] -> 30.391856 | AB27: ='LUC NGHGI'!DW17 -> -0.0248 | AC27: =IF(F27="incl",Table12[[#This Row],[GHG emissions incl LULUCF]]-Table12[[#This Row],[LULUCF emis-sions in 20213]],Table12[[#This Row],[GHG emissions incl LULUCF]]) -> 30.391856 | AD27: ='input site'!BS27 -> 30.178257 | AE27: ='LUC NGHGI'!EH17 -> -0.031253049 | AF27: =IF(F27="incl",Table12[[#This Row],[Current Policies 2030 incl LULUCF]]-Table12[[#This Row],[LULUCF CurPol 2030]],Table12[[#This Row],[Current Policies 2030 incl LULUCF]]) -> 30.178257 | AG27: =IF(Table12[[#This Row],[Net-zero target status]]<=1,"",IF(Table12[[#This Row],[NZ GHG year]]="","",1000000000*(Table12[[#This Row],[residual LULUCF emissions in 2050]]-Table12[[#This Row],[GHG emissions excl LULUCF]])/(Table12[[#This Row],[NZ GHG year]]-2021)/Table12[[#This Row],[Population]])) -> -315.22323 | AH27: =IF(Table12[[#This Row],[Peak revised]]="Yes",IF(Table12[[#This Row],[Net-zero target status]]<=1,"",IF(Table12[[#This Row],[NZ GHG year]]="","",1000000000*(Table12[[#This Row],[residual LULUCF emissions in 2050]]-Table12[[#This Row],[GHG emissions excl LULUCF]])/(Table12[[#This Row],[NZ GHG year]]-2021)/Table12[[#This Row],[Population]])),"") -> -315.22323 | AI27: =MAX(0,(1000000*(Table12[[#This Row],[Current Policies 2030 excl LULUCF]]/2+Table12[[#This Row],[GHG emissions excl LULUCF]]/2)/Table12[[#This Row],[Population]]-$AI$8)*10)*$AI$10 -> -997.60903 | AJ27: =IF(Table12[[#This Row],[Peak revised]]="No",IF(Table12[[#This Row],[Net-zero target status]]<=1,"",IF(Table12[[#This Row],[NZ GHG year]]="","",1000000000*(Table12[[#This Row],[residual LULUCF emissions in 2050]]-Table12[[#This Row],[Current Policies 2030 excl LULUCF]])/(Table12[[#This Row],[NZ GHG year]]-2021)/Table12[[#This Row],[Population]])),"") | AK27: =IF(Table12[[#This Row],[Formule no Peak (2)]]="","",Table12[[#This Row],[Penalty (1)]]+Table12[[#This Row],[Formule no Peak (2)]]) | AL27: =(Table12[[#This Row],[Current Policies 2030 excl LULUCF]]-Table12[[#This Row],[GHG emissions excl LULUCF]])/(2030-2021)/Table12[[#This Row],[GHG emissions excl LULUCF]] -> -0.00078090693 | AM27: =IF(Table12[[#This Row],[Net-zero target status]]<=1,"",IF(Table12[[#This Row],[NZ GHG year]]="","",(Table12[[#This Row],[residual LULUCF emissions in 2050]]-Table12[[#This Row],[Current Policies 2030 excl LULUCF]])/(Table12[[#This Row],[NZ GHG year]]-2030)/Table12[[#This Row],[Current Policies 2030 excl LULUCF]])) -> -0.02220396 | AN27: =IF(Table12[[#This Row],[Net-zero target status]]<=1,"",IF(Table12[[#This Row],[NZ GHG year]]="","",(Table12[[#This Row],[residual LULUCF emissions in 2050]]-Table12[[#This Row],[GHG emissions excl LULUCF]])/(Table12[[#This Row],[NZ GHG year]]-2021)/Table12[[#This Row],[GHG emissions excl LULUCF]])) -> -0.018503407 | AO27: =IF(Table12[[#This Row],[Net-zero target status]]<=1,"",IF(Table12[[#This Row],[NZ GHG year]]="","",(Table12[[#This Row],[residual LULUCF emissions in 2050]]-Table12[[#This Row],[2030 conditional NDCs]])/(Table12[[#This Row],[NZ GHG year]]-2030)/Table12[[#This Row],[2030 conditional NDCs]])) -> #VALUE! | AP27: =MAX('input site'!AH27:AS27) -> 37.885545 | AQ27: =IF(Table12[[#This Row],[Current Policies 2030 incl LULUCF]]>Table12[[#This Row],[Maximum inventory data]],"No","Yes") -> Yes | AR27: =IF(Table12[[#This Row],[Net-zero target status]]>=1.5,Table12[[#This Row],[residual LULUCF emissions in 2050]]/Table12[[#This Row],[GHG emissions excl LULUCF]],"") -> 0.00081600808 | AS27: ='input site'!BE27 | AU27: ='input site'!BG27 | AW27: =IF(Table12[[#This Row],[2030 unconditional NDCs]]="","",IF(F27="incl",Table12[[#This Row],[2030 unconditional NDCs]]-Table12[[#This Row],[LULUCF NDC uncond]],Table12[[#This Row],[2030 unconditional NDCs]])) | AX27: =IF(Table12[[#This Row],[2030 unconditional NDCs2]]="","",IF(F27="incl",Table12[[#This Row],[2030 unconditional NDCs2]]-Table12[[#This Row],[LULUCF NDC uncond]],Table12[[#This Row],[2030 unconditional NDCs2]])) | AY27: =IF(Table12[[#This Row],[2030 conditional NDCs]]="","",IF(F27="incl",Table12[[#This Row],[2030 conditional NDCs]]-Table12[[#This Row],[LULUCF NDC cond]],Table12[[#This Row],[2030 conditional NDCs]])) | AZ27: =IF(Table12[[#This Row],[2030 conditional NDCs2]]="","",IF(F27="incl",Table12[[#This Row],[2030 conditional NDCs2]]-Table12[[#This Row],[LULUCF NDC cond]],Table12[[#This Row],[2030 conditional NDCs2]])) | BA27: =VLOOKUP($G27,'Population90 20'!$C$6:$AU$231,37,FALSE) -> 1783983 | BB27: =VLOOKUP($G27,'Overview GDP (PPP)'!$C$6:$AI$231,33,FALSE) -> 65874537 | BC27: =Table12[[#This Row],[Income]]/Table12[[#This Row],[Population]] -> 36.925541 | BD27: =Table12[[#This Row],[GHG emissions excl LULUCF]]*1000000/Table12[[#This Row],[Population]] -> 17.035956 | BE27: =VLOOKUP($G27,EGR2023_MASTER!$B$4:$S$38,14,FALSE) -> #N/A | BF27: =VLOOKUP($G27,EGR2023_MASTER!$B$4:$S$38,15,FALSE) -> #N/A | BG27: =VLOOKUP($G27,EGR2023_MASTER!$B$4:$S$38,16,FALSE) -> #N/A | BH27: =IF(AND(BE27="Y",AND(BF27="credible",BG27="Y")),"higher",IF(BG27="Y","lower",IF(AND(BG27="N",OR(BE27="Y",BF27="credible")),"lower","much lower"))) -> #N/A | BI27: =IF(AND($BF27="credible",BG27="Y"),"stronger","weak") -> #N/A | BJ27: =(Table12[[#This Row],[Current Policies 2030 excl LULUCF]]/Table12[[#This Row],[GHG emissions excl LULUCF]])^(1/(2030-2021))-1 -> -0.00078335704 | BK27: =IF(Table12[[#This Row],[Net-zero target status]]<=1,"",IF(Table12[[#This Row],[NZ GHG year]]="","",((MAX(Table12[[#This Row],[residual LULUCF emissions in 2050]],0.1)/Table12[[#This Row],[Current Policies 2030 excl LULUCF]])^(1/(Table12[[#This Row],[NZ GHG year]]-2021))-1))) -> -0.10033725 | BL27: =IF(Table12[[#This Row],[Net-zero target status]]<=1,"",IF(Table12[[#This Row],[NZ GHG year]]="","",((MAX(Table12[[#This Row],[residual LULUCF emissions in 2050]],0.1)/Table12[[#This Row],[GHG emissions excl LULUCF]])^(1/(Table12[[#This Row],[NZ GHG year]]-2021))-1))) -> -0.10045475 | BM27: =IF(Table12[[#This Row],[Net-zero target status]]<=1,"",IF(Table12[[#This Row],[NZ GHG year]]="","",((MAX(Table12[[#This Row],[residual LULUCF emissions in 2050]],0.1)/AVERAGE(Table12[[#This Row],[2030 conditional NDCs]:[2030 conditional NDCs2]]))^(1/(Table12[[#This Row],[NZ GHG year]]-2021))-1))) -> #DIV/0! | BR27: Bahrain | BT27: =IF(Table12[[#This Row],[Reduction rate 2021 to NZ target2]]="","",J27*(1+AN27)^(Table12[[#This Row],[NZ GHG year]]-2021)) -> 11.085422
A28: 0 | B28: 0 | C28: 50 | D28: 13 | E28: 25 | F28: ='input site'!M28 -> excl | G28: BGD | H28: Bangladesh | I28: =VLOOKUP($G28,'NZT data'!$B$3:$C$200,2,FALSE) -> 1 | J28: ='input site'!AS28 -> 203.90574 | K28: ='input site'!BS28 -> 248.03692 | L28: =IF(I28>=1,O28,K28) -> 0 | M28: =IF(I28>=1,O28,N28) -> 0 | N28: ='input site'!EV28 -> 122.00198 | Q28: =IF(I28>=1,O28,R28) -> 0 | R28: ='input site'!EZ28 -> 51.129986 | S28: ='input site'!FA28 -> 2050 | T28: =Table12[[#This Row],[(Mt CO2 equivalent)]] -> Bangladesh | U28: =VLOOKUP($G28,'NZT data'!$B$3:$F$200,4,FALSE) -> 2110 | V28: =VLOOKUP($G28,'NZT data'!$B$3:$F$200,5,FALSE) -> 2110 | W28: =-IF('LUC NGHGI'!EC18="",MIN('LUC NGHGI'!DW18,0.1),MIN('LUC NGHGI'!EC18,0.1)) -> -0.1 | X28: ='LUC NGHGI'!EC18 -> 8.2258266 | Y28: ='LUC NGHGI'!DY18 -> 8.2258266 | Z28: ='LUC NGHGI'!DZ18 -> 8.2258266 | AA28: =Table12[[#This Row],[2021 emissions]] -> 203.90574 | AB28: ='LUC NGHGI'!DW18 -> 8.3191934 | AC28: =IF(F28="incl",Table12[[#This Row],[GHG emissions incl LULUCF]]-Table12[[#This Row],[LULUCF emis-sions in 20213]],Table12[[#This Row],[GHG emissions incl LULUCF]]) -> 203.90574 | AD28: ='input site'!BS28 -> 248.03692 | AE28: ='LUC NGHGI'!EH18 -> 7.6369218 | AF28: =IF(F28="incl",Table12[[#This Row],[Current Policies 2030 incl LULUCF]]-Table12[[#This Row],[LULUCF CurPol 2030]],Table12[[#This Row],[Current Policies 2030 incl LULUCF]]) -> 248.03692 | AG28: =IF(Table12[[#This Row],[Net-zero target status]]<=1,"",IF(Table12[[#This Row],[NZ GHG year]]="","",1000000000*(Table12[[#This Row],[residual LULUCF emissions in 2050]]-Table12[[#This Row],[GHG emissions excl LULUCF]])/(Table12[[#This Row],[NZ GHG year]]-2021)/Table12[[#This Row],[Population]])) | AH28: =IF(Table12[[#This Row],[Peak revised]]="Yes",IF(Table12[[#This Row],[Net-zero target status]]<=1,"",IF(Table12[[#This Row],[NZ GHG year]]="","",1000000000*(Table12[[#This Row],[residual LULUCF emissions in 2050]]-Table12[[#This Row],[GHG emissions excl LULUCF]])/(Table12[[#This Row],[NZ GHG year]]-2021)/Table12[[#This Row],[Population]])),"") | AI28: =MAX(0,(1000000*(Table12[[#This Row],[Current Policies 2030 excl LULUCF]]/2+Table12[[#This Row],[GHG emissions excl LULUCF]]/2)/Table12[[#This Row],[Population]]-$AI$8)*10)*$AI$10 -> 0 | AJ28: =IF(Table12[[#This Row],[Peak revised]]="No",IF(Table12[[#This Row],[Net-zero target status]]<=1,"",IF(Table12[[#This Row],[NZ GHG year]]="","",1000000000*(Table12[[#This Row],[residual LULUCF emissions in 2050]]-Table12[[#This Row],[Current Policies 2030 excl LULUCF]])/(Table12[[#This Row],[NZ GHG year]]-2021)/Table12[[#This Row],[Population]])),"") | AK28: =IF(Table12[[#This Row],[Formule no Peak (2)]]="","",Table12[[#This Row],[Penalty (1)]]+Table12[[#This Row],[Formule no Peak (2)]]) | AL28: =(Table12[[#This Row],[Current Policies 2030 excl LULUCF]]-Table12[[#This Row],[GHG emissions excl LULUCF]])/(2030-2021)/Table12[[#This Row],[GHG emissions excl LULUCF]] -> 0.024047702 | AM28: =IF(Table12[[#This Row],[Net-zero target status]]<=1,"",IF(Table12[[#This Row],[NZ GHG year]]="","",(Table12[[#This Row],[residual LULUCF emissions in 2050]]-Table12[[#This Row],[Current Policies 2030 excl LULUCF]])/(Table12[[#This Row],[NZ GHG year]]-2030)/Table12[[#This Row],[Current Policies 2030 excl LULUCF]])) | AN28: =IF(Table12[[#This Row],[Net-zero target status]]<=1,"",IF(Table12[[#This Row],[NZ GHG year]]="","",(Table12[[#This Row],[residual LULUCF emissions in 2050]]-Table12[[#This Row],[GHG emissions excl LULUCF]])/(Table12[[#This Row],[NZ GHG year]]-2021)/Table12[[#This Row],[GHG emissions excl LULUCF]])) | AO28: =IF(Table12[[#This Row],[Net-zero target status]]<=1,"",IF(Table12[[#This Row],[NZ GHG year]]="","",(Table12[[#This Row],[residual LULUCF emissions in 2050]]-Table12[[#This Row],[2030 conditional NDCs]])/(Table12[[#This Row],[NZ GHG year]]-2030)/Table12[[#This Row],[2030 conditional NDCs]])) | AP28: =MAX('input site'!AH28:AS28) -> 203.90574 | AQ28: =IF(Table12[[#This Row],[Current Policies 2030 incl LULUCF]]>Table12[[#This Row],[Maximum inventory data]],"No","Yes") -> No | AR28: =IF(Table12[[#This Row],[Net-zero target status]]>=1.5,Table12[[#This Row],[residual LULUCF emissions in 2050]]/Table12[[#This Row],[GHG emissions excl LULUCF]],"") | AS28: ='input site'!BE28 -> 381.85671 | AT28: ='input site'!BF28 -> 381.85671 | AU28: ='input site'!BG28 -> 347.50721 | AV28: ='input site'!BH28 -> 347.50721 | AW28: =IF(Table12[[#This Row],[2030 unconditional NDCs]]="","",IF(F28="incl",Table12[[#This Row],[2030 unconditional NDCs]]-Table12[[#This Row],[LULUCF NDC uncond]],Table12[[#This Row],[2030 unconditional NDCs]])) -> 381.85671 | AX28: =IF(Table12[[#This Row],[2030 unconditional NDCs2]]="","",IF(F28="incl",Table12[[#This Row],[2030 unconditional NDCs2]]-Table12[[#This Row],[LULUCF NDC uncond]],Table12[[#This Row],[2030 unconditional NDCs2]])) -> 381.85671 | AY28: =IF(Table12[[#This Row],[2030 conditional NDCs]]="","",IF(F28="incl",Table12[[#This Row],[2030 conditional NDCs]]-Table12[[#This Row],[LULUCF NDC cond]],Table12[[#This Row],[2030 conditional NDCs]])) -> 347.50721 | AZ28: =IF(Table12[[#This Row],[2030 conditional NDCs2]]="","",IF(F28="incl",Table12[[#This Row],[2030 conditional NDCs2]]-Table12[[#This Row],[LULUCF NDC cond]],Table12[[#This Row],[2030 conditional NDCs2]])) -> 347.50721 | BA28: =VLOOKUP($G28,'Population90 20'!$C$6:$AU$231,37,FALSE) -> 167885689 | BB28: =VLOOKUP($G28,'Overview GDP (PPP)'!$C$6:$AI$231,33,FALSE) -> 6.2592614e+08 | BC28: =Table12[[#This Row],[Income]]/Table12[[#This Row],[Population]] -> 3.7282876 | BD28: =Table12[[#This Row],[GHG emissions excl LULUCF]]*1000000/Table12[[#This Row],[Population]] -> 1.2145511 | BE28: =VLOOKUP($G28,EGR2023_MASTER!$B$4:$S$38,14,FALSE) -> #N/A | BF28: =VLOOKUP($G28,EGR2023_MASTER!$B$4:$S$38,15,FALSE) -> #N/A | BG28: =VLOOKUP($G28,EGR2023_MASTER!$B$4:$S$38,16,FALSE) -> #N/A | BH28: =IF(AND(BE28="Y",AND(BF28="credible",BG28="Y")),"higher",IF(BG28="Y","lower",IF(AND(BG28="N",OR(BE28="Y",BF28="credible")),"lower","much lower"))) -> #N/A | BI28: =IF(AND($BF28="credible",BG28="Y"),"stronger","weak") -> #N/A | BJ28: =(Table12[[#This Row],[Current Policies 2030 excl LULUCF]]/Table12[[#This Row],[GHG emissions excl LULUCF]])^(1/(2030-2021))-1 -> 0.022007535 | BK28: =IF(Table12[[#This Row],[Net-zero target status]]<=1,"",IF(Table12[[#This Row],[NZ GHG year]]="","",((MAX(Table12[[#This Row],[residual LULUCF emissions in 2050]],0.1)/Table12[[#This Row],[Current Policies 2030 excl LULUCF]])^(1/(Table12[[#This Row],[NZ GHG year]]-2021))-1))) | BL28: =IF(Table12[[#This Row],[Net-zero target status]]<=1,"",IF(Table12[[#This Row],[NZ GHG year]]="","",((MAX(Table12[[#This Row],[residual LULUCF emissions in 2050]],0.1)/Table12[[#This Row],[GHG emissions excl LULUCF]])^(1/(Table12[[#This Row],[NZ GHG year]]-2021))-1))) | BM28: =IF(Table12[[#This Row],[Net-zero target status]]<=1,"",IF(Table12[[#This Row],[NZ GHG year]]="","",((MAX(Table12[[#This Row],[residual LULUCF emissions in 2050]],0.1)/AVERAGE(Table12[[#This Row],[2030 conditional NDCs]:[2030 conditional NDCs2]]))^(1/(Table12[[#This Row],[NZ GHG year]]-2021))-1))) | BR28: Bangladesh | BT28: =IF(Table12[[#This Row],[Reduction rate 2021 to NZ target2]]="","",J28*(1+AN28)^(Table12[[#This Row],[NZ GHG year]]-2021))
A29: 0 | B29: 0 | C29: 52 | D29: 15 | E29: 4 | F29: ='input site'!M29 -> incl | G29: BRB | H29: Barbados | I29: =VLOOKUP($G29,'NZT data'!$B$3:$C$200,2,FALSE) -> 3 | J29: ='input site'!AS29 -> 4.9662674 | K29: ='input site'!BS29 -> 6.1237513 | L29: =IF(I29>=1,O29,K29) -> 0 | M29: =IF(I29>=1,O29,N29) -> 0 | N29: ='input site'!EV29 -> 2.7320572 | Q29: =IF(I29>=1,O29,R29) -> 0 | R29: ='input site'!EZ29 -> 0.55564689 | S29: ='input site'!FA29 -> 0 | T29: =Table12[[#This Row],[(Mt CO2 equivalent)]] -> Barbados | U29: =VLOOKUP($G29,'NZT data'!$B$3:$F$200,4,FALSE) -> 2030 | V29: =VLOOKUP($G29,'NZT data'!$B$3:$F$200,5,FALSE) -> 2030 | W29: =-IF('LUC NGHGI'!EC19="",MIN('LUC NGHGI'!DW19,0.1),MIN('LUC NGHGI'!EC19,0.1)) -> 0.087220779 | X29: ='LUC NGHGI'!EC19 -> -0.087220779 | Y29: ='LUC NGHGI'!DY19 -> -0.087220779 | Z29: ='LUC NGHGI'!DZ19 -> -0.087220779 | AA29: =Table12[[#This Row],[2021 emissions]] -> 4.9662674 | AB29: ='LUC NGHGI'!DW19 -> -0.089972294 | AC29: =IF(F29="incl",Table12[[#This Row],[GHG emissions incl LULUCF]]-Table12[[#This Row],[LULUCF emis-sions in 20213]],Table12[[#This Row],[GHG emissions incl LULUCF]]) -> 5.0562397 | AD29: ='input site'!BS29 -> 6.1237513 | AE29: ='LUC NGHGI'!EH19 -> -0.1225843 | AF29: =IF(F29="incl",Table12[[#This Row],[Current Policies 2030 incl LULUCF]]-Table12[[#This Row],[LULUCF CurPol 2030]],Table12[[#This Row],[Current Policies 2030 incl LULUCF]]) -> 6.2463356 | AG29: =IF(Table12[[#This Row],[Net-zero target status]]<=1,"",IF(Table12[[#This Row],[NZ GHG year]]="","",1000000000*(Table12[[#This Row],[residual LULUCF emissions in 2050]]-Table12[[#This Row],[GHG emissions excl LULUCF]])/(Table12[[#This Row],[NZ GHG year]]-2021)/Table12[[#This Row],[Population]])) -> -1916.9067 | AH29: =IF(Table12[[#This Row],[Peak revised]]="Yes",IF(Table12[[#This Row],[Net-zero target status]]<=1,"",IF(Table12[[#This Row],[NZ GHG year]]="","",1000000000*(Table12[[#This Row],[residual LULUCF emissions in 2050]]-Table12[[#This Row],[GHG emissions excl LULUCF]])/(Table12[[#This Row],[NZ GHG year]]-2021)/Table12[[#This Row],[Population]])),"") | AI29: =MAX(0,(1000000*(Table12[[#This Row],[Current Policies 2030 excl LULUCF]]/2+Table12[[#This Row],[GHG emissions excl LULUCF]]/2)/Table12[[#This Row],[Population]]-$AI$8)*10)*$AI$10 -> -1262.096 | AJ29: =IF(Table12[[#This Row],[Peak revised]]="No",IF(Table12[[#This Row],[Net-zero target status]]<=1,"",IF(Table12[[#This Row],[NZ GHG year]]="","",1000000000*(Table12[[#This Row],[residual LULUCF emissions in 2050]]-Table12[[#This Row],[Current Policies 2030 excl LULUCF]])/(Table12[[#This Row],[NZ GHG year]]-2021)/Table12[[#This Row],[Population]])),"") -> -2376.012 | AK29: =IF(Table12[[#This Row],[Formule no Peak (2)]]="","",Table12[[#This Row],[Penalty (1)]]+Table12[[#This Row],[Formule no Peak (2)]]) -> -3638.1079 | AL29: =(Table12[[#This Row],[Current Policies 2030 excl LULUCF]]-Table12[[#This Row],[GHG emissions excl LULUCF]])/(2030-2021)/Table12[[#This Row],[GHG emissions excl LULUCF]] -> 0.026152415 | AM29: =IF(Table12[[#This Row],[Net-zero target status]]<=1,"",IF(Table12[[#This Row],[NZ GHG year]]="","",(Table12[[#This Row],[residual LULUCF emissions in 2050]]-Table12[[#This Row],[Current Policies 2030 excl LULUCF]])/(Table12[[#This Row],[NZ GHG year]]-2030)/Table12[[#This Row],[Current Policies 2030 excl LULUCF]])) -> #DIV/0! | AN29: =IF(Table12[[#This Row],[Net-zero target status]]<=1,"",IF(Table12[[#This Row],[NZ GHG year]]="","",(Table12[[#This Row],[residual LULUCF emissions in 2050]]-Table12[[#This Row],[GHG emissions excl LULUCF]])/(Table12[[#This Row],[NZ GHG year]]-2021)/Table12[[#This Row],[GHG emissions excl LULUCF]])) -> -0.10919443 | AO29: =IF(Table12[[#This Row],[Net-zero target status]]<=1,"",IF(Table12[[#This Row],[NZ GHG year]]="","",(Table12[[#This Row],[residual LULUCF emissions in 2050]]-Table12[[#This Row],[2030 conditional NDCs]])/(Table12[[#This Row],[NZ GHG year]]-2030)/Table12[[#This Row],[2030 conditional NDCs]])) -> #DIV/0! | AP29: =MAX('input site'!AH29:AS29) -> 5.950326 | AQ29: =IF(Table12[[#This Row],[Current Policies 2030 incl LULUCF]]>Table12[[#This Row],[Maximum inventory data]],"No","Yes") -> No | AR29: =IF(Table12[[#This Row],[Net-zero target status]]>=1.5,Table12[[#This Row],[residual LULUCF emissions in 2050]]/Table12[[#This Row],[GHG emissions excl LULUCF]],"") -> 0.017250127 | AS29: ='input site'!BE29 | AU29: ='input site'!BG29 -> 1.4014 | AV29: ='input site'!BH29 -> 1.4014 | AW29: =IF(Table12[[#This Row],[2030 unconditional NDCs]]="","",IF(F29="incl",Table12[[#This Row],[2030 unconditional NDCs]]-Table12[[#This Row],[LULUCF NDC uncond]],Table12[[#This Row],[2030 unconditional NDCs]])) | AX29: =IF(Table12[[#This Row],[2030 unconditional NDCs2]]="","",IF(F29="incl",Table12[[#This Row],[2030 unconditional NDCs2]]-Table12[[#This Row],[LULUCF NDC uncond]],Table12[[#This Row],[2030 unconditional NDCs2]])) | AY29: =IF(Table12[[#This Row],[2030 conditional NDCs]]="","",IF(F29="incl",Table12[[#This Row],[2030 conditional NDCs]]-Table12[[#This Row],[LULUCF NDC cond]],Table12[[#This Row],[2030 conditional NDCs]])) -> 1.4886208 | AZ29: =IF(Table12[[#This Row],[2030 conditional NDCs2]]="","",IF(F29="incl",Table12[[#This Row],[2030 conditional NDCs2]]-Table12[[#This Row],[LULUCF NDC cond]],Table12[[#This Row],[2030 conditional NDCs2]])) -> 1.4886208 | BA29: =VLOOKUP($G29,'Population90 20'!$C$6:$AU$231,37,FALSE) -> 288023 | BB29: =VLOOKUP($G29,'Overview GDP (PPP)'!$C$6:$AI$231,33,FALSE) -> 4795778.3 | BC29: =Table12[[#This Row],[Income]]/Table12[[#This Row],[Population]] -> 16.650678 | BD29: =Table12[[#This Row],[GHG emissions excl LULUCF]]*1000000/Table12[[#This Row],[Population]] -> 17.554986 | BE29: =VLOOKUP($G29,EGR2023_MASTER!$B$4:$S$38,14,FALSE) -> #N/A | BF29: =VLOOKUP($G29,EGR2023_MASTER!$B$4:$S$38,15,FALSE) -> #N/A | BG29: =VLOOKUP($G29,EGR2023_MASTER!$B$4:$S$38,16,FALSE) -> #N/A | BH29: =IF(AND(BE29="Y",AND(BF29="credible",BG29="Y")),"higher",IF(BG29="Y","lower",IF(AND(BG29="N",OR(BE29="Y",BF29="credible")),"lower","much lower"))) -> #N/A | BI29: =IF(AND($BF29="credible",BG29="Y"),"stronger","weak") -> #N/A | BJ29: =(Table12[[#This Row],[Current Policies 2030 excl LULUCF]]/Table12[[#This Row],[GHG emissions excl LULUCF]])^(1/(2030-2021))-1 -> 0.023763732 | BK29: =IF(Table12[[#This Row],[Net-zero target status]]<=1,"",IF(Table12[[#This Row],[NZ GHG year]]="","",((MAX(Table12[[#This Row],[residual LULUCF emissions in 2050]],0.1)/Table12[[#This Row],[Current Policies 2030 excl LULUCF]])^(1/(Table12[[#This Row],[NZ GHG year]]-2021))-1))) -> -0.36833607 | BL29: =IF(Table12[[#This Row],[Net-zero target status]]<=1,"",IF(Table12[[#This Row],[NZ GHG year]]="","",((MAX(Table12[[#This Row],[residual LULUCF emissions in 2050]],0.1)/Table12[[#This Row],[GHG emissions excl LULUCF]])^(1/(Table12[[#This Row],[NZ GHG year]]-2021))-1))) -> -0.35332538 | BM29: =IF(Table12[[#This Row],[Net-zero target status]]<=1,"",IF(Table12[[#This Row],[NZ GHG year]]="","",((MAX(Table12[[#This Row],[residual LULUCF emissions in 2050]],0.1)/AVERAGE(Table12[[#This Row],[2030 conditional NDCs]:[2030 conditional NDCs2]]))^(1/(Table12[[#This Row],[NZ GHG year]]-2021))-1))) -> -0.2542312 | BR29: Barbados | BT29: =IF(Table12[[#This Row],[Reduction rate 2021 to NZ target2]]="","",J29*(1+AN29)^(Table12[[#This Row],[NZ GHG year]]-2021)) -> 1.7541891
A30: 0 | B30: 0 | C30: 112 | D30: 30 | E30: 14 | F30: ='input site'!M30 -> incl | G30: BLR | H30: Belarus | I30: =VLOOKUP($G30,'NZT data'!$B$3:$C$200,2,FALSE) -> 0 | J30: ='input site'!AS30 -> 48.914918 | K30: ='input site'!BS30 -> 56.397629 | L30: =IF(I30>=1,O30,K30) -> 56.397629 | M30: =IF(I30>=1,O30,N30) -> 7.6933524 | N30: ='input site'!EV30 -> 7.6933524 | Q30: =IF(I30>=1,O30,R30) -> -9.2227666 | R30: ='input site'!EZ30 -> -9.2227666 | S30: ='input site'!FA30 -> 0 | T30: =Table12[[#This Row],[(Mt CO2 equivalent)]] -> Belarus | U30: =VLOOKUP($G30,'NZT data'!$B$3:$F$200,4,FALSE) -> 2110 | V30: =VLOOKUP($G30,'NZT data'!$B$3:$F$200,5,FALSE) | W30: =-IF('LUC NGHGI'!EC20="",MIN('LUC NGHGI'!DW20,0.1),MIN('LUC NGHGI'!EC20,0.1)) -> 37.448418 | X30: ='LUC NGHGI'!EC20 -> -37.448418 | Y30: ='LUC NGHGI'!DY20 -> -29.22 | Z30: ='LUC NGHGI'!DZ20 -> -29.22 | AA30: =Table12[[#This Row],[2021 emissions]] -> 48.914918 | AB30: ='LUC NGHGI'!DW20 -> -43.073284 | AC30: =IF(F30="incl",Table12[[#This Row],[GHG emissions incl LULUCF]]-Table12[[#This Row],[LULUCF emis-sions in 20213]],Table12[[#This Row],[GHG emissions incl LULUCF]]) -> 91.988202 | AD30: ='input site'!BS30 -> 56.397629 | AE30: ='LUC NGHGI'!EH20 -> -49.885381 | AF30: =IF(F30="incl",Table12[[#This Row],[Current Policies 2030 incl LULUCF]]-Table12[[#This Row],[LULUCF CurPol 2030]],Table12[[#This Row],[Current Policies 2030 incl LULUCF]]) -> 106.28301 | AG30: =IF(Table12[[#This Row],[Net-zero target status]]<=1,"",IF(Table12[[#This Row],[NZ GHG year]]="","",1000000000*(Table12[[#This Row],[residual LULUCF emissions in 2050]]-Table12[[#This Row],[GHG emissions excl LULUCF]])/(Table12[[#This Row],[NZ GHG year]]-2021)/Table12[[#This Row],[Population]])) | AH30: =IF(Table12[[#This Row],[Peak revised]]="Yes",IF(Table12[[#This Row],[Net-zero target status]]<=1,"",IF(Table12[[#This Row],[NZ GHG year]]="","",1000000000*(Table12[[#This Row],[residual LULUCF emissions in 2050]]-Table12[[#This Row],[GHG emissions excl LULUCF]])/(Table12[[#This Row],[NZ GHG year]]-2021)/Table12[[#This Row],[Population]])),"") | AI30: =MAX(0,(1000000*(Table12[[#This Row],[Current Policies 2030 excl LULUCF]]/2+Table12[[#This Row],[GHG emissions excl LULUCF]]/2)/Table12[[#This Row],[Population]]-$AI$8)*10)*$AI$10 -> -350.9669 | AJ30: =IF(Table12[[#This Row],[Peak revised]]="No",IF(Table12[[#This Row],[Net-zero target status]]<=1,"",IF(Table12[[#This Row],[NZ GHG year]]="","",1000000000*(Table12[[#This Row],[residual LULUCF emissions in 2050]]-Table12[[#This Row],[Current Policies 2030 excl LULUCF]])/(Table12[[#This Row],[NZ GHG year]]-2021)/Table12[[#This Row],[Population]])),"") | AK30: =IF(Table12[[#This Row],[Formule no Peak (2)]]="","",Table12[[#This Row],[Penalty (1)]]+Table12[[#This Row],[Formule no Peak (2)]]) | AL30: =(Table12[[#This Row],[Current Policies 2030 excl LULUCF]]-Table12[[#This Row],[GHG emissions excl LULUCF]])/(2030-2021)/Table12[[#This Row],[GHG emissions excl LULUCF]] -> 0.017266475 | AM30: =IF(Table12[[#This Row],[Net-zero target status]]<=1,"",IF(Table12[[#This Row],[NZ GHG year]]="","",(Table12[[#This Row],[residual LULUCF emissions in 2050]]-Table12[[#This Row],[Current Policies 2030 excl LULUCF]])/(Table12[[#This Row],[NZ GHG year]]-2030)/Table12[[#This Row],[Current Policies 2030 excl LULUCF]])) | AN30: =IF(Table12[[#This Row],[Net-zero target status]]<=1,"",IF(Table12[[#This Row],[NZ GHG year]]="","",(Table12[[#This Row],[residual LULUCF emissions in 2050]]-Table12[[#This Row],[GHG emissions excl LULUCF]])/(Table12[[#This Row],[NZ GHG year]]-2021)/Table12[[#This Row],[GHG emissions excl LULUCF]])) | AO30: =IF(Table12[[#This Row],[Net-zero target status]]<=1,"",IF(Table12[[#This Row],[NZ GHG year]]="","",(Table12[[#This Row],[residual LULUCF emissions in 2050]]-Table12[[#This Row],[2030 conditional NDCs]])/(Table12[[#This Row],[NZ GHG year]]-2030)/Table12[[#This Row],[2030 conditional NDCs]])) | AP30: =MAX('input site'!AH30:AS30) -> 56.661426 | AQ30: =IF(Table12[[#This Row],[Current Policies 2030 incl LULUCF]]>Table12[[#This Row],[Maximum inventory data]],"No","Yes") -> Yes | AR30: =IF(Table12[[#This Row],[Net-zero target status]]>=1.5,Table12[[#This Row],[residual LULUCF emissions in 2050]]/Table12[[#This Row],[GHG emissions excl LULUCF]],"") | AS30: ='input site'!BE30 -> 76.18 | AT30: ='input site'!BF30 -> 76.18 | AU30: ='input site'!BG30 -> 70.32 | AV30: ='input site'!BH30 -> 70.32 | AW30: =IF(Table12[[#This Row],[2030 unconditional NDCs]]="","",IF(F30="incl",Table12[[#This Row],[2030 unconditional NDCs]]-Table12[[#This Row],[LULUCF NDC uncond]],Table12[[#This Row],[2030 unconditional NDCs]])) -> 105.4 | AX30: =IF(Table12[[#This Row],[2030 unconditional NDCs2]]="","",IF(F30="incl",Table12[[#This Row],[2030 unconditional NDCs2]]-Table12[[#This Row],[LULUCF NDC uncond]],Table12[[#This Row],[2030 unconditional NDCs2]])) -> 105.4 | AY30: =IF(Table12[[#This Row],[2030 conditional NDCs]]="","",IF(F30="incl",Table12[[#This Row],[2030 conditional NDCs]]-Table12[[#This Row],[LULUCF NDC cond]],Table12[[#This Row],[2030 conditional NDCs]])) -> 99.54 | AZ30: =IF(Table12[[#This Row],[2030 conditional NDCs2]]="","",IF(F30="incl",Table12[[#This Row],[2030 conditional NDCs2]]-Table12[[#This Row],[LULUCF NDC cond]],Table12[[#This Row],[2030 conditional NDCs2]])) -> 99.54 | BA30: =VLOOKUP($G30,'Population90 20'!$C$6:$AU$231,37,FALSE) -> 9432800 | BB30: =VLOOKUP($G30,'Overview GDP (PPP)'!$C$6:$AI$231,33,FALSE) -> 1.6828841e+08 | BC30: =Table12[[#This Row],[Income]]/Table12[[#This Row],[Population]] -> 17.84077 | BD30: =Table12[[#This Row],[GHG emissions excl LULUCF]]*1000000/Table12[[#This Row],[Population]] -> 9.7519509 | BE30: =VLOOKUP($G30,EGR2023_MASTER!$B$4:$S$38,14,FALSE) -> #N/A | BF30: =VLOOKUP($G30,EGR2023_MASTER!$B$4:$S$38,15,FALSE) -> #N/A | BG30: =VLOOKUP($G30,EGR2023_MASTER!$B$4:$S$38,16,FALSE) -> #N/A | BH30: =IF(AND(BE30="Y",AND(BF30="credible",BG30="Y")),"higher",IF(BG30="Y","lower",IF(AND(BG30="N",OR(BE30="Y",BF30="credible")),"lower","much lower"))) -> #N/A | BI30: =IF(AND($BF30="credible",BG30="Y"),"stronger","weak") -> #N/A | BJ30: =(Table12[[#This Row],[Current Policies 2030 excl LULUCF]]/Table12[[#This Row],[GHG emissions excl LULUCF]])^(1/(2030-2021))-1 -> 0.016178942 | BK30: =IF(Table12[[#This Row],[Net-zero target status]]<=1,"",IF(Table12[[#This Row],[NZ GHG year]]="","",((MAX(Table12[[#This Row],[residual LULUCF emissions in 2050]],0.1)/Table12[[#This Row],[Current Policies 2030 excl LULUCF]])^(1/(Table12[[#This Row],[NZ GHG year]]-2021))-1))) | BL30: =IF(Table12[[#This Row],[Net-zero target status]]<=1,"",IF(Table12[[#This Row],[NZ GHG year]]="","",((MAX(Table12[[#This Row],[residual LULUCF emissions in 2050]],0.1)/Table12[[#This Row],[GHG emissions excl LULUCF]])^(1/(Table12[[#This Row],[NZ GHG year]]-2021))-1))) | BM30: =IF(Table12[[#This Row],[Net-zero target status]]<=1,"",IF(Table12[[#This Row],[NZ GHG year]]="","",((MAX(Table12[[#This Row],[residual LULUCF emissions in 2050]],0.1)/AVERAGE(Table12[[#This Row],[2030 conditional NDCs]:[2030 conditional NDCs2]]))^(1/(Table12[[#This Row],[NZ GHG year]]-2021))-1))) | BR30: Belarus | BT30: =IF(Table12[[#This Row],[Reduction rate 2021 to NZ target2]]="","",J30*(1+AN30)^(Table12[[#This Row],[NZ GHG year]]-2021))
A31: 0 | B31: 0 | C31: 56 | D31: 16 | E31: 11 | F31: ='input site'!M31 -> incl | G31: BEL | H31: Belgium | I31: =VLOOKUP($G31,'NZT data'!$B$3:$C$200,2,FALSE) -> 3 | J31: ='input site'!AS31 -> 110.50611 | K31: ='input site'!BS31 -> 61.656827 | L31: =IF(I31>=1,O31,K31) -> 0 | M31: =IF(I31>=1,O31,N31) -> 0 | N31: ='input site'!EV31 -> 23.906789 | Q31: =IF(I31>=1,O31,R31) -> 0 | R31: ='input site'!EZ31 -> 13.223417 | S31: ='input site'!FA31 -> 2050 (part of the EU) | T31: =Table12[[#This Row],[(Mt CO2 equivalent)]] -> Belgium | U31: =VLOOKUP($G31,'NZT data'!$B$3:$F$200,4,FALSE) -> 2050 | V31: =VLOOKUP($G31,'NZT data'!$B$3:$F$200,5,FALSE) -> 2050 | W31: =-IF('LUC NGHGI'!EC21="",MIN('LUC NGHGI'!DW21,0.1),MIN('LUC NGHGI'!EC21,0.1)) -> 0.35387688 | X31: ='LUC NGHGI'!EC21 -> -0.35387688 | Y31: ='LUC NGHGI'!DY21 -> -0.35387688 | Z31: ='LUC NGHGI'!DZ21 -> -0.35387688 | AA31: =Table12[[#This Row],[2021 emissions]] -> 110.50611 | AB31: ='LUC NGHGI'!DW21 -> -0.34309454 | AC31: =IF(F31="incl",Table12[[#This Row],[GHG emissions incl LULUCF]]-Table12[[#This Row],[LULUCF emis-sions in 20213]],Table12[[#This Row],[GHG emissions incl LULUCF]]) -> 110.8492 | AD31: ='input site'!BS31 -> 61.656827 | AE31: ='LUC NGHGI'!EH21 -> -0.61246357 | AF31: =IF(F31="incl",Table12[[#This Row],[Current Policies 2030 incl LULUCF]]-Table12[[#This Row],[LULUCF CurPol 2030]],Table12[[#This Row],[Current Policies 2030 incl LULUCF]]) -> 62.269291 | AG31: =IF(Table12[[#This Row],[Net-zero target status]]<=1,"",IF(Table12[[#This Row],[NZ GHG year]]="","",1000000000*(Table12[[#This Row],[residual LULUCF emissions in 2050]]-Table12[[#This Row],[GHG emissions excl LULUCF]])/(Table12[[#This Row],[NZ GHG year]]-2021)/Table12[[#This Row],[Population]])) -> -326.54206 | AH31: =IF(Table12[[#This Row],[Peak revised]]="Yes",IF(Table12[[#This Row],[Net-zero target status]]<=1,"",IF(Table12[[#This Row],[NZ GHG year]]="","",1000000000*(Table12[[#This Row],[residual LULUCF emissions in 2050]]-Table12[[#This Row],[GHG emissions excl LULUCF]])/(Table12[[#This Row],[NZ GHG year]]-2021)/Table12[[#This Row],[Population]])),"") -> -326.54206 | AI31: =MAX(0,(1000000*(Table12[[#This Row],[Current Policies 2030 excl LULUCF]]/2+Table12[[#This Row],[GHG emissions excl LULUCF]]/2)/Table12[[#This Row],[Population]]-$AI$8)*10)*$AI$10 -> -41.833931 | AJ31: =IF(Table12[[#This Row],[Peak revised]]="No",IF(Table12[[#This Row],[Net-zero target status]]<=1,"",IF(Table12[[#This Row],[NZ GHG year]]="","",1000000000*(Table12[[#This Row],[residual LULUCF emissions in 2050]]-Table12[[#This Row],[Current Policies 2030 excl LULUCF]])/(Table12[[#This Row],[NZ GHG year]]-2021)/Table12[[#This Row],[Population]])),"") | AK31: =IF(Table12[[#This Row],[Formule no Peak (2)]]="","",Table12[[#This Row],[Penalty (1)]]+Table12[[#This Row],[Formule no Peak (2)]]) | AL31: =(Table12[[#This Row],[Current Policies 2030 excl LULUCF]]-Table12[[#This Row],[GHG emissions excl LULUCF]])/(2030-2021)/Table12[[#This Row],[GHG emissions excl LULUCF]] -> -0.048694692 | AM31: =IF(Table12[[#This Row],[Net-zero target status]]<=1,"",IF(Table12[[#This Row],[NZ GHG year]]="","",(Table12[[#This Row],[residual LULUCF emissions in 2050]]-Table12[[#This Row],[Current Policies 2030 excl LULUCF]])/(Table12[[#This Row],[NZ GHG year]]-2030)/Table12[[#This Row],[Current Policies 2030 excl LULUCF]])) -> -0.04971585 | AN31: =IF(Table12[[#This Row],[Net-zero target status]]<=1,"",IF(Table12[[#This Row],[NZ GHG year]]="","",(Table12[[#This Row],[residual LULUCF emissions in 2050]]-Table12[[#This Row],[GHG emissions excl LULUCF]])/(Table12[[#This Row],[NZ GHG year]]-2021)/Table12[[#This Row],[GHG emissions excl LULUCF]])) -> -0.034372675 | AO31: =IF(Table12[[#This Row],[Net-zero target status]]<=1,"",IF(Table12[[#This Row],[NZ GHG year]]="","",(Table12[[#This Row],[residual LULUCF emissions in 2050]]-Table12[[#This Row],[2030 conditional NDCs]])/(Table12[[#This Row],[NZ GHG year]]-2030)/Table12[[#This Row],[2030 conditional NDCs]])) -> #DIV/0! | AP31: =MAX('input site'!AH31:AS31) -> 133.31339 | AQ31: =IF(Table12[[#This Row],[Current Policies 2030 incl LULUCF]]>Table12[[#This Row],[Maximum inventory data]],"No","Yes") -> Yes | AR31: =IF(Table12[[#This Row],[Net-zero target status]]>=1.5,Table12[[#This Row],[residual LULUCF emissions in 2050]]/Table12[[#This Row],[GHG emissions excl LULUCF]],"") -> 0.0031924171 | AS31: ='input site'!BE31 | AW31: =IF(Table12[[#This Row],[2030 unconditional NDCs]]="","",IF(F31="incl",Table12[[#This Row],[2030 unconditional NDCs]]-Table12[[#This Row],[LULUCF NDC uncond]],Table12[[#This Row],[2030 unconditional NDCs]])) | AX31: =IF(Table12[[#This Row],[2030 unconditional NDCs2]]="","",IF(F31="incl",Table12[[#This Row],[2030 unconditional NDCs2]]-Table12[[#This Row],[LULUCF NDC uncond]],Table12[[#This Row],[2030 unconditional NDCs2]])) | AY31: =IF(Table12[[#This Row],[2030 conditional NDCs]]="","",IF(F31="incl",Table12[[#This Row],[2030 conditional NDCs]]-Table12[[#This Row],[LULUCF NDC cond]],Table12[[#This Row],[2030 conditional NDCs]])) | AZ31: =IF(Table12[[#This Row],[2030 conditional NDCs2]]="","",IF(F31="incl",Table12[[#This Row],[2030 conditional NDCs2]]-Table12[[#This Row],[LULUCF NDC cond]],Table12[[#This Row],[2030 conditional NDCs2]])) | BA31: =VLOOKUP($G31,'Population90 20'!$C$6:$AU$231,37,FALSE) -> 11668278 | BB31: =VLOOKUP($G31,'Overview GDP (PPP)'!$C$6:$AI$231,33,FALSE) -> 4.9363839e+08 | BC31: =Table12[[#This Row],[Income]]/Table12[[#This Row],[Population]] -> 42.306019 | BD31: =Table12[[#This Row],[GHG emissions excl LULUCF]]*1000000/Table12[[#This Row],[Population]] -> 9.5000479 | BE31: =VLOOKUP($G31,EGR2023_MASTER!$B$4:$S$38,14,FALSE) -> #N/A | BF31: =VLOOKUP($G31,EGR2023_MASTER!$B$4:$S$38,15,FALSE) -> #N/A | BG31: =VLOOKUP($G31,EGR2023_MASTER!$B$4:$S$38,16,FALSE) -> #N/A | BH31: =IF(AND(BE31="Y",AND(BF31="credible",BG31="Y")),"higher",IF(BG31="Y","lower",IF(AND(BG31="N",OR(BE31="Y",BF31="credible")),"lower","much lower"))) -> #N/A | BI31: =IF(AND($BF31="credible",BG31="Y"),"stronger","weak") -> #N/A | BJ31: =(Table12[[#This Row],[Current Policies 2030 excl LULUCF]]/Table12[[#This Row],[GHG emissions excl LULUCF]])^(1/(2030-2021))-1 -> -0.062068197 | BK31: =IF(Table12[[#This Row],[Net-zero target status]]<=1,"",IF(Table12[[#This Row],[NZ GHG year]]="","",((MAX(Table12[[#This Row],[residual LULUCF emissions in 2050]],0.1)/Table12[[#This Row],[Current Policies 2030 excl LULUCF]])^(1/(Table12[[#This Row],[NZ GHG year]]-2021))-1))) -> -0.16329635 | BL31: =IF(Table12[[#This Row],[Net-zero target status]]<=1,"",IF(Table12[[#This Row],[NZ GHG year]]="","",((MAX(Table12[[#This Row],[residual LULUCF emissions in 2050]],0.1)/Table12[[#This Row],[GHG emissions excl LULUCF]])^(1/(Table12[[#This Row],[NZ GHG year]]-2021))-1))) -> -0.17977093 | BM31: =IF(Table12[[#This Row],[Net-zero target status]]<=1,"",IF(Table12[[#This Row],[NZ GHG year]]="","",((MAX(Table12[[#This Row],[residual LULUCF emissions in 2050]],0.1)/AVERAGE(Table12[[#This Row],[2030 conditional NDCs]:[2030 conditional NDCs2]]))^(1/(Table12[[#This Row],[NZ GHG year]]-2021))-1))) -> #DIV/0! | BR31: Belgium | BT31: =IF(Table12[[#This Row],[Reduction rate 2021 to NZ target2]]="","",J31*(1+AN31)^(Table12[[#This Row],[NZ GHG year]]-2021)) -> 40.07404
A32: 0 | B32: 0 | C32: 84 | D32: 23 | E32: 4 | F32: ='input site'!M32 -> excl | G32: BLZ | H32: Belize | I32: =VLOOKUP($G32,'NZT data'!$B$3:$C$200,2,FALSE) -> 3 | J32: ='input site'!AS32 -> 1.8645148 | K32: ='input site'!BS32 -> 2.2990758 | L32: =IF(I32>=1,O32,K32) -> 0 | M32: =IF(I32>=1,O32,N32) -> 0 | N32: ='input site'!EV32 -> 0.88293438 | O32: 0 | P32: =O32-N32 -> -0.88293438 | Q32: =IF(I32>=1,O32,R32) -> 0 | R32: ='input site'!EZ32 -> 0.17957155 | S32: ='input site'!FA32 -> 2050 | T32: =Table12[[#This Row],[(Mt CO2 equivalent)]] -> Belize | U32: =VLOOKUP($G32,'NZT data'!$B$3:$F$200,4,FALSE) -> 2050 | V32: =VLOOKUP($G32,'NZT data'!$B$3:$F$200,5,FALSE) -> 2050 | W32: =-IF('LUC NGHGI'!EC22="",MIN('LUC NGHGI'!DW22,0.1),MIN('LUC NGHGI'!EC22,0.1)) -> 9.6 | X32: ='LUC NGHGI'!EC22 -> -9.6 | Y32: ='LUC NGHGI'!DY22 -> -6.7078298 | Z32: ='LUC NGHGI'!DZ22 -> -6.7078298 | AA32: =Table12[[#This Row],[2021 emissions]] -> 1.8645148 | AB32: ='LUC NGHGI'!DW22 -> -6.4080854 | AC32: =IF(F32="incl",Table12[[#This Row],[GHG emissions incl LULUCF]]-Table12[[#This Row],[LULUCF emis-sions in 20213]],Table12[[#This Row],[GHG emissions incl LULUCF]]) -> 1.8645148 | AD32: ='input site'!BS32 -> 2.2990758 | AE32: ='LUC NGHGI'!EH22 -> -9.4275087 | AF32: =IF(F32="incl",Table12[[#This Row],[Current Policies 2030 incl LULUCF]]-Table12[[#This Row],[LULUCF CurPol 2030]],Table12[[#This Row],[Current Policies 2030 incl LULUCF]]) -> 2.2990758 | AG32: =IF(Table12[[#This Row],[Net-zero target status]]<=1,"",IF(Table12[[#This Row],[NZ GHG year]]="","",1000000000*(Table12[[#This Row],[residual LULUCF emissions in 2050]]-Table12[[#This Row],[GHG emissions excl LULUCF]])/(Table12[[#This Row],[NZ GHG year]]-2021)/Table12[[#This Row],[Population]])) -> 647.13086 | AH32: =IF(Table12[[#This Row],[Peak revised]]="Yes",IF(Table12[[#This Row],[Net-zero target status]]<=1,"",IF(Table12[[#This Row],[NZ GHG year]]="","",1000000000*(Table12[[#This Row],[residual LULUCF emissions in 2050]]-Table12[[#This Row],[GHG emissions excl LULUCF]])/(Table12[[#This Row],[NZ GHG year]]-2021)/Table12[[#This Row],[Population]])),"") | AI32: =MAX(0,(1000000*(Table12[[#This Row],[Current Policies 2030 excl LULUCF]]/2+Table12[[#This Row],[GHG emissions excl LULUCF]]/2)/Table12[[#This Row],[Population]]-$AI$8)*10)*$AI$10 -> 0 | AJ32: =IF(Table12[[#This Row],[Peak revised]]="No",IF(Table12[[#This Row],[Net-zero target status]]<=1,"",IF(Table12[[#This Row],[NZ GHG year]]="","",1000000000*(Table12[[#This Row],[residual LULUCF emissions in 2050]]-Table12[[#This Row],[Current Policies 2030 excl LULUCF]])/(Table12[[#This Row],[NZ GHG year]]-2021)/Table12[[#This Row],[Population]])),"") -> 610.7766 | AK32: =IF(Table12[[#This Row],[Formule no Peak (2)]]="","",Table12[[#This Row],[Penalty (1)]]+Table12[[#This Row],[Formule no Peak (2)]]) -> 610.7766 | AL32: =(Table12[[#This Row],[Current Policies 2030 excl LULUCF]]-Table12[[#This Row],[GHG emissions excl LULUCF]])/(2030-2021)/Table12[[#This Row],[GHG emissions excl LULUCF]] -> 0.025896577 | AM32: =IF(Table12[[#This Row],[Net-zero target status]]<=1,"",IF(Table12[[#This Row],[NZ GHG year]]="","",(Table12[[#This Row],[residual LULUCF emissions in 2050]]-Table12[[#This Row],[Current Policies 2030 excl LULUCF]])/(Table12[[#This Row],[NZ GHG year]]-2030)/Table12[[#This Row],[Current Policies 2030 excl LULUCF]])) -> 0.15877955 | AN32: =IF(Table12[[#This Row],[Net-zero target status]]<=1,"",IF(Table12[[#This Row],[NZ GHG year]]="","",(Table12[[#This Row],[residual LULUCF emissions in 2050]]-Table12[[#This Row],[GHG emissions excl LULUCF]])/(Table12[[#This Row],[NZ GHG year]]-2021)/Table12[[#This Row],[GHG emissions excl LULUCF]])) -> 0.14306181 | AO32: =IF(Table12[[#This Row],[Net-zero target status]]<=1,"",IF(Table12[[#This Row],[NZ GHG year]]="","",(Table12[[#This Row],[residual LULUCF emissions in 2050]]-Table12[[#This Row],[2030 conditional NDCs]])/(Table12[[#This Row],[NZ GHG year]]-2030)/Table12[[#This Row],[2030 conditional NDCs]])) -> #DIV/0! | AP32: =MAX('input site'!AH32:AS32) -> 1.8645148 | AQ32: =IF(Table12[[#This Row],[Current Policies 2030 incl LULUCF]]>Table12[[#This Row],[Maximum inventory data]],"No","Yes") -> No | AR32: =IF(Table12[[#This Row],[Net-zero target status]]>=1.5,Table12[[#This Row],[residual LULUCF emissions in 2050]]/Table12[[#This Row],[GHG emissions excl LULUCF]],"") -> 5.1487926 | AS32: ='input site'!BE32 | AW32: =IF(Table12[[#This Row],[2030 unconditional NDCs]]="","",IF(F32="incl",Table12[[#This Row],[2030 unconditional NDCs]]-Table12[[#This Row],[LULUCF NDC uncond]],Table12[[#This Row],[2030 unconditional NDCs]])) | AX32: =IF(Table12[[#This Row],[2030 unconditional NDCs2]]="","",IF(F32="incl",Table12[[#This Row],[2030 unconditional NDCs2]]-Table12[[#This Row],[LULUCF NDC uncond]],Table12[[#This Row],[2030 unconditional NDCs2]])) | AY32: =IF(Table12[[#This Row],[2030 conditional NDCs]]="","",IF(F32="incl",Table12[[#This Row],[2030 conditional NDCs]]-Table12[[#This Row],[LULUCF NDC cond]],Table12[[#This Row],[2030 conditional NDCs]])) | AZ32: =IF(Table12[[#This Row],[2030 conditional NDCs2]]="","",IF(F32="incl",Table12[[#This Row],[2030 conditional NDCs2]]-Table12[[#This Row],[LULUCF NDC cond]],Table12[[#This Row],[2030 conditional NDCs2]])) | BA32: =VLOOKUP($G32,'Population90 20'!$C$6:$AU$231,37,FALSE) -> 412190 | BB32: =VLOOKUP($G32,'Overview GDP (PPP)'!$C$6:$AI$231,33,FALSE) -> 2991875.7 | BC32: =Table12[[#This Row],[Income]]/Table12[[#This Row],[Population]] -> 7.2584869 | BD32: =Table12[[#This Row],[GHG emissions excl LULUCF]]*1000000/Table12[[#This Row],[Population]] -> 4.5234353 | BE32: =VLOOKUP($G32,EGR2023_MASTER!$B$4:$S$38,14,FALSE) -> #N/A | BF32: =VLOOKUP($G32,EGR2023_MASTER!$B$4:$S$38,15,FALSE) -> #N/A | BG32: =VLOOKUP($G32,EGR2023_MASTER!$B$4:$S$38,16,FALSE) -> #N/A | BH32: =IF(AND(BE32="Y",AND(BF32="credible",BG32="Y")),"higher",IF(BG32="Y","lower",IF(AND(BG32="N",OR(BE32="Y",BF32="credible")),"lower","much lower"))) -> #N/A | BI32: =IF(AND($BF32="credible",BG32="Y"),"stronger","weak") -> #N/A | BJ32: =(Table12[[#This Row],[Current Policies 2030 excl LULUCF]]/Table12[[#This Row],[GHG emissions excl LULUCF]])^(1/(2030-2021))-1 -> 0.02355154 | BK32: =IF(Table12[[#This Row],[Net-zero target status]]<=1,"",IF(Table12[[#This Row],[NZ GHG year]]="","",((MAX(Table12[[#This Row],[residual LULUCF emissions in 2050]],0.1)/Table12[[#This Row],[Current Policies 2030 excl LULUCF]])^(1/(Table12[[#This Row],[NZ GHG year]]-2021))-1))) -> 0.050519377 | BL32: =IF(Table12[[#This Row],[Net-zero target status]]<=1,"",IF(Table12[[#This Row],[NZ GHG year]]="","",((MAX(Table12[[#This Row],[residual LULUCF emissions in 2050]],0.1)/Table12[[#This Row],[GHG emissions excl LULUCF]])^(1/(Table12[[#This Row],[NZ GHG year]]-2021))-1))) -> 0.058136183 | BM32: =IF(Table12[[#This Row],[Net-zero target status]]<=1,"",IF(Table12[[#This Row],[NZ GHG year]]="","",((MAX(Table12[[#This Row],[residual LULUCF emissions in 2050]],0.1)/AVERAGE(Table12[[#This Row],[2030 conditional NDCs]:[2030 conditional NDCs2]]))^(1/(Table12[[#This Row],[NZ GHG year]]-2021))-1))) -> #DIV/0! | BR32: Belize | BT32: =IF(Table12[[#This Row],[Reduction rate 2021 to NZ target2]]="","",J32*(1+AN32)^(Table12[[#This Row],[NZ GHG year]]-2021)) -> 90.071545
A33: 0 | B33: 0 | C33: 204 | D33: 52 | E33: 8 | F33: ='input site'!M33 -> excl | G33: BEN | H33: Benin | I33: =VLOOKUP($G33,'NZT data'!$B$3:$C$200,2,FALSE) -> 5 | J33: ='input site'!AS33 -> 19.31618 | K33: ='input site'!BS33 -> 23.005311 | L33: =IF(I33>=1,O33,K33) -> 0 | M33: =IF(I33>=1,O33,N33) -> 0 | N33: ='input site'!EV33 -> 16.752043 | O33: 0 | P33: =O33-N33 -> -16.752043 | Q33: =IF(I33>=1,O33,R33) -> 0 | R33: ='input site'!EZ33 -> 9.5419683 | S33: ='input site'!FA33 -> 2050 | T33: =Table12[[#This Row],[(Mt CO2 equivalent)]] -> Benin | U33: =VLOOKUP($G33,'NZT data'!$B$3:$F$200,4,FALSE) -> 2000 | V33: =VLOOKUP($G33,'NZT data'!$B$3:$F$200,5,FALSE) -> 2000 | W33: =-IF('LUC NGHGI'!EC23="",MIN('LUC NGHGI'!DW23,0.1),MIN('LUC NGHGI'!EC23,0.1)) -> 163 | X33: ='LUC NGHGI'!EC23 -> -163 | Y33: ='LUC NGHGI'!DY23 -> -10 | Z33: ='LUC NGHGI'!DZ23 -> -10 | AA33: =Table12[[#This Row],[2021 emissions]] -> 19.31618 | AB33: ='LUC NGHGI'!DW23 -> -3.734658 | AC33: =IF(F33="incl",Table12[[#This Row],[GHG emissions incl LULUCF]]-Table12[[#This Row],[LULUCF emis-sions in 20213]],Table12[[#This Row],[GHG emissions incl LULUCF]]) -> 19.31618 | AD33: ='input site'!BS33 -> 23.005311 | AE33: ='LUC NGHGI'!EH23 -> -4.8500275 | AF33: =IF(F33="incl",Table12[[#This Row],[Current Policies 2030 incl LULUCF]]-Table12[[#This Row],[LULUCF CurPol 2030]],Table12[[#This Row],[Current Policies 2030 incl LULUCF]]) -> 23.005311 | AG33: =IF(Table12[[#This Row],[Net-zero target status]]<=1,"",IF(Table12[[#This Row],[NZ GHG year]]="","",1000000000*(Table12[[#This Row],[residual LULUCF emissions in 2050]]-Table12[[#This Row],[GHG emissions excl LULUCF]])/(Table12[[#This Row],[NZ GHG year]]-2021)/Table12[[#This Row],[Population]])) -> -535.17664 | AH33: =IF(Table12[[#This Row],[Peak revised]]="Yes",IF(Table12[[#This Row],[Net-zero target status]]<=1,"",IF(Table12[[#This Row],[NZ GHG year]]="","",1000000000*(Table12[[#This Row],[residual LULUCF emissions in 2050]]-Table12[[#This Row],[GHG emissions excl LULUCF]])/(Table12[[#This Row],[NZ GHG year]]-2021)/Table12[[#This Row],[Population]])),"") | AI33: =MAX(0,(1000000*(Table12[[#This Row],[Current Policies 2030 excl LULUCF]]/2+Table12[[#This Row],[GHG emissions excl LULUCF]]/2)/Table12[[#This Row],[Population]]-$AI$8)*10)*$AI$10 -> 0 | AJ33: =IF(Table12[[#This Row],[Peak revised]]="No",IF(Table12[[#This Row],[Net-zero target status]]<=1,"",IF(Table12[[#This Row],[NZ GHG year]]="","",1000000000*(Table12[[#This Row],[residual LULUCF emissions in 2050]]-Table12[[#This Row],[Current Policies 2030 excl LULUCF]])/(Table12[[#This Row],[NZ GHG year]]-2021)/Table12[[#This Row],[Population]])),"") -> -521.4358 | AK33: =IF(Table12[[#This Row],[Formule no Peak (2)]]="","",Table12[[#This Row],[Penalty (1)]]+Table12[[#This Row],[Formule no Peak (2)]]) -> -521.4358 | AL33: =(Table12[[#This Row],[Current Policies 2030 excl LULUCF]]-Table12[[#This Row],[GHG emissions excl LULUCF]])/(2030-2021)/Table12[[#This Row],[GHG emissions excl LULUCF]] -> 0.021220729 | AM33: =IF(Table12[[#This Row],[Net-zero target status]]<=1,"",IF(Table12[[#This Row],[NZ GHG year]]="","",(Table12[[#This Row],[residual LULUCF emissions in 2050]]-Table12[[#This Row],[Current Policies 2030 excl LULUCF]])/(Table12[[#This Row],[NZ GHG year]]-2030)/Table12[[#This Row],[Current Policies 2030 excl LULUCF]])) -> -0.20284402 | AN33: =IF(Table12[[#This Row],[Net-zero target status]]<=1,"",IF(Table12[[#This Row],[NZ GHG year]]="","",(Table12[[#This Row],[residual LULUCF emissions in 2050]]-Table12[[#This Row],[GHG emissions excl LULUCF]])/(Table12[[#This Row],[NZ GHG year]]-2021)/Table12[[#This Row],[GHG emissions excl LULUCF]])) -> -0.35421531 | AO33: =IF(Table12[[#This Row],[Net-zero target status]]<=1,"",IF(Table12[[#This Row],[NZ GHG year]]="","",(Table12[[#This Row],[residual LULUCF emissions in 2050]]-Table12[[#This Row],[2030 conditional NDCs]])/(Table12[[#This Row],[NZ GHG year]]-2030)/Table12[[#This Row],[2030 conditional NDCs]])) -> -0.27389501 | AP33: =MAX('input site'!AH33:AS33) -> 19.31618 | AQ33: =IF(Table12[[#This Row],[Current Policies 2030 incl LULUCF]]>Table12[[#This Row],[Maximum inventory data]],"No","Yes") -> No | AR33: =IF(Table12[[#This Row],[Net-zero target status]]>=1.5,Table12[[#This Row],[residual LULUCF emissions in 2050]]/Table12[[#This Row],[GHG emissions excl LULUCF]],"") -> 8.4385215 | AS33: ='input site'!BE33 | AU33: ='input site'!BG33 -> 17.685 | AV33: ='input site'!BH33 -> 17.685 | AW33: =IF(Table12[[#This Row],[2030 unconditional NDCs]]="","",IF(F33="incl",Table12[[#This Row],[2030 unconditional NDCs]]-Table12[[#This Row],[LULUCF NDC uncond]],Table12[[#This Row],[2030 unconditional NDCs]])) | AX33: =IF(Table12[[#This Row],[2030 unconditional NDCs2]]="","",IF(F33="incl",Table12[[#This Row],[2030 unconditional NDCs2]]-Table12[[#This Row],[LULUCF NDC uncond]],Table12[[#This Row],[2030 unconditional NDCs2]])) | AY33: =IF(Table12[[#This Row],[2030 conditional NDCs]]="","",IF(F33="incl",Table12[[#This Row],[2030 conditional NDCs]]-Table12[[#This Row],[LULUCF NDC cond]],Table12[[#This Row],[2030 conditional NDCs]])) -> 17.685 | AZ33: =IF(Table12[[#This Row],[2030 conditional NDCs2]]="","",IF(F33="incl",Table12[[#This Row],[2030 conditional NDCs2]]-Table12[[#This Row],[LULUCF NDC cond]],Table12[[#This Row],[2030 conditional NDCs2]])) -> 17.685 | BA33: =VLOOKUP($G33,'Population90 20'!$C$6:$AU$231,37,FALSE) -> 12784726 | BB33: =VLOOKUP($G33,'Overview GDP (PPP)'!$C$6:$AI$231,33,FALSE) -> 24710577 | BC33: =Table12[[#This Row],[Income]]/Table12[[#This Row],[Population]] -> 1.9328202 | BD33: =Table12[[#This Row],[GHG emissions excl LULUCF]]*1000000/Table12[[#This Row],[Population]] -> 1.5108795 | BE33: =VLOOKUP($G33,EGR2023_MASTER!$B$4:$S$38,14,FALSE) -> #N/A | BF33: =VLOOKUP($G33,EGR2023_MASTER!$B$4:$S$38,15,FALSE) -> #N/A | BG33: =VLOOKUP($G33,EGR2023_MASTER!$B$4:$S$38,16,FALSE) -> #N/A | BH33: =IF(AND(BE33="Y",AND(BF33="credible",BG33="Y")),"higher",IF(BG33="Y","lower",IF(AND(BG33="N",OR(BE33="Y",BF33="credible")),"lower","much lower"))) -> #N/A | BI33: =IF(AND($BF33="credible",BG33="Y"),"stronger","weak") -> #N/A | BJ33: =(Table12[[#This Row],[Current Policies 2030 excl LULUCF]]/Table12[[#This Row],[GHG emissions excl LULUCF]])^(1/(2030-2021))-1 -> 0.019610022 | BK33: =IF(Table12[[#This Row],[Net-zero target status]]<=1,"",IF(Table12[[#This Row],[NZ GHG year]]="","",((MAX(Table12[[#This Row],[residual LULUCF emissions in 2050]],0.1)/Table12[[#This Row],[Current Policies 2030 excl LULUCF]])^(1/(Table12[[#This Row],[NZ GHG year]]-2021))-1))) -> -0.089024514 | BL33: =IF(Table12[[#This Row],[Net-zero target status]]<=1,"",IF(Table12[[#This Row],[NZ GHG year]]="","",((MAX(Table12[[#This Row],[residual LULUCF emissions in 2050]],0.1)/Table12[[#This Row],[GHG emissions excl LULUCF]])^(1/(Table12[[#This Row],[NZ GHG year]]-2021))-1))) -> -0.096575055 | BM33: =IF(Table12[[#This Row],[Net-zero target status]]<=1,"",IF(Table12[[#This Row],[NZ GHG year]]="","",((MAX(Table12[[#This Row],[residual LULUCF emissions in 2050]],0.1)/AVERAGE(Table12[[#This Row],[2030 conditional NDCs]:[2030 conditional NDCs2]]))^(1/(Table12[[#This Row],[NZ GHG year]]-2021))-1))) -> -0.10036261 | BR33: Benin | BT33: =IF(Table12[[#This Row],[Reduction rate 2021 to NZ target2]]="","",J33*(1+AN33)^(Table12[[#This Row],[NZ GHG year]]-2021)) -> 187965.69
A34: 0 | B34: 0 | C34: 60 | D34: 17 | E34: 4 | F34: ='input site'!M34 -> excl | G34: BMU | H34: Bermuda | I34: =VLOOKUP($G34,'NZT data'!$B$3:$C$200,2,FALSE) -> 0 | J34: ='input site'!AS34 -> 0 | K34: ='input site'!BS34 -> 0 | L34: =IF(I34>=1,O34,K34) -> 0 | M34: =IF(I34>=1,O34,N34) -> 0 | N34: ='input site'!EV34 -> 0 | Q34: =IF(I34>=1,O34,R34) -> 0 | R34: ='input site'!EZ34 -> 0 | S34: ='input site'!FA34 -> 0 | T34: =Table12[[#This Row],[(Mt CO2 equivalent)]] -> Bermuda | U34: =VLOOKUP($G34,'NZT data'!$B$3:$F$200,4,FALSE) -> 2110 | V34: =VLOOKUP($G34,'NZT data'!$B$3:$F$200,5,FALSE) | W34: =-IF('LUC NGHGI'!EC24="",MIN('LUC NGHGI'!DW24,0.1),MIN('LUC NGHGI'!EC24,0.1)) -> 0 | X34: ='LUC NGHGI'!EC24 | Y34: ='LUC NGHGI'!DY24 | Z34: ='LUC NGHGI'!DZ24 | AA34: =Table12[[#This Row],[2021 emissions]] -> 0 | AB34: ='LUC NGHGI'!DW24 -> 0 | AC34: =IF(F34="incl",Table12[[#This Row],[GHG emissions incl LULUCF]]-Table12[[#This Row],[LULUCF emis-sions in 20213]],Table12[[#This Row],[GHG emissions incl LULUCF]]) -> 0 | AD34: ='input site'!BS34 -> 0 | AE34: ='LUC NGHGI'!EH24 -> 0 | AF34: =IF(F34="incl",Table12[[#This Row],[Current Policies 2030 incl LULUCF]]-Table12[[#This Row],[LULUCF CurPol 2030]],Table12[[#This Row],[Current Policies 2030 incl LULUCF]]) -> 0 | AG34: =IF(Table12[[#This Row],[Net-zero target status]]<=1,"",IF(Table12[[#This Row],[NZ GHG year]]="","",1000000000*(Table12[[#This Row],[residual LULUCF emissions in 2050]]-Table12[[#This Row],[GHG emissions excl LULUCF]])/(Table12[[#This Row],[NZ GHG year]]-2021)/Table12[[#This Row],[Population]])) | AH34: =IF(Table12[[#This Row],[Peak revised]]="Yes",IF(Table12[[#This Row],[Net-zero target status]]<=1,"",IF(Table12[[#This Row],[NZ GHG year]]="","",1000000000*(Table12[[#This Row],[residual LULUCF emissions in 2050]]-Table12[[#This Row],[GHG emissions excl LULUCF]])/(Table12[[#This Row],[NZ GHG year]]-2021)/Table12[[#This Row],[Population]])),"") | AI34: =MAX(0,(1000000*(Table12[[#This Row],[Current Policies 2030 excl LULUCF]]/2+Table12[[#This Row],[GHG emissions excl LULUCF]]/2)/Table12[[#This Row],[Population]]-$AI$8)*10)*$AI$10 -> 0 | AJ34: =IF(Table12[[#This Row],[Peak revised]]="No",IF(Table12[[#This Row],[Net-zero target status]]<=1,"",IF(Table12[[#This Row],[NZ GHG year]]="","",1000000000*(Table12[[#This Row],[residual LULUCF emissions in 2050]]-Table12[[#This Row],[Current Policies 2030 excl LULUCF]])/(Table12[[#This Row],[NZ GHG year]]-2021)/Table12[[#This Row],[Population]])),"") | AK34: =IF(Table12[[#This Row],[Formule no Peak (2)]]="","",Table12[[#This Row],[Penalty (1)]]+Table12[[#This Row],[Formule no Peak (2)]]) | AL34: =(Table12[[#This Row],[Current Policies 2030 excl LULUCF]]-Table12[[#This Row],[GHG emissions excl LULUCF]])/(2030-2021)/Table12[[#This Row],[GHG emissions excl LULUCF]] -> #DIV/0! | AM34: =IF(Table12[[#This Row],[Net-zero target status]]<=1,"",IF(Table12[[#This Row],[NZ GHG year]]="","",(Table12[[#This Row],[residual LULUCF emissions in 2050]]-Table12[[#This Row],[Current Policies 2030 excl LULUCF]])/(Table12[[#This Row],[NZ GHG year]]-2030)/Table12[[#This Row],[Current Policies 2030 excl LULUCF]])) | AN34: =IF(Table12[[#This Row],[Net-zero target status]]<=1,"",IF(Table12[[#This Row],[NZ GHG year]]="","",(Table12[[#This Row],[residual LULUCF emissions in 2050]]-Table12[[#This Row],[GHG emissions excl LULUCF]])/(Table12[[#This Row],[NZ GHG year]]-2021)/Table12[[#This Row],[GHG emissions excl LULUCF]])) | AO34: =IF(Table12[[#This Row],[Net-zero target status]]<=1,"",IF(Table12[[#This Row],[NZ GHG year]]="","",(Table12[[#This Row],[residual LULUCF emissions in 2050]]-Table12[[#This Row],[2030 conditional NDCs]])/(Table12[[#This Row],[NZ GHG year]]-2030)/Table12[[#This Row],[2030 conditional NDCs]])) | AP34: =MAX('input site'!AH34:AS34) -> 0 | AQ34: =IF(Table12[[#This Row],[Current Policies 2030 incl LULUCF]]>Table12[[#This Row],[Maximum inventory data]],"No","Yes") -> Yes | AR34: =IF(Table12[[#This Row],[Net-zero target status]]>=1.5,Table12[[#This Row],[residual LULUCF emissions in 2050]]/Table12[[#This Row],[GHG emissions excl LULUCF]],"") | AS34: ='input site'!BE34 | AU34: ='input site'!BG34 | AW34: =IF(Table12[[#This Row],[2030 unconditional NDCs]]="","",IF(F34="incl",Table12[[#This Row],[2030 unconditional NDCs]]-Table12[[#This Row],[LULUCF NDC uncond]],Table12[[#This Row],[2030 unconditional NDCs]])) | AX34: =IF(Table12[[#This Row],[2030 unconditional NDCs2]]="","",IF(F34="incl",Table12[[#This Row],[2030 unconditional NDCs2]]-Table12[[#This Row],[LULUCF NDC uncond]],Table12[[#This Row],[2030 unconditional NDCs2]])) | AY34: =IF(Table12[[#This Row],[2030 conditional NDCs]]="","",IF(F34="incl",Table12[[#This Row],[2030 conditional NDCs]]-Table12[[#This Row],[LULUCF NDC cond]],Table12[[#This Row],[2030 conditional NDCs]])) | AZ34: =IF(Table12[[#This Row],[2030 conditional NDCs2]]="","",IF(F34="incl",Table12[[#This Row],[2030 conditional NDCs2]]-Table12[[#This Row],[LULUCF NDC cond]],Table12[[#This Row],[2030 conditional NDCs2]])) | BA34: =VLOOKUP($G34,'Population90 20'!$C$6:$AU$231,37,FALSE) -> 61939 | BB34: =VLOOKUP($G34,'Overview GDP (PPP)'!$C$6:$AI$231,33,FALSE) -> 3331135.6 | BC34: =Table12[[#This Row],[Income]]/Table12[[#This Row],[Population]] -> 53.780907 | BD34: =Table12[[#This Row],[GHG emissions excl LULUCF]]*1000000/Table12[[#This Row],[Population]] -> 0 | BE34: =VLOOKUP($G34,EGR2023_MASTER!$B$4:$S$38,14,FALSE) -> #N/A | BF34: =VLOOKUP($G34,EGR2023_MASTER!$B$4:$S$38,15,FALSE) -> #N/A | BG34: =VLOOKUP($G34,EGR2023_MASTER!$B$4:$S$38,16,FALSE) -> #N/A | BH34: =IF(AND(BE34="Y",AND(BF34="credible",BG34="Y")),"higher",IF(BG34="Y","lower",IF(AND(BG34="N",OR(BE34="Y",BF34="credible")),"lower","much lower"))) -> #N/A | BI34: =IF(AND($BF34="credible",BG34="Y"),"stronger","weak") -> #N/A | BJ34: =(Table12[[#This Row],[Current Policies 2030 excl LULUCF]]/Table12[[#This Row],[GHG emissions excl LULUCF]])^(1/(2030-2021))-1 -> #DIV/0! | BK34: =IF(Table12[[#This Row],[Net-zero target status]]<=1,"",IF(Table12[[#This Row],[NZ GHG year]]="","",((MAX(Table12[[#This Row],[residual LULUCF emissions in 2050]],0.1)/Table12[[#This Row],[Current Policies 2030 excl LULUCF]])^(1/(Table12[[#This Row],[NZ GHG year]]-2021))-1))) | BL34: =IF(Table12[[#This Row],[Net-zero target status]]<=1,"",IF(Table12[[#This Row],[NZ GHG year]]="","",((MAX(Table12[[#This Row],[residual LULUCF emissions in 2050]],0.1)/Table12[[#This Row],[GHG emissions excl LULUCF]])^(1/(Table12[[#This Row],[NZ GHG year]]-2021))-1))) | BM34: =IF(Table12[[#This Row],[Net-zero target status]]<=1,"",IF(Table12[[#This Row],[NZ GHG year]]="","",((MAX(Table12[[#This Row],[residual LULUCF emissions in 2050]],0.1)/AVERAGE(Table12[[#This Row],[2030 conditional NDCs]:[2030 conditional NDCs2]]))^(1/(Table12[[#This Row],[NZ GHG year]]-2021))-1))) | BR34: Bermuda | BT34: =IF(Table12[[#This Row],[Reduction rate 2021 to NZ target2]]="","",J34*(1+AN34)^(Table12[[#This Row],[NZ GHG year]]-2021))
A35: 0 | B35: 0 | C35: 64 | D35: 18 | E35: 25 | F35: ='input site'!M35 -> excl | G35: BTN | H35: Bhutan | I35: =VLOOKUP($G35,'NZT data'!$B$3:$C$200,2,FALSE) -> 5 | J35: ='input site'!AS35 -> 2.4534623 | K35: ='input site'!BS35 -> 2.9844635 | L35: =IF(I35>=1,O35,K35) -> 0 | M35: =IF(I35>=1,O35,N35) -> 0 | N35: ='input site'!EV35 -> 1.841801 | O35: 0 | P35: =O35-N35 -> -1.841801 | Q35: =IF(I35>=1,O35,R35) -> 0 | R35: ='input site'!EZ35 -> 0.77188304 | S35: ='input site'!FA35 -> 0 | T35: =Table12[[#This Row],[(Mt CO2 equivalent)]] -> Bhutan | U35: =VLOOKUP($G35,'NZT data'!$B$3:$F$200,4,FALSE) -> 2030 | V35: =VLOOKUP($G35,'NZT data'!$B$3:$F$200,5,FALSE) -> 2030 | W35: =-IF('LUC NGHGI'!EC25="",MIN('LUC NGHGI'!DW25,0.1),MIN('LUC NGHGI'!EC25,0.1)) -> 7.255 | X35: ='LUC NGHGI'!EC25 -> -7.255 | Y35: ='LUC NGHGI'!DY25 -> -9.3776939 | Z35: ='LUC NGHGI'!DZ25 -> -9.3776939 | AA35: =Table12[[#This Row],[2021 emissions]] -> 2.4534623 | AB35: ='LUC NGHGI'!DW25 -> -9.5715552 | AC35: =IF(F35="incl",Table12[[#This Row],[GHG emissions incl LULUCF]]-Table12[[#This Row],[LULUCF emis-sions in 20213]],Table12[[#This Row],[GHG emissions incl LULUCF]]) -> 2.4534623 | AD35: ='input site'!BS35 -> 2.9844635 | AE35: ='LUC NGHGI'!EH25 -> -10.049063 | AF35: =IF(F35="incl",Table12[[#This Row],[Current Policies 2030 incl LULUCF]]-Table12[[#This Row],[LULUCF CurPol 2030]],Table12[[#This Row],[Current Policies 2030 incl LULUCF]]) -> 2.9844635 | AG35: =IF(Table12[[#This Row],[Net-zero target status]]<=1,"",IF(Table12[[#This Row],[NZ GHG year]]="","",1000000000*(Table12[[#This Row],[residual LULUCF emissions in 2050]]-Table12[[#This Row],[GHG emissions excl LULUCF]])/(Table12[[#This Row],[NZ GHG year]]-2021)/Table12[[#This Row],[Population]])) -> 677.08647 | AH35: =IF(Table12[[#This Row],[Peak revised]]="Yes",IF(Table12[[#This Row],[Net-zero target status]]<=1,"",IF(Table12[[#This Row],[NZ GHG year]]="","",1000000000*(Table12[[#This Row],[residual LULUCF emissions in 2050]]-Table12[[#This Row],[GHG emissions excl LULUCF]])/(Table12[[#This Row],[NZ GHG year]]-2021)/Table12[[#This Row],[Population]])),"") | AI35: =MAX(0,(1000000*(Table12[[#This Row],[Current Policies 2030 excl LULUCF]]/2+Table12[[#This Row],[GHG emissions excl LULUCF]]/2)/Table12[[#This Row],[Population]]-$AI$8)*10)*$AI$10 -> 0 | AJ35: =IF(Table12[[#This Row],[Peak revised]]="No",IF(Table12[[#This Row],[Net-zero target status]]<=1,"",IF(Table12[[#This Row],[NZ GHG year]]="","",1000000000*(Table12[[#This Row],[residual LULUCF emissions in 2050]]-Table12[[#This Row],[Current Policies 2030 excl LULUCF]])/(Table12[[#This Row],[NZ GHG year]]-2021)/Table12[[#This Row],[Population]])),"") -> 602.2076 | AK35: =IF(Table12[[#This Row],[Formule no Peak (2)]]="","",Table12[[#This Row],[Penalty (1)]]+Table12[[#This Row],[Formule no Peak (2)]]) -> 602.2076 | AL35: =(Table12[[#This Row],[Current Policies 2030 excl LULUCF]]-Table12[[#This Row],[GHG emissions excl LULUCF]])/(2030-2021)/Table12[[#This Row],[GHG emissions excl LULUCF]] -> 0.024047702 | AM35: =IF(Table12[[#This Row],[Net-zero target status]]<=1,"",IF(Table12[[#This Row],[NZ GHG year]]="","",(Table12[[#This Row],[residual LULUCF emissions in 2050]]-Table12[[#This Row],[Current Policies 2030 excl LULUCF]])/(Table12[[#This Row],[NZ GHG year]]-2030)/Table12[[#This Row],[Current Policies 2030 excl LULUCF]])) -> #DIV/0! | AN35: =IF(Table12[[#This Row],[Net-zero target status]]<=1,"",IF(Table12[[#This Row],[NZ GHG year]]="","",(Table12[[#This Row],[residual LULUCF emissions in 2050]]-Table12[[#This Row],[GHG emissions excl LULUCF]])/(Table12[[#This Row],[NZ GHG year]]-2021)/Table12[[#This Row],[GHG emissions excl LULUCF]])) -> 0.21744952 | AO35: =IF(Table12[[#This Row],[Net-zero target status]]<=1,"",IF(Table12[[#This Row],[NZ GHG year]]="","",(Table12[[#This Row],[residual LULUCF emissions in 2050]]-Table12[[#This Row],[2030 conditional NDCs]])/(Table12[[#This Row],[NZ GHG year]]-2030)/Table12[[#This Row],[2030 conditional NDCs]])) -> #VALUE! | AP35: =MAX('input site'!AH35:AS35) -> 2.8309242 | AQ35: =IF(Table12[[#This Row],[Current Policies 2030 incl LULUCF]]>Table12[[#This Row],[Maximum inventory data]],"No","Yes") -> No | AR35: =IF(Table12[[#This Row],[Net-zero target status]]>=1.5,Table12[[#This Row],[residual LULUCF emissions in 2050]]/Table12[[#This Row],[GHG emissions excl LULUCF]],"") -> 2.9570456 | AS35: ='input site'!BE35 | AU35: ='input site'!BG35 | AW35: =IF(Table12[[#This Row],[2030 unconditional NDCs]]="","",IF(F35="incl",Table12[[#This Row],[2030 unconditional NDCs]]-Table12[[#This Row],[LULUCF NDC uncond]],Table12[[#This Row],[2030 unconditional NDCs]])) | AX35: =IF(Table12[[#This Row],[2030 unconditional NDCs2]]="","",IF(F35="incl",Table12[[#This Row],[2030 unconditional NDCs2]]-Table12[[#This Row],[LULUCF NDC uncond]],Table12[[#This Row],[2030 unconditional NDCs2]])) | AY35: =IF(Table12[[#This Row],[2030 conditional NDCs]]="","",IF(F35="incl",Table12[[#This Row],[2030 conditional NDCs]]-Table12[[#This Row],[LULUCF NDC cond]],Table12[[#This Row],[2030 conditional NDCs]])) | AZ35: =IF(Table12[[#This Row],[2030 conditional NDCs2]]="","",IF(F35="incl",Table12[[#This Row],[2030 conditional NDCs2]]-Table12[[#This Row],[LULUCF NDC cond]],Table12[[#This Row],[2030 conditional NDCs2]])) | BA35: =VLOOKUP($G35,'Population90 20'!$C$6:$AU$231,37,FALSE) -> 787941 | BB35: =VLOOKUP($G35,'Overview GDP (PPP)'!$C$6:$AI$231,33,FALSE) -> 7051944.2 | BC35: =Table12[[#This Row],[Income]]/Table12[[#This Row],[Population]] -> 8.9498379 | BD35: =Table12[[#This Row],[GHG emissions excl LULUCF]]*1000000/Table12[[#This Row],[Population]] -> 3.113764 | BE35: =VLOOKUP($G35,EGR2023_MASTER!$B$4:$S$38,14,FALSE) -> #N/A | BF35: =VLOOKUP($G35,EGR2023_MASTER!$B$4:$S$38,15,FALSE) -> #N/A | BG35: =VLOOKUP($G35,EGR2023_MASTER!$B$4:$S$38,16,FALSE) -> #N/A | BH35: =IF(AND(BE35="Y",AND(BF35="credible",BG35="Y")),"higher",IF(BG35="Y","lower",IF(AND(BG35="N",OR(BE35="Y",BF35="credible")),"lower","much lower"))) -> #N/A | BI35: =IF(AND($BF35="credible",BG35="Y"),"stronger","weak") -> #N/A | BJ35: =(Table12[[#This Row],[Current Policies 2030 excl LULUCF]]/Table12[[#This Row],[GHG emissions excl LULUCF]])^(1/(2030-2021))-1 -> 0.022007535 | BK35: =IF(Table12[[#This Row],[Net-zero target status]]<=1,"",IF(Table12[[#This Row],[NZ GHG year]]="","",((MAX(Table12[[#This Row],[residual LULUCF emissions in 2050]],0.1)/Table12[[#This Row],[Current Policies 2030 excl LULUCF]])^(1/(Table12[[#This Row],[NZ GHG year]]-2021))-1))) -> 0.10373156 | BL35: =IF(Table12[[#This Row],[Net-zero target status]]<=1,"",IF(Table12[[#This Row],[NZ GHG year]]="","",((MAX(Table12[[#This Row],[residual LULUCF emissions in 2050]],0.1)/Table12[[#This Row],[GHG emissions excl LULUCF]])^(1/(Table12[[#This Row],[NZ GHG year]]-2021))-1))) -> 0.12802197 | BM35: =IF(Table12[[#This Row],[Net-zero target status]]<=1,"",IF(Table12[[#This Row],[NZ GHG year]]="","",((MAX(Table12[[#This Row],[residual LULUCF emissions in 2050]],0.1)/AVERAGE(Table12[[#This Row],[2030 conditional NDCs]:[2030 conditional NDCs2]]))^(1/(Table12[[#This Row],[NZ GHG year]]-2021))-1))) -> #DIV/0! | BR35: Bhutan | BT35: =IF(Table12[[#This Row],[Reduction rate 2021 to NZ target2]]="","",J35*(1+AN35)^(Table12[[#This Row],[NZ GHG year]]-2021)) -> 14.415776
A36: 0 | B36: 0 | C36: 68 | D36: 19 | E36: 6 | F36: ='input site'!M36 -> excl | G36: BOL | H36: Bolivia | I36: =VLOOKUP($G36,'NZT data'!$B$3:$C$200,2,FALSE) -> 0 | J36: ='input site'!AS36 -> 92.235589 | K36: ='input site'!BS36 -> 102.51497 | L36: =IF(I36>=1,O36,K36) -> 102.51497 | M36: =IF(I36>=1,O36,N36) -> 52.582733 | N36: ='input site'!EV36 -> 52.582733 | Q36: =IF(I36>=1,O36,R36) -> 31.109327 | R36: ='input site'!EZ36 -> 31.109327 | S36: ='input site'!FA36 -> 0 | T36: =Table12[[#This Row],[(Mt CO2 equivalent)]] -> Bolivia | U36: 2100 | V36: 2100 | W36: =-IF('LUC NGHGI'!EC26="",MIN('LUC NGHGI'!DW26,0.1),MIN('LUC NGHGI'!EC26,0.1)) -> 16.428556 | X36: ='LUC NGHGI'!EC26 -> -16.428556 | Y36: ='LUC NGHGI'!DY26 -> -55.428556 | Z36: ='LUC NGHGI'!DZ26 -> -55.428556 | AA36: =Table12[[#This Row],[2021 emissions]] -> 92.235589 | AB36: ='LUC NGHGI'!DW26 -> -16.61433 | AC36: =IF(F36="incl",Table12[[#This Row],[GHG emissions incl LULUCF]]-Table12[[#This Row],[LULUCF emis-sions in 20213]],Table12[[#This Row],[GHG emissions incl LULUCF]]) -> 92.235589 | AD36: ='input site'!BS36 -> 102.51497 | AE36: ='LUC NGHGI'!EH26 -> -20.676427 | AF36: =IF(F36="incl",Table12[[#This Row],[Current Policies 2030 incl LULUCF]]-Table12[[#This Row],[LULUCF CurPol 2030]],Table12[[#This Row],[Current Policies 2030 incl LULUCF]]) -> 102.51497 | AG36: =IF(Table12[[#This Row],[Net-zero target status]]<=1,"",IF(Table12[[#This Row],[NZ GHG year]]="","",1000000000*(Table12[[#This Row],[residual LULUCF emissions in 2050]]-Table12[[#This Row],[GHG emissions excl LULUCF]])/(Table12[[#This Row],[NZ GHG year]]-2021)/Table12[[#This Row],[Population]])) | AH36: =IF(Table12[[#This Row],[Peak revised]]="Yes",IF(Table12[[#This Row],[Net-zero target status]]<=1,"",IF(Table12[[#This Row],[NZ GHG year]]="","",1000000000*(Table12[[#This Row],[residual LULUCF emissions in 2050]]-Table12[[#This Row],[GHG emissions excl LULUCF]])/(Table12[[#This Row],[NZ GHG year]]-2021)/Table12[[#This Row],[Population]])),"") | AI36: =MAX(0,(1000000*(Table12[[#This Row],[Current Policies 2030 excl LULUCF]]/2+Table12[[#This Row],[GHG emissions excl LULUCF]]/2)/Table12[[#This Row],[Population]]-$AI$8)*10)*$AI$10 -> -111.95756 | AJ36: =IF(Table12[[#This Row],[Peak revised]]="No",IF(Table12[[#This Row],[Net-zero target status]]<=1,"",IF(Table12[[#This Row],[NZ GHG year]]="","",1000000000*(Table12[[#This Row],[residual LULUCF emissions in 2050]]-Table12[[#This Row],[Current Policies 2030 excl LULUCF]])/(Table12[[#This Row],[NZ GHG year]]-2021)/Table12[[#This Row],[Population]])),"") | AK36: =IF(Table12[[#This Row],[Formule no Peak (2)]]="","",Table12[[#This Row],[Penalty (1)]]+Table12[[#This Row],[Formule no Peak (2)]]) | AL36: =(Table12[[#This Row],[Current Policies 2030 excl LULUCF]]-Table12[[#This Row],[GHG emissions excl LULUCF]])/(2030-2021)/Table12[[#This Row],[GHG emissions excl LULUCF]] -> 0.012382997 | AM36: =IF(Table12[[#This Row],[Net-zero target status]]<=1,"",IF(Table12[[#This Row],[NZ GHG year]]="","",(Table12[[#This Row],[residual LULUCF emissions in 2050]]-Table12[[#This Row],[Current Policies 2030 excl LULUCF]])/(Table12[[#This Row],[NZ GHG year]]-2030)/Table12[[#This Row],[Current Policies 2030 excl LULUCF]])) | AN36: =IF(Table12[[#This Row],[Net-zero target status]]<=1,"",IF(Table12[[#This Row],[NZ GHG year]]="","",(Table12[[#This Row],[residual LULUCF emissions in 2050]]-Table12[[#This Row],[GHG emissions excl LULUCF]])/(Table12[[#This Row],[NZ GHG year]]-2021)/Table12[[#This Row],[GHG emissions excl LULUCF]])) | AO36: =IF(Table12[[#This Row],[Net-zero target status]]<=1,"",IF(Table12[[#This Row],[NZ GHG year]]="","",(Table12[[#This Row],[residual LULUCF emissions in 2050]]-Table12[[#This Row],[2030 conditional NDCs]])/(Table12[[#This Row],[NZ GHG year]]-2030)/Table12[[#This Row],[2030 conditional NDCs]])) | AP36: =MAX('input site'!AH36:AS36) -> 92.235589 | AQ36: =IF(Table12[[#This Row],[Current Policies 2030 incl LULUCF]]>Table12[[#This Row],[Maximum inventory data]],"No","Yes") -> No | AR36: =IF(Table12[[#This Row],[Net-zero target status]]>=1.5,Table12[[#This Row],[residual LULUCF emissions in 2050]]/Table12[[#This Row],[GHG emissions excl LULUCF]],"") | AS36: ='input site'!BE36 | AU36: ='input site'!BG36 | AW36: =IF(Table12[[#This Row],[2030 unconditional NDCs]]="","",IF(F36="incl",Table12[[#This Row],[2030 unconditional NDCs]]-Table12[[#This Row],[LULUCF NDC uncond]],Table12[[#This Row],[2030 unconditional NDCs]])) | AX36: =IF(Table12[[#This Row],[2030 unconditional NDCs2]]="","",IF(F36="incl",Table12[[#This Row],[2030 unconditional NDCs2]]-Table12[[#This Row],[LULUCF NDC uncond]],Table12[[#This Row],[2030 unconditional NDCs2]])) | AY36: =IF(Table12[[#This Row],[2030 conditional NDCs]]="","",IF(F36="incl",Table12[[#This Row],[2030 conditional NDCs]]-Table12[[#This Row],[LULUCF NDC cond]],Table12[[#This Row],[2030 conditional NDCs]])) | AZ36: =IF(Table12[[#This Row],[2030 conditional NDCs2]]="","",IF(F36="incl",Table12[[#This Row],[2030 conditional NDCs2]]-Table12[[#This Row],[LULUCF NDC cond]],Table12[[#This Row],[2030 conditional NDCs2]])) | BA36: =VLOOKUP($G36,'Population90 20'!$C$6:$AU$231,37,FALSE) -> 11992656 | BB36: =VLOOKUP($G36,'Overview GDP (PPP)'!$C$6:$AI$231,33,FALSE) -> 79313578 | BC36: =Table12[[#This Row],[Income]]/Table12[[#This Row],[Population]] -> 6.6135123 | BD36: =Table12[[#This Row],[GHG emissions excl LULUCF]]*1000000/Table12[[#This Row],[Population]] -> 7.691006 | BE36: =VLOOKUP($G36,EGR2023_MASTER!$B$4:$S$38,14,FALSE) -> #N/A | BF36: =VLOOKUP($G36,EGR2023_MASTER!$B$4:$S$38,15,FALSE) -> #N/A | BG36: =VLOOKUP($G36,EGR2023_MASTER!$B$4:$S$38,16,FALSE) -> #N/A | BH36: =IF(AND(BE36="Y",AND(BF36="credible",BG36="Y")),"higher",IF(BG36="Y","lower",IF(AND(BG36="N",OR(BE36="Y",BF36="credible")),"lower","much lower"))) -> #N/A | BI36: =IF(AND($BF36="credible",BG36="Y"),"stronger","weak") -> #N/A | BJ36: =(Table12[[#This Row],[Current Policies 2030 excl LULUCF]]/Table12[[#This Row],[GHG emissions excl LULUCF]])^(1/(2030-2021))-1 -> 0.011809493 | BK36: =IF(Table12[[#This Row],[Net-zero target status]]<=1,"",IF(Table12[[#This Row],[NZ GHG year]]="","",((MAX(Table12[[#This Row],[residual LULUCF emissions in 2050]],0.1)/Table12[[#This Row],[Current Policies 2030 excl LULUCF]])^(1/(Table12[[#This Row],[NZ GHG year]]-2021))-1))) | BL36: =IF(Table12[[#This Row],[Net-zero target status]]<=1,"",IF(Table12[[#This Row],[NZ GHG year]]="","",((MAX(Table12[[#This Row],[residual LULUCF emissions in 2050]],0.1)/Table12[[#This Row],[GHG emissions excl LULUCF]])^(1/(Table12[[#This Row],[NZ GHG year]]-2021))-1))) | BM36: =IF(Table12[[#This Row],[Net-zero target status]]<=1,"",IF(Table12[[#This Row],[NZ GHG year]]="","",((MAX(Table12[[#This Row],[residual LULUCF emissions in 2050]],0.1)/AVERAGE(Table12[[#This Row],[2030 conditional NDCs]:[2030 conditional NDCs2]]))^(1/(Table12[[#This Row],[NZ GHG year]]-2021))-1))) | BR36: Bolivia | BT36: =IF(Table12[[#This Row],[Reduction rate 2021 to NZ target2]]="","",J36*(1+AN36)^(Table12[[#This Row],[NZ GHG year]]-2021))
